Workbook

Sheet Dashboard
B12: Australia | G12: =_xlfn.XLOOKUP($B$12,qry_Master_Clean__2[Country],qry_Master_Clean__2[GDP per Capita (US$)]) -> 64595.588 | M12: =_xlfn.XLOOKUP($B$12,qry_Master_Clean__2[Country],qry_Master_Clean__2[Emissions Per Capita (tonnes per person)]) -> 14.218102 | S12: {=_xlfn.XLOOKUP($B$12,qry_Master_Clean__2[Country],qry_Master_Clean__2[Renewalble]/100)} -> 0.123
B103: What-If Analysis:
B104: Current Renewable Share | G104: 0.286
B105: Increase (%) | G105: +10 percentage points
B106: New Renewable Share | G106: 0.386
B107: Cuarrent CO₂ per Capita | G107: =Calculations!B4 -> 3.7043236 | H107: tonnes/person
B108: Estimated CO₂ per Capita | G108: =(-0.0958 * 38.6 + 7.2488) -> 3.55092 | H108: tonnes/person
B109: Estimated CO₂ Reduction | G109: =(G108-G107) -> -0.15340355 | H109: tonnes/person

Sheet qry_Master_Clean (2)
A1: Country | B1: Population_Millions | C1: GDP_Billions | D1: Land_Area_Sq_Km | E1: Energy_QuadBTU | F1: CO2_Tonnes | G1: GDP per Capita (US$) | H1: Energy Consumption per Capita (QuadBTU per million people) | I1: Income Group | J1: CO₂ Tonnes per Billion GDP | K1: Renewalble | L1: Emissions Per Capita (tonnes per person) | N1: CO₂ Emissions (Tonnes per US$1 Billion GDP)
A2: Afghanistan | B2: 42.6 | C2: 17.2 | D2: 652230 | E2: 0.13461777 | F2: 10825998 | G2: =(qry_Master_Clean__2[[#This Row],[GDP_Billions]]*1000/qry_Master_Clean__2[[#This Row],[Population_Millions]]) -> 403.75587 | H2: =IF(qry_Master_Clean__2[[#This Row],[Population_Millions]]=0,"",qry_Master_Clean__2[[#This Row],[Energy_QuadBTU]]/qry_Master_Clean__2[[#This Row],[Population_Millions]]) -> 0.0031600415 | I2: =_xlfn.XLOOKUP(qry_Master_Clean__2[[#This Row],[Country]],Metadata!$E:$E,Metadata!$C:$C,"Not Found") -> Low income | J2: =(F2/C2) -> 629418.49 | K2: =_xlfn.XLOOKUP( qry_Master_Clean__2[[#This Row],[Country]], Renewable!$A$2:$A$267, Renewable!$BN$2:$BN$267, "" ) -> 20 | L2: =qry_Master_Clean__2[[#This Row],[CO2_Tonnes]]/(qry_Master_Clean__2[[#This Row],[Population_Millions]]*1000000) -> 0.25413141
A3: Albania | B3: 2.4 | C3: 27 | D3: 27400 | E3: 0.087328996 | F3: 4444448 | G3: =(qry_Master_Clean__2[[#This Row],[GDP_Billions]]*1000/qry_Master_Clean__2[[#This Row],[Population_Millions]]) -> 11250 | H3: =IF(qry_Master_Clean__2[[#This Row],[Population_Millions]]=0,"",qry_Master_Clean__2[[#This Row],[Energy_QuadBTU]]/qry_Master_Clean__2[[#This Row],[Population_Millions]]) -> 0.036387082 | I3: =_xlfn.XLOOKUP(qry_Master_Clean__2[[#This Row],[Country]],Metadata!$E:$E,Metadata!$C:$C,"Not Found") -> Upper middle income | J3: =(F3/C3) -> 164609.19 | K3: =_xlfn.XLOOKUP( qry_Master_Clean__2[[#This Row],[Country]], Renewable!$A$2:$A$267, Renewable!$BN$2:$BN$267, "" ) -> 41.9 | L3: =qry_Master_Clean__2[[#This Row],[CO2_Tonnes]]/(qry_Master_Clean__2[[#This Row],[Population_Millions]]*1000000) -> 1.8518533
A4: Algeria | B4: 46.8 | C4: 269.3 | D4: 2381740 | E4: 2.8879649 | F4: 198203180 | G4: =(qry_Master_Clean__2[[#This Row],[GDP_Billions]]*1000/qry_Master_Clean__2[[#This Row],[Population_Millions]]) -> 5754.2735 | H4: =IF(qry_Master_Clean__2[[#This Row],[Population_Millions]]=0,"",qry_Master_Clean__2[[#This Row],[Energy_QuadBTU]]/qry_Master_Clean__2[[#This Row],[Population_Millions]]) -> 0.061708652 | I4: =_xlfn.XLOOKUP(qry_Master_Clean__2[[#This Row],[Country]],Metadata!$E:$E,Metadata!$C:$C,"Not Found") -> Upper middle income | J4: =(F4/C4) -> 735993.98 | K4: =_xlfn.XLOOKUP( qry_Master_Clean__2[[#This Row],[Country]], Renewable!$A$2:$A$267, Renewable!$BN$2:$BN$267, "" ) -> 0.1 | L4: =qry_Master_Clean__2[[#This Row],[CO2_Tonnes]]/(qry_Master_Clean__2[[#This Row],[Population_Millions]]*1000000) -> 4.2351107
A5: American Samoa | B5: 0 | C5: 0.9 | D5: 200 | E5: 0.0079105991 | F5: 0 | G5: =(qry_Master_Clean__2[[#This Row],[GDP_Billions]]*1000/qry_Master_Clean__2[[#This Row],[Population_Millions]]) -> #DIV/0! | H5: =IF(qry_Master_Clean__2[[#This Row],[Population_Millions]]=0,"",qry_Master_Clean__2[[#This Row],[Energy_QuadBTU]]/qry_Master_Clean__2[[#This Row],[Population_Millions]]) | I5: =_xlfn.XLOOKUP(qry_Master_Clean__2[[#This Row],[Country]],Metadata!$E:$E,Metadata!$C:$C,"Not Found") -> High income | J5: =(qry_Master_Clean__2[[#This Row],[CO2_Tonnes]]/(qry_Master_Clean__2[[#This Row],[GDP_Billions]]/1000000000)) -> 0 | K5: =_xlfn.XLOOKUP( qry_Master_Clean__2[[#This Row],[Country]], Renewable!$A$2:$A$267, Renewable!$BN$2:$BN$267, "" ) -> 0.4 | L5: =qry_Master_Clean__2[[#This Row],[CO2_Tonnes]]/(qry_Master_Clean__2[[#This Row],[Population_Millions]]*1000000) -> #DIV/0!
A6: Andorra | B6: 0.1 | C6: 4 | D6: 470 | E6: 0 | F6: 424663 | G6: =(qry_Master_Clean__2[[#This Row],[GDP_Billions]]*1000/qry_Master_Clean__2[[#This Row],[Population_Millions]]) -> 40000 | H6: =IF(qry_Master_Clean__2[[#This Row],[Population_Millions]]=0,"",qry_Master_Clean__2[[#This Row],[Energy_QuadBTU]]/qry_Master_Clean__2[[#This Row],[Population_Millions]]) -> 0 | I6: =_xlfn.XLOOKUP(qry_Master_Clean__2[[#This Row],[Country]],Metadata!$E:$E,Metadata!$C:$C,"Not Found") -> High income | J6: =(F6/C6) -> 106165.75 | K6: =_xlfn.XLOOKUP( qry_Master_Clean__2[[#This Row],[Country]], Renewable!$A$2:$A$267, Renewable!$BN$2:$BN$267, "" ) -> 18.4 | L6: =qry_Master_Clean__2[[#This Row],[CO2_Tonnes]]/(qry_Master_Clean__2[[#This Row],[Population_Millions]]*1000000) -> 4.24663
A7: Angola | B7: 37.9 | C7: 101 | D7: 1246700 | E7: 0.34382359 | F7: 22333584 | G7: =(qry_Master_Clean__2[[#This Row],[GDP_Billions]]*1000/qry_Master_Clean__2[[#This Row],[Population_Millions]]) -> 2664.9077 | H7: =IF(qry_Master_Clean__2[[#This Row],[Population_Millions]]=0,"",qry_Master_Clean__2[[#This Row],[Energy_QuadBTU]]/qry_Master_Clean__2[[#This Row],[Population_Millions]]) -> 0.0090718625 | I7: =_xlfn.XLOOKUP(qry_Master_Clean__2[[#This Row],[Country]],Metadata!$E:$E,Metadata!$C:$C,"Not Found") -> Lower middle income | J7: =(F7/C7) -> 221124.59 | K7: =_xlfn.XLOOKUP( qry_Master_Clean__2[[#This Row],[Country]], Renewable!$A$2:$A$267, Renewable!$BN$2:$BN$267, "" ) -> 52.9 | L7: =qry_Master_Clean__2[[#This Row],[CO2_Tonnes]]/(qry_Master_Clean__2[[#This Row],[Population_Millions]]*1000000) -> 0.58927662
A8: Antigua and Barbuda | B8: 0.1 | C8: 2.2 | D8: 440 | E8: 0.010637457 | F8: 665140 | G8: =(qry_Master_Clean__2[[#This Row],[GDP_Billions]]*1000/qry_Master_Clean__2[[#This Row],[Population_Millions]]) -> 22000 | H8: =IF(qry_Master_Clean__2[[#This Row],[Population_Millions]]=0,"",qry_Master_Clean__2[[#This Row],[Energy_QuadBTU]]/qry_Master_Clean__2[[#This Row],[Population_Millions]]) -> 0.10637457 | I8: =_xlfn.XLOOKUP(qry_Master_Clean__2[[#This Row],[Country]],Metadata!$E:$E,Metadata!$C:$C,"Not Found") -> High income | J8: =(F8/C8) -> 302336.36 | K8: =_xlfn.XLOOKUP( qry_Master_Clean__2[[#This Row],[Country]], Renewable!$A$2:$A$267, Renewable!$BN$2:$BN$267, "" ) -> 0.9 | L8: =qry_Master_Clean__2[[#This Row],[CO2_Tonnes]]/(qry_Master_Clean__2[[#This Row],[Population_Millions]]*1000000) -> 6.6514
A9: Argentina | B9: 45.7 | C9: 638.4 | D9: 2736690 | E9: 3.565998 | F9: 171059260 | G9: =(qry_Master_Clean__2[[#This Row],[GDP_Billions]]*1000/qry_Master_Clean__2[[#This Row],[Population_Millions]]) -> 13969.365 | H9: =IF(qry_Master_Clean__2[[#This Row],[Population_Millions]]=0,"",qry_Master_Clean__2[[#This Row],[Energy_QuadBTU]]/qry_Master_Clean__2[[#This Row],[Population_Millions]]) -> 0.078030591 | I9: =_xlfn.XLOOKUP(qry_Master_Clean__2[[#This Row],[Country]],Metadata!$E:$E,Metadata!$C:$C,"Not Found") -> Upper middle income | J9: =(F9/C9) -> 267949.97 | K9: =_xlfn.XLOOKUP( qry_Master_Clean__2[[#This Row],[Country]], Renewable!$A$2:$A$267, Renewable!$BN$2:$BN$267, "" ) -> 9.2 | L9: =qry_Master_Clean__2[[#This Row],[CO2_Tonnes]]/(qry_Master_Clean__2[[#This Row],[Population_Millions]]*1000000) -> 3.743091
A10: Armenia | B10: 3 | C10: 26 | D10: 28197 | E10: 0.16985684 | F10: 7430715 | G10: =(qry_Master_Clean__2[[#This Row],[GDP_Billions]]*1000/qry_Master_Clean__2[[#This Row],[Population_Millions]]) -> 8666.6667 | H10: =IF(qry_Master_Clean__2[[#This Row],[Population_Millions]]=0,"",qry_Master_Clean__2[[#This Row],[Energy_QuadBTU]]/qry_Master_Clean__2[[#This Row],[Population_Millions]]) -> 0.056618947 | I10: =_xlfn.XLOOKUP(qry_Master_Clean__2[[#This Row],[Country]],Metadata!$E:$E,Metadata!$C:$C,"Not Found") -> Upper middle income | J10: =(F10/C10) -> 285796.73 | K10: =_xlfn.XLOOKUP( qry_Master_Clean__2[[#This Row],[Country]], Renewable!$A$2:$A$267, Renewable!$BN$2:$BN$267, "" ) -> 9.1 | L10: =qry_Master_Clean__2[[#This Row],[CO2_Tonnes]]/(qry_Master_Clean__2[[#This Row],[Population_Millions]]*1000000) -> 2.476905
A11: Aruba | B11: 0.1 | C11: 4.3 | D11: 180 | E11: 0.016806703 | F11: 920644 | G11: =(qry_Master_Clean__2[[#This Row],[GDP_Billions]]*1000/qry_Master_Clean__2[[#This Row],[Population_Millions]]) -> 43000 | H11: =IF(qry_Master_Clean__2[[#This Row],[Population_Millions]]=0,"",qry_Master_Clean__2[[#This Row],[Energy_QuadBTU]]/qry_Master_Clean__2[[#This Row],[Population_Millions]]) -> 0.16806703 | I11: =_xlfn.XLOOKUP(qry_Master_Clean__2[[#This Row],[Country]],Metadata!$E:$E,Metadata!$C:$C,"Not Found") -> High income | J11: =(F11/C11) -> 214103.26 | K11: =_xlfn.XLOOKUP( qry_Master_Clean__2[[#This Row],[Country]], Renewable!$A$2:$A$267, Renewable!$BN$2:$BN$267, "" ) -> 8.8 | L11: =qry_Master_Clean__2[[#This Row],[CO2_Tonnes]]/(qry_Master_Clean__2[[#This Row],[Population_Millions]]*1000000) -> 9.20644
A12: Australia | B12: 27.2 | C12: 1757 | D12: 7692020 | E12: 5.9926708 | F12: 386732380 | G12: =(qry_Master_Clean__2[[#This Row],[GDP_Billions]]*1000/qry_Master_Clean__2[[#This Row],[Population_Millions]]) -> 64595.588 | H12: =IF(qry_Master_Clean__2[[#This Row],[Population_Millions]]=0,"",qry_Master_Clean__2[[#This Row],[Energy_QuadBTU]]/qry_Master_Clean__2[[#This Row],[Population_Millions]]) -> 0.22031878 | I12: =_xlfn.XLOOKUP(qry_Master_Clean__2[[#This Row],[Country]],Metadata!$E:$E,Metadata!$C:$C,"Not Found") -> High income | J12: =(F12/C12) -> 220109.49 | K12: =_xlfn.XLOOKUP( qry_Master_Clean__2[[#This Row],[Country]], Renewable!$A$2:$A$267, Renewable!$BN$2:$BN$267, "" ) -> 12.3 | L12: =qry_Master_Clean__2[[#This Row],[CO2_Tonnes]]/(qry_Master_Clean__2[[#This Row],[Population_Millions]]*1000000) -> 14.218102
A13: Austria | B13: 9.2 | C13: 534.8 | D13: 82520 | E13: 1.0674109 | F13: 56367656 | G13: =(qry_Master_Clean__2[[#This Row],[GDP_Billions]]*1000/qry_Master_Clean__2[[#This Row],[Population_Millions]]) -> 58130.435 | H13: =IF(qry_Master_Clean__2[[#This Row],[Population_Millions]]=0,"",qry_Master_Clean__2[[#This Row],[Energy_QuadBTU]]/qry_Master_Clean__2[[#This Row],[Population_Millions]]) -> 0.11602293 | I13: =_xlfn.XLOOKUP(qry_Master_Clean__2[[#This Row],[Country]],Metadata!$E:$E,Metadata!$C:$C,"Not Found") -> High income | J13: =(F13/C13) -> 105399.51 | K13: =_xlfn.XLOOKUP( qry_Master_Clean__2[[#This Row],[Country]], Renewable!$A$2:$A$267, Renewable!$BN$2:$BN$267, "" ) -> 36 | L13: =qry_Master_Clean__2[[#This Row],[CO2_Tonnes]]/(qry_Master_Clean__2[[#This Row],[Population_Millions]]*1000000) -> 6.1269191
A14: Azerbaijan | B14: 10.2 | C14: 74.3 | D14: 82650 | E14: 0.65287564 | F14: 39830140 | G14: =(qry_Master_Clean__2[[#This Row],[GDP_Billions]]*1000/qry_Master_Clean__2[[#This Row],[Population_Millions]]) -> 7284.3137 | H14: =IF(qry_Master_Clean__2[[#This Row],[Population_Millions]]=0,"",qry_Master_Clean__2[[#This Row],[Energy_QuadBTU]]/qry_Master_Clean__2[[#This Row],[Population_Millions]]) -> 0.064007416 | I14: =_xlfn.XLOOKUP(qry_Master_Clean__2[[#This Row],[Country]],Metadata!$E:$E,Metadata!$C:$C,"Not Found") -> Upper middle income | J14: =(F14/C14) -> 536071.87 | K14: =_xlfn.XLOOKUP( qry_Master_Clean__2[[#This Row],[Country]], Renewable!$A$2:$A$267, Renewable!$BN$2:$BN$267, "" ) -> 1.3 | L14: =qry_Master_Clean__2[[#This Row],[CO2_Tonnes]]/(qry_Master_Clean__2[[#This Row],[Population_Millions]]*1000000) -> 3.9049157
A15: Bahamas, The | B15: 0.4 | C15: 15.8 | D15: 10010 | E15: 0 | F15: 0 | G15: =(qry_Master_Clean__2[[#This Row],[GDP_Billions]]*1000/qry_Master_Clean__2[[#This Row],[Population_Millions]]) -> 39500 | H15: =IF(qry_Master_Clean__2[[#This Row],[Population_Millions]]=0,"",qry_Master_Clean__2[[#This Row],[Energy_QuadBTU]]/qry_Master_Clean__2[[#This Row],[Population_Millions]]) -> 0 | I15: =_xlfn.XLOOKUP(qry_Master_Clean__2[[#This Row],[Country]],Metadata!$E:$E,Metadata!$C:$C,"Not Found") -> High income | J15: =(qry_Master_Clean__2[[#This Row],[CO2_Tonnes]]/(qry_Master_Clean__2[[#This Row],[GDP_Billions]]/1000000000)) -> 0 | K15: =_xlfn.XLOOKUP( qry_Master_Clean__2[[#This Row],[Country]], Renewable!$A$2:$A$267, Renewable!$BN$2:$BN$267, "" ) -> 1.1 | L15: =qry_Master_Clean__2[[#This Row],[CO2_Tonnes]]/(qry_Master_Clean__2[[#This Row],[Population_Millions]]*1000000) -> 0
A16: Bahrain | B16: 1.6 | C16: 47.1 | D16: 790 | E16: 0.8337039 | F16: 39003456 | G16: =(qry_Master_Clean__2[[#This Row],[GDP_Billions]]*1000/qry_Master_Clean__2[[#This Row],[Population_Millions]]) -> 29437.5 | H16: =IF(qry_Master_Clean__2[[#This Row],[Population_Millions]]=0,"",qry_Master_Clean__2[[#This Row],[Energy_QuadBTU]]/qry_Master_Clean__2[[#This Row],[Population_Millions]]) -> 0.52106494 | I16: =_xlfn.XLOOKUP(qry_Master_Clean__2[[#This Row],[Country]],Metadata!$E:$E,Metadata!$C:$C,"Not Found") -> High income | J16: =(F16/C16) -> 828098.85 | K16: =_xlfn.XLOOKUP( qry_Master_Clean__2[[#This Row],[Country]], Renewable!$A$2:$A$267, Renewable!$BN$2:$BN$267, "" ) -> 0 | L16: =qry_Master_Clean__2[[#This Row],[CO2_Tonnes]]/(qry_Master_Clean__2[[#This Row],[Population_Millions]]*1000000) -> 24.37716
A17: Korea, Dem. People's Rep. | B17: 26.5 | C17: 0 | D17: 120410 | E17: 0 | F17: 0 | G17: =(qry_Master_Clean__2[[#This Row],[GDP_Billions]]*1000/qry_Master_Clean__2[[#This Row],[Population_Millions]]) -> 0 | H17: =IF(qry_Master_Clean__2[[#This Row],[Population_Millions]]=0,"",qry_Master_Clean__2[[#This Row],[Energy_QuadBTU]]/qry_Master_Clean__2[[#This Row],[Population_Millions]]) -> 0 | I17: =_xlfn.XLOOKUP(qry_Master_Clean__2[[#This Row],[Country]],Metadata!$E:$E,Metadata!$C:$C,"Not Found") -> Low income | J17: =(qry_Master_Clean__2[[#This Row],[CO2_Tonnes]]/(qry_Master_Clean__2[[#This Row],[GDP_Billions]]/1000000000)) -> #DIV/0! | K17: =_xlfn.XLOOKUP( qry_Master_Clean__2[[#This Row],[Country]], Renewable!$A$2:$A$267, Renewable!$BN$2:$BN$267, "" ) -> 14.7 | L17: =qry_Master_Clean__2[[#This Row],[CO2_Tonnes]]/(qry_Master_Clean__2[[#This Row],[Population_Millions]]*1000000) -> 0
A18: Bangladesh | B18: 173.6 | C18: 450.1 | D18: 130170 | E18: 1.9686078 | F18: 108317880 | G18: =(qry_Master_Clean__2[[#This Row],[GDP_Billions]]*1000/qry_Master_Clean__2[[#This Row],[Population_Millions]]) -> 2592.7419 | H18: =IF(qry_Master_Clean__2[[#This Row],[Population_Millions]]=0,"",qry_Master_Clean__2[[#This Row],[Energy_QuadBTU]]/qry_Master_Clean__2[[#This Row],[Population_Millions]]) -> 0.011339906 | I18: =_xlfn.XLOOKUP(qry_Master_Clean__2[[#This Row],[Country]],Metadata!$E:$E,Metadata!$C:$C,"Not Found") -> Lower middle income | J18: =(F18/C18) -> 240652.92 | K18: =_xlfn.XLOOKUP( qry_Master_Clean__2[[#This Row],[Country]], Renewable!$A$2:$A$267, Renewable!$BN$2:$BN$267, "" ) -> 25 | L18: =qry_Master_Clean__2[[#This Row],[CO2_Tonnes]]/(qry_Master_Clean__2[[#This Row],[Population_Millions]]*1000000) -> 0.62395092
A19: Barbados | B19: 0.3 | C19: 7.5 | D19: 430 | E19: 0.023098936 | F19: 1365171 | G19: =(qry_Master_Clean__2[[#This Row],[GDP_Billions]]*1000/qry_Master_Clean__2[[#This Row],[Population_Millions]]) -> 25000 | H19: =IF(qry_Master_Clean__2[[#This Row],[Population_Millions]]=0,"",qry_Master_Clean__2[[#This Row],[Energy_QuadBTU]]/qry_Master_Clean__2[[#This Row],[Population_Millions]]) -> 0.076996454 | I19: =_xlfn.XLOOKUP(qry_Master_Clean__2[[#This Row],[Country]],Metadata!$E:$E,Metadata!$C:$C,"Not Found") -> High income | J19: =(F19/C19) -> 182022.8 | K19: =_xlfn.XLOOKUP( qry_Master_Clean__2[[#This Row],[Country]], Renewable!$A$2:$A$267, Renewable!$BN$2:$BN$267, "" ) -> 5.5 | L19: =qry_Master_Clean__2[[#This Row],[CO2_Tonnes]]/(qry_Master_Clean__2[[#This Row],[Population_Millions]]*1000000) -> 4.55057
A20: Belarus | B20: 9.1 | C20: 76 | D20: 202950 | E20: 0.99457682 | F20: 55818416 | G20: =(qry_Master_Clean__2[[#This Row],[GDP_Billions]]*1000/qry_Master_Clean__2[[#This Row],[Population_Millions]]) -> 8351.6484 | H20: =IF(qry_Master_Clean__2[[#This Row],[Population_Millions]]=0,"",qry_Master_Clean__2[[#This Row],[Energy_QuadBTU]]/qry_Master_Clean__2[[#This Row],[Population_Millions]]) -> 0.10929416 | I20: =_xlfn.XLOOKUP(qry_Master_Clean__2[[#This Row],[Country]],Metadata!$E:$E,Metadata!$C:$C,"Not Found") -> Upper middle income | J20: =(F20/C20) -> 734452.84 | K20: =_xlfn.XLOOKUP( qry_Master_Clean__2[[#This Row],[Country]], Renewable!$A$2:$A$267, Renewable!$BN$2:$BN$267, "" ) -> 8.2 | L20: =qry_Master_Clean__2[[#This Row],[CO2_Tonnes]]/(qry_Master_Clean__2[[#This Row],[Population_Millions]]*1000000) -> 6.1338919
A21: Belgium | B21: 11.9 | C21: 671.4 | D21: 30494 | E21: 2.2828087 | F21: 85456200 | G21: =(qry_Master_Clean__2[[#This Row],[GDP_Billions]]*1000/qry_Master_Clean__2[[#This Row],[Population_Millions]]) -> 56420.168 | H21: =IF(qry_Master_Clean__2[[#This Row],[Population_Millions]]=0,"",qry_Master_Clean__2[[#This Row],[Energy_QuadBTU]]/qry_Master_Clean__2[[#This Row],[Population_Millions]]) -> 0.19183266 | I21: =_xlfn.XLOOKUP(qry_Master_Clean__2[[#This Row],[Country]],Metadata!$E:$E,Metadata!$C:$C,"Not Found") -> High income | J21: =(F21/C21) -> 127280.61 | K21: =_xlfn.XLOOKUP( qry_Master_Clean__2[[#This Row],[Country]], Renewable!$A$2:$A$267, Renewable!$BN$2:$BN$267, "" ) -> 11.7 | L21: =qry_Master_Clean__2[[#This Row],[CO2_Tonnes]]/(qry_Master_Clean__2[[#This Row],[Population_Millions]]*1000000) -> 7.1811933
A22: Belize | B22: 0.4 | C22: 3.2 | D22: 22810 | E22: 0.014390815 | F22: 796027 | G22: =(qry_Master_Clean__2[[#This Row],[GDP_Billions]]*1000/qry_Master_Clean__2[[#This Row],[Population_Millions]]) -> 8000 | H22: =IF(qry_Master_Clean__2[[#This Row],[Population_Millions]]=0,"",qry_Master_Clean__2[[#This Row],[Energy_QuadBTU]]/qry_Master_Clean__2[[#This Row],[Population_Millions]]) -> 0.035977038 | I22: =_xlfn.XLOOKUP(qry_Master_Clean__2[[#This Row],[Country]],Metadata!$E:$E,Metadata!$C:$C,"Not Found") -> Upper middle income | J22: =(F22/C22) -> 248758.44 | K22: =_xlfn.XLOOKUP( qry_Master_Clean__2[[#This Row],[Country]], Renewable!$A$2:$A$267, Renewable!$BN$2:$BN$267, "" ) -> 26.6 | L22: =qry_Master_Clean__2[[#This Row],[CO2_Tonnes]]/(qry_Master_Clean__2[[#This Row],[Population_Millions]]*1000000) -> 1.9900675
A23: Benin | B23: 14.5 | C23: 21.5 | D23: 112760 | E23: 0.10717695 | F23: 6066339 | G23: =(qry_Master_Clean__2[[#This Row],[GDP_Billions]]*1000/qry_Master_Clean__2[[#This Row],[Population_Millions]]) -> 1482.7586 | H23: =IF(qry_Master_Clean__2[[#This Row],[Population_Millions]]=0,"",qry_Master_Clean__2[[#This Row],[Energy_QuadBTU]]/qry_Master_Clean__2[[#This Row],[Population_Millions]]) -> 0.0073915136 | I23: =_xlfn.XLOOKUP(qry_Master_Clean__2[[#This Row],[Country]],Metadata!$E:$E,Metadata!$C:$C,"Not Found") -> Lower middle income | J23: =(F23/C23) -> 282155.3 | K23: =_xlfn.XLOOKUP( qry_Master_Clean__2[[#This Row],[Country]], Renewable!$A$2:$A$267, Renewable!$BN$2:$BN$267, "" ) -> 54.5 | L23: =qry_Master_Clean__2[[#This Row],[CO2_Tonnes]]/(qry_Master_Clean__2[[#This Row],[Population_Millions]]*1000000) -> 0.41836821
A24: Bermuda | B24: 0.1 | C24: 9.2 | D24: 54 | E24: 0.0082251094 | F24: 550001 | G24: =(qry_Master_Clean__2[[#This Row],[GDP_Billions]]*1000/qry_Master_Clean__2[[#This Row],[Population_Millions]]) -> 92000 | H24: =IF(qry_Master_Clean__2[[#This Row],[Population_Millions]]=0,"",qry_Master_Clean__2[[#This Row],[Energy_QuadBTU]]/qry_Master_Clean__2[[#This Row],[Population_Millions]]) -> 0.082251094 | I24: =_xlfn.XLOOKUP(qry_Master_Clean__2[[#This Row],[Country]],Metadata!$E:$E,Metadata!$C:$C,"Not Found") -> High income | J24: =(F24/C24) -> 59782.717 | K24: =_xlfn.XLOOKUP( qry_Master_Clean__2[[#This Row],[Country]], Renewable!$A$2:$A$267, Renewable!$BN$2:$BN$267, "" ) -> 0.9 | L24: =qry_Master_Clean__2[[#This Row],[CO2_Tonnes]]/(qry_Master_Clean__2[[#This Row],[Population_Millions]]*1000000) -> 5.50001
A25: Bhutan | B25: 0.8 | C25: 3 | D25: 38140 | E25: 0.060721214 | F25: 1657416 | G25: =(qry_Master_Clean__2[[#This Row],[GDP_Billions]]*1000/qry_Master_Clean__2[[#This Row],[Population_Millions]]) -> 3750 | H25: =IF(qry_Master_Clean__2[[#This Row],[Population_Millions]]=0,"",qry_Master_Clean__2[[#This Row],[Energy_QuadBTU]]/qry_Master_Clean__2[[#This Row],[Population_Millions]]) -> 0.075901518 | I25: =_xlfn.XLOOKUP(qry_Master_Clean__2[[#This Row],[Country]],Metadata!$E:$E,Metadata!$C:$C,"Not Found") -> Lower middle income | J25: =(F25/C25) -> 552472 | K25: =_xlfn.XLOOKUP( qry_Master_Clean__2[[#This Row],[Country]], Renewable!$A$2:$A$267, Renewable!$BN$2:$BN$267, "" ) -> 81.8 | L25: =qry_Master_Clean__2[[#This Row],[CO2_Tonnes]]/(qry_Master_Clean__2[[#This Row],[Population_Millions]]*1000000) -> 2.07177
A26: Bolivia | B26: 12.4 | C26: 54.9 | D26: 1083300 | E26: 0.39731764 | F26: 28708664 | G26: =(qry_Master_Clean__2[[#This Row],[GDP_Billions]]*1000/qry_Master_Clean__2[[#This Row],[Population_Millions]]) -> 4427.4194 | H26: =IF(qry_Master_Clean__2[[#This Row],[Population_Millions]]=0,"",qry_Master_Clean__2[[#This Row],[Energy_QuadBTU]]/qry_Master_Clean__2[[#This Row],[Population_Millions]]) -> 0.032041745 | I26: =_xlfn.XLOOKUP(qry_Master_Clean__2[[#This Row],[Country]],Metadata!$E:$E,Metadata!$C:$C,"Not Found") -> Lower middle income | J26: =(F26/C26) -> 522926.48 | K26: =_xlfn.XLOOKUP( qry_Master_Clean__2[[#This Row],[Country]], Renewable!$A$2:$A$267, Renewable!$BN$2:$BN$267, "" ) -> 12.8 | L26: =qry_Master_Clean__2[[#This Row],[CO2_Tonnes]]/(qry_Master_Clean__2[[#This Row],[Population_Millions]]*1000000) -> 2.3152148
A27: Bosnia and Herzegovina | B27: 3.2 | C27: 29.6 | D27: 51200 | E27: 0.29860538 | F27: 19425932 | G27: =(qry_Master_Clean__2[[#This Row],[GDP_Billions]]*1000/qry_Master_Clean__2[[#This Row],[Population_Millions]]) -> 9250 | H27: =IF(qry_Master_Clean__2[[#This Row],[Population_Millions]]=0,"",qry_Master_Clean__2[[#This Row],[Energy_QuadBTU]]/qry_Master_Clean__2[[#This Row],[Population_Millions]]) -> 0.093314182 | I27: =_xlfn.XLOOKUP(qry_Master_Clean__2[[#This Row],[Country]],Metadata!$E:$E,Metadata!$C:$C,"Not Found") -> Upper middle income | J27: =(F27/C27) -> 656281.49 | K27: =_xlfn.XLOOKUP( qry_Master_Clean__2[[#This Row],[Country]], Renewable!$A$2:$A$267, Renewable!$BN$2:$BN$267, "" ) -> 36.6 | L27: =qry_Master_Clean__2[[#This Row],[CO2_Tonnes]]/(qry_Master_Clean__2[[#This Row],[Population_Millions]]*1000000) -> 6.0706038
A28: Botswana | B28: 2.5 | C28: 19.4 | D28: 566730 | E28: 0.084397061 | F28: 7461599 | G28: =(qry_Master_Clean__2[[#This Row],[GDP_Billions]]*1000/qry_Master_Clean__2[[#This Row],[Population_Millions]]) -> 7760 | H28: =IF(qry_Master_Clean__2[[#This Row],[Population_Millions]]=0,"",qry_Master_Clean__2[[#This Row],[Energy_QuadBTU]]/qry_Master_Clean__2[[#This Row],[Population_Millions]]) -> 0.033758824 | I28: =_xlfn.XLOOKUP(qry_Master_Clean__2[[#This Row],[Country]],Metadata!$E:$E,Metadata!$C:$C,"Not Found") -> Upper middle income | J28: =(F28/C28) -> 384618.51 | K28: =_xlfn.XLOOKUP( qry_Master_Clean__2[[#This Row],[Country]], Renewable!$A$2:$A$267, Renewable!$BN$2:$BN$267, "" ) -> 27.4 | L28: =qry_Master_Clean__2[[#This Row],[CO2_Tonnes]]/(qry_Master_Clean__2[[#This Row],[Population_Millions]]*1000000) -> 2.9846396
A29: Brazil | B29: 212 | C29: 2185.8 | D29: 8358140 | E29: 10.686541 | F29: 483011550 | G29: =(qry_Master_Clean__2[[#This Row],[GDP_Billions]]*1000/qry_Master_Clean__2[[#This Row],[Population_Millions]]) -> 10310.377 | H29: =IF(qry_Master_Clean__2[[#This Row],[Population_Millions]]=0,"",qry_Master_Clean__2[[#This Row],[Energy_QuadBTU]]/qry_Master_Clean__2[[#This Row],[Population_Millions]]) -> 0.050408213 | I29: =_xlfn.XLOOKUP(qry_Master_Clean__2[[#This Row],[Country]],Metadata!$E:$E,Metadata!$C:$C,"Not Found") -> Upper middle income | J29: =(F29/C29) -> 220977.01 | K29: =_xlfn.XLOOKUP( qry_Master_Clean__2[[#This Row],[Country]], Renewable!$A$2:$A$267, Renewable!$BN$2:$BN$267, "" ) -> 46.5 | L29: =qry_Master_Clean__2[[#This Row],[CO2_Tonnes]]/(qry_Master_Clean__2[[#This Row],[Population_Millions]]*1000000) -> 2.2783564
A30: Brunei Darussalam | B30: 0.5 | C30: 15.3 | D30: 5270 | E30: 0 | F30: 0 | G30: =(qry_Master_Clean__2[[#This Row],[GDP_Billions]]*1000/qry_Master_Clean__2[[#This Row],[Population_Millions]]) -> 30600 | H30: =IF(qry_Master_Clean__2[[#This Row],[Population_Millions]]=0,"",qry_Master_Clean__2[[#This Row],[Energy_QuadBTU]]/qry_Master_Clean__2[[#This Row],[Population_Millions]]) -> 0 | I30: =_xlfn.XLOOKUP(qry_Master_Clean__2[[#This Row],[Country]],Metadata!$E:$E,Metadata!$C:$C,"Not Found") -> High income | J30: =(qry_Master_Clean__2[[#This Row],[CO2_Tonnes]]/(qry_Master_Clean__2[[#This Row],[GDP_Billions]]/1000000000)) -> 0 | K30: =_xlfn.XLOOKUP( qry_Master_Clean__2[[#This Row],[Country]], Renewable!$A$2:$A$267, Renewable!$BN$2:$BN$267, "" ) -> 0 | L30: =qry_Master_Clean__2[[#This Row],[CO2_Tonnes]]/(qry_Master_Clean__2[[#This Row],[Population_Millions]]*1000000) -> 0
A31: Bulgaria | B31: 6.4 | C31: 113.3 | D31: 108560 | E31: 0.64979131 | F31: 31621824 | G31: =(qry_Master_Clean__2[[#This Row],[GDP_Billions]]*1000/qry_Master_Clean__2[[#This Row],[Population_Millions]]) -> 17703.125 | H31: =IF(qry_Master_Clean__2[[#This Row],[Population_Millions]]=0,"",qry_Master_Clean__2[[#This Row],[Energy_QuadBTU]]/qry_Master_Clean__2[[#This Row],[Population_Millions]]) -> 0.10152989 | I31: =_xlfn.XLOOKUP(qry_Master_Clean__2[[#This Row],[Country]],Metadata!$E:$E,Metadata!$C:$C,"Not Found") -> High income | J31: =(F31/C31) -> 279098.18 | K31: =_xlfn.XLOOKUP( qry_Master_Clean__2[[#This Row],[Country]], Renewable!$A$2:$A$267, Renewable!$BN$2:$BN$267, "" ) -> 20.4 | L31: =qry_Master_Clean__2[[#This Row],[CO2_Tonnes]]/(qry_Master_Clean__2[[#This Row],[Population_Millions]]*1000000) -> 4.94091
A32: Burkina Faso | B32: 23.5 | C32: 23.1 | D32: 273600 | E32: 0.085374167 | F32: 6507663 | G32: =(qry_Master_Clean__2[[#This Row],[GDP_Billions]]*1000/qry_Master_Clean__2[[#This Row],[Population_Millions]]) -> 982.97872 | H32: =IF(qry_Master_Clean__2[[#This Row],[Population_Millions]]=0,"",qry_Master_Clean__2[[#This Row],[Energy_QuadBTU]]/qry_Master_Clean__2[[#This Row],[Population_Millions]]) -> 0.0036329433 | I32: =_xlfn.XLOOKUP(qry_Master_Clean__2[[#This Row],[Country]],Metadata!$E:$E,Metadata!$C:$C,"Not Found") -> Low income | J32: =(F32/C32) -> 281717.01 | K32: =_xlfn.XLOOKUP( qry_Master_Clean__2[[#This Row],[Country]], Renewable!$A$2:$A$267, Renewable!$BN$2:$BN$267, "" ) -> 71.2 | L32: =qry_Master_Clean__2[[#This Row],[CO2_Tonnes]]/(qry_Master_Clean__2[[#This Row],[Population_Millions]]*1000000) -> 0.27692183
A33: Burundi | B33: 14 | C33: 3.1 | D33: 25680 | E33: 0.013341732 | F33: 916664 | G33: =(qry_Master_Clean__2[[#This Row],[GDP_Billions]]*1000/qry_Master_Clean__2[[#This Row],[Population_Millions]]) -> 221.42857 | H33: =IF(qry_Master_Clean__2[[#This Row],[Population_Millions]]=0,"",qry_Master_Clean__2[[#This Row],[Energy_QuadBTU]]/qry_Master_Clean__2[[#This Row],[Population_Millions]]) -> 0.00095298086 | I33: =_xlfn.XLOOKUP(qry_Master_Clean__2[[#This Row],[Country]],Metadata!$E:$E,Metadata!$C:$C,"Not Found") -> Low income | J33: =(F33/C33) -> 295698.06 | K33: =_xlfn.XLOOKUP( qry_Master_Clean__2[[#This Row],[Country]], Renewable!$A$2:$A$267, Renewable!$BN$2:$BN$267, "" ) -> 83.1 | L33: =qry_Master_Clean__2[[#This Row],[CO2_Tonnes]]/(qry_Master_Clean__2[[#This Row],[Population_Millions]]*1000000) -> 0.065476
A34: Cabo Verde | B34: 0.5 | C34: 2.7 | D34: 4030 | E34: 0.010623084 | F34: 0 | G34: =(qry_Master_Clean__2[[#This Row],[GDP_Billions]]*1000/qry_Master_Clean__2[[#This Row],[Population_Millions]]) -> 5400 | H34: =IF(qry_Master_Clean__2[[#This Row],[Population_Millions]]=0,"",qry_Master_Clean__2[[#This Row],[Energy_QuadBTU]]/qry_Master_Clean__2[[#This Row],[Population_Millions]]) -> 0.021246169 | I34: =_xlfn.XLOOKUP(qry_Master_Clean__2[[#This Row],[Country]],Metadata!$E:$E,Metadata!$C:$C,"Not Found") -> Upper middle income | J34: =(qry_Master_Clean__2[[#This Row],[CO2_Tonnes]]/(qry_Master_Clean__2[[#This Row],[GDP_Billions]]/1000000000)) -> 0 | K34: =_xlfn.XLOOKUP( qry_Master_Clean__2[[#This Row],[Country]], Renewable!$A$2:$A$267, Renewable!$BN$2:$BN$267, "" ) -> 22.6 | L34: =qry_Master_Clean__2[[#This Row],[CO2_Tonnes]]/(qry_Master_Clean__2[[#This Row],[Population_Millions]]*1000000) -> 0
A35: Cambodia | B35: 17.6 | C35: 46.4 | D35: 176520 | E35: 0.29900285 | F35: 21882690 | G35: =(qry_Master_Clean__2[[#This Row],[GDP_Billions]]*1000/qry_Master_Clean__2[[#This Row],[Population_Millions]]) -> 2636.3636 | H35: =IF(qry_Master_Clean__2[[#This Row],[Population_Millions]]=0,"",qry_Master_Clean__2[[#This Row],[Energy_QuadBTU]]/qry_Master_Clean__2[[#This Row],[Population_Millions]]) -> 0.016988799 | I35: =_xlfn.XLOOKUP(qry_Master_Clean__2[[#This Row],[Country]],Metadata!$E:$E,Metadata!$C:$C,"Not Found") -> Lower middle income | J35: =(F35/C35) -> 471609.7 | K35: =_xlfn.XLOOKUP( qry_Master_Clean__2[[#This Row],[Country]], Renewable!$A$2:$A$267, Renewable!$BN$2:$BN$267, "" ) -> 52.4 | L35: =qry_Master_Clean__2[[#This Row],[CO2_Tonnes]]/(qry_Master_Clean__2[[#This Row],[Population_Millions]]*1000000) -> 1.2433347
A36: Yemen, Rep. | B36: 40.6 | C36: 0 | D36: 527970 | E36: 0 | F36: 0 | G36: =(qry_Master_Clean__2[[#This Row],[GDP_Billions]]*1000/qry_Master_Clean__2[[#This Row],[Population_Millions]]) -> 0 | H36: =IF(qry_Master_Clean__2[[#This Row],[Population_Millions]]=0,"",qry_Master_Clean__2[[#This Row],[Energy_QuadBTU]]/qry_Master_Clean__2[[#This Row],[Population_Millions]]) -> 0 | I36: =_xlfn.XLOOKUP(qry_Master_Clean__2[[#This Row],[Country]],Metadata!$E:$E,Metadata!$C:$C,"Not Found") -> Low income | J36: =(qry_Master_Clean__2[[#This Row],[CO2_Tonnes]]/(qry_Master_Clean__2[[#This Row],[GDP_Billions]]/1000000000)) -> #DIV/0! | K36: =_xlfn.XLOOKUP( qry_Master_Clean__2[[#This Row],[Country]], Renewable!$A$2:$A$267, Renewable!$BN$2:$BN$267, "" ) -> 3.7 | L36: =qry_Master_Clean__2[[#This Row],[CO2_Tonnes]]/(qry_Master_Clean__2[[#This Row],[Population_Millions]]*1000000) -> 0
A37: Eritrea | B37: 3.5 | C37: 0 | D37: 121178 | E37: 0.010705254 | F37: 742647 | G37: =(qry_Master_Clean__2[[#This Row],[GDP_Billions]]*1000/qry_Master_Clean__2[[#This Row],[Population_Millions]]) -> 0 | H37: =IF(qry_Master_Clean__2[[#This Row],[Population_Millions]]=0,"",qry_Master_Clean__2[[#This Row],[Energy_QuadBTU]]/qry_Master_Clean__2[[#This Row],[Population_Millions]]) -> 0.0030586439 | I37: =_xlfn.XLOOKUP(qry_Master_Clean__2[[#This Row],[Country]],Metadata!$E:$E,Metadata!$C:$C,"Not Found") -> Low income | J37: =(F37/C37) -> #DIV/0! | K37: =_xlfn.XLOOKUP( qry_Master_Clean__2[[#This Row],[Country]], Renewable!$A$2:$A$267, Renewable!$BN$2:$BN$267, "" ) -> 80.7 | L37: =qry_Master_Clean__2[[#This Row],[CO2_Tonnes]]/(qry_Master_Clean__2[[#This Row],[Population_Millions]]*1000000) -> 0.21218486
A38: South Sudan | B38: 11.9 | C38: 0 | D38: 631930 | E38: 0.024908716 | F38: 1695552 | G38: =(qry_Master_Clean__2[[#This Row],[GDP_Billions]]*1000/qry_Master_Clean__2[[#This Row],[Population_Millions]]) -> 0 | H38: =IF(qry_Master_Clean__2[[#This Row],[Population_Millions]]=0,"",qry_Master_Clean__2[[#This Row],[Energy_QuadBTU]]/qry_Master_Clean__2[[#This Row],[Population_Millions]]) -> 0.0020931694 | I38: =_xlfn.XLOOKUP(qry_Master_Clean__2[[#This Row],[Country]],Metadata!$E:$E,Metadata!$C:$C,"Not Found") -> Low income | J38: =(F38/C38) -> #DIV/0! | K38: =_xlfn.XLOOKUP( qry_Master_Clean__2[[#This Row],[Country]], Renewable!$A$2:$A$267, Renewable!$BN$2:$BN$267, "" ) -> 32.4 | L38: =qry_Master_Clean__2[[#This Row],[CO2_Tonnes]]/(qry_Master_Clean__2[[#This Row],[Population_Millions]]*1000000) -> 0.14248336
A39: Cuba | B39: 11 | C39: 0 | D39: 103800 | E39: 0.28749625 | F39: 24440234 | G39: =(qry_Master_Clean__2[[#This Row],[GDP_Billions]]*1000/qry_Master_Clean__2[[#This Row],[Population_Millions]]) -> 0 | H39: =IF(qry_Master_Clean__2[[#This Row],[Population_Millions]]=0,"",qry_Master_Clean__2[[#This Row],[Energy_QuadBTU]]/qry_Master_Clean__2[[#This Row],[Population_Millions]]) -> 0.026136023 | I39: =_xlfn.XLOOKUP(qry_Master_Clean__2[[#This Row],[Country]],Metadata!$E:$E,Metadata!$C:$C,"Not Found") -> Upper middle income | J39: =(F39/C39) -> #DIV/0! | K39: =_xlfn.XLOOKUP( qry_Master_Clean__2[[#This Row],[Country]], Renewable!$A$2:$A$267, Renewable!$BN$2:$BN$267, "" ) -> 20.9 | L39: =qry_Master_Clean__2[[#This Row],[CO2_Tonnes]]/(qry_Master_Clean__2[[#This Row],[Population_Millions]]*1000000) -> 2.2218395
A40: Cameroon | B40: 29.1 | C40: 53.3 | D40: 472710 | E40: 0.11952242 | F40: 9631583 | G40: =(qry_Master_Clean__2[[#This Row],[GDP_Billions]]*1000/qry_Master_Clean__2[[#This Row],[Population_Millions]]) -> 1831.6151 | H40: =IF(qry_Master_Clean__2[[#This Row],[Population_Millions]]=0,"",qry_Master_Clean__2[[#This Row],[Energy_QuadBTU]]/qry_Master_Clean__2[[#This Row],[Population_Millions]]) -> 0.0041072997 | I40: =_xlfn.XLOOKUP(qry_Master_Clean__2[[#This Row],[Country]],Metadata!$E:$E,Metadata!$C:$C,"Not Found") -> Lower middle income | J40: =(F40/C40) -> 180705.12 | K40: =_xlfn.XLOOKUP( qry_Master_Clean__2[[#This Row],[Country]], Renewable!$A$2:$A$267, Renewable!$BN$2:$BN$267, "" ) -> 79.2 | L40: =qry_Master_Clean__2[[#This Row],[CO2_Tonnes]]/(qry_Master_Clean__2[[#This Row],[Population_Millions]]*1000000) -> 0.33098223
A41: Canada | B41: 41.3 | C41: 2243.6 | D41: 8788700 | E41: 12.679478 | F41: 533340100 | G41: =(qry_Master_Clean__2[[#This Row],[GDP_Billions]]*1000/qry_Master_Clean__2[[#This Row],[Population_Millions]]) -> 54324.455 | H41: =IF(qry_Master_Clean__2[[#This Row],[Population_Millions]]=0,"",qry_Master_Clean__2[[#This Row],[Energy_QuadBTU]]/qry_Master_Clean__2[[#This Row],[Population_Millions]]) -> 0.30700916 | I41: =_xlfn.XLOOKUP(qry_Master_Clean__2[[#This Row],[Country]],Metadata!$E:$E,Metadata!$C:$C,"Not Found") -> High income | J41: =(F41/C41) -> 237716.22 | K41: =_xlfn.XLOOKUP( qry_Master_Clean__2[[#This Row],[Country]], Renewable!$A$2:$A$267, Renewable!$BN$2:$BN$267, "" ) -> 23.8 | L41: =qry_Master_Clean__2[[#This Row],[CO2_Tonnes]]/(qry_Master_Clean__2[[#This Row],[Population_Millions]]*1000000) -> 12.913804 | N41: Country | O41: Population_Millions | P41: GDP_Billions | Q41: Land_Area_Sq_Km | R41: Energy_QuadBTU | S41: CO2_Tonnes | T41: GDP per Capita (US$) | U41: Energy Consumption per Capita (QuadBTU per million people) | V41: Income Group | W41: CO₂ Tonnes per Billion GDP
A42: Cayman Islands | B42: 0.1 | C42: 7.2 | D42: 240 | E42: 0.012128745 | F42: 0 | G42: =(qry_Master_Clean__2[[#This Row],[GDP_Billions]]*1000/qry_Master_Clean__2[[#This Row],[Population_Millions]]) -> 72000 | H42: =IF(qry_Master_Clean__2[[#This Row],[Population_Millions]]=0,"",qry_Master_Clean__2[[#This Row],[Energy_QuadBTU]]/qry_Master_Clean__2[[#This Row],[Population_Millions]]) -> 0.12128745 | I42: =_xlfn.XLOOKUP(qry_Master_Clean__2[[#This Row],[Country]],Metadata!$E:$E,Metadata!$C:$C,"Not Found") -> High income | J42: =(qry_Master_Clean__2[[#This Row],[CO2_Tonnes]]/(qry_Master_Clean__2[[#This Row],[GDP_Billions]]/1000000000)) -> 0 | K42: =_xlfn.XLOOKUP( qry_Master_Clean__2[[#This Row],[Country]], Renewable!$A$2:$A$267, Renewable!$BN$2:$BN$267, "" ) -> 0 | L42: =qry_Master_Clean__2[[#This Row],[CO2_Tonnes]]/(qry_Master_Clean__2[[#This Row],[Population_Millions]]*1000000) -> 0 | N42: India | O42: 1450.9 | P42: 3909.9 | Q42: 2973190 | R42: 37.490302 | S42: 3193478100 | T42: 2694.8101 | U42: 0.025839343 | V42: Lower middle income | W42: 816767.21
A43: Central African Republic | B43: 5.3 | C43: 2.8 | D43: 622980 | E43: 0.0064871421 | F43: 0 | G43: =(qry_Master_Clean__2[[#This Row],[GDP_Billions]]*1000/qry_Master_Clean__2[[#This Row],[Population_Millions]]) -> 528.30189 | H43: =IF(qry_Master_Clean__2[[#This Row],[Population_Millions]]=0,"",qry_Master_Clean__2[[#This Row],[Energy_QuadBTU]]/qry_Master_Clean__2[[#This Row],[Population_Millions]]) -> 0.0012239891 | I43: =_xlfn.XLOOKUP(qry_Master_Clean__2[[#This Row],[Country]],Metadata!$E:$E,Metadata!$C:$C,"Not Found") -> Low income | J43: =(qry_Master_Clean__2[[#This Row],[CO2_Tonnes]]/(qry_Master_Clean__2[[#This Row],[GDP_Billions]]/1000000000)) -> 0 | K43: =_xlfn.XLOOKUP( qry_Master_Clean__2[[#This Row],[Country]], Renewable!$A$2:$A$267, Renewable!$BN$2:$BN$267, "" ) -> 90.9 | L43: =qry_Master_Clean__2[[#This Row],[CO2_Tonnes]]/(qry_Master_Clean__2[[#This Row],[Population_Millions]]*1000000) -> 0 | N43: Bahrain | O43: 1.6 | P43: 47.1 | Q43: 790 | R43: 0.8337039 | S43: 39003456 | T43: 29437.5 | U43: 0.52106494 | V43: High income | W43: 828098.85
A44: Chad | B44: 20.3 | C44: 19.5 | D44: 1259200 | E44: 0.026496087 | F44: 2831401 | G44: =(qry_Master_Clean__2[[#This Row],[GDP_Billions]]*1000/qry_Master_Clean__2[[#This Row],[Population_Millions]]) -> 960.59113 | H44: =IF(qry_Master_Clean__2[[#This Row],[Population_Millions]]=0,"",qry_Master_Clean__2[[#This Row],[Energy_QuadBTU]]/qry_Master_Clean__2[[#This Row],[Population_Millions]]) -> 0.0013052259 | I44: =_xlfn.XLOOKUP(qry_Master_Clean__2[[#This Row],[Country]],Metadata!$E:$E,Metadata!$C:$C,"Not Found") -> Low income | J44: =(F44/C44) -> 145200.05 | K44: =_xlfn.XLOOKUP( qry_Master_Clean__2[[#This Row],[Country]], Renewable!$A$2:$A$267, Renewable!$BN$2:$BN$267, "" ) -> 69.9 | L44: =qry_Master_Clean__2[[#This Row],[CO2_Tonnes]]/(qry_Master_Clean__2[[#This Row],[Population_Millions]]*1000000) -> 0.13947788 | N44: Iraq | O44: 46 | P44: 279.6 | Q44: 434130 | R44: 2.9150554 | S44: 233635500 | T44: 6078.2609 | U44: 0.063370769 | V44: Upper middle income | W44: 835606.22
A45: Channel Islands | B45: 0.2 | C45: 12.5 | D45: 198 | E45: 0 | F45: 0 | G45: =(qry_Master_Clean__2[[#This Row],[GDP_Billions]]*1000/qry_Master_Clean__2[[#This Row],[Population_Millions]]) -> 62500 | H45: =IF(qry_Master_Clean__2[[#This Row],[Population_Millions]]=0,"",qry_Master_Clean__2[[#This Row],[Energy_QuadBTU]]/qry_Master_Clean__2[[#This Row],[Population_Millions]]) -> 0 | I45: =_xlfn.XLOOKUP(qry_Master_Clean__2[[#This Row],[Country]],Metadata!$E:$E,Metadata!$C:$C,"Not Found") -> High income | J45: =(qry_Master_Clean__2[[#This Row],[CO2_Tonnes]]/(qry_Master_Clean__2[[#This Row],[GDP_Billions]]/1000000000)) -> 0 | K45: =_xlfn.XLOOKUP( qry_Master_Clean__2[[#This Row],[Country]], Renewable!$A$2:$A$267, Renewable!$BN$2:$BN$267, "" ) -> 0 | L45: =qry_Master_Clean__2[[#This Row],[CO2_Tonnes]]/(qry_Master_Clean__2[[#This Row],[Population_Millions]]*1000000) -> 0 | N45: Kazakhstan | O45: 20.6 | P45: 291.5 | Q45: 2699700 | R45: 3.6340199 | S45: 287005950 | T45: 14150.485 | U45: 0.17640873 | V45: Upper middle income | W45: 984583.02
A46: Chile | B46: 19.8 | C46: 330.3 | D46: 742832 | E46: 1.3542548 | F46: 78725544 | G46: =(qry_Master_Clean__2[[#This Row],[GDP_Billions]]*1000/qry_Master_Clean__2[[#This Row],[Population_Millions]]) -> 16681.818 | H46: =IF(qry_Master_Clean__2[[#This Row],[Population_Millions]]=0,"",qry_Master_Clean__2[[#This Row],[Energy_QuadBTU]]/qry_Master_Clean__2[[#This Row],[Population_Millions]]) -> 0.068396707 | I46: =_xlfn.XLOOKUP(qry_Master_Clean__2[[#This Row],[Country]],Metadata!$E:$E,Metadata!$C:$C,"Not Found") -> High income | J46: =(F46/C46) -> 238345.58 | K46: =_xlfn.XLOOKUP( qry_Master_Clean__2[[#This Row],[Country]], Renewable!$A$2:$A$267, Renewable!$BN$2:$BN$267, "" ) -> 24.2 | L46: =qry_Master_Clean__2[[#This Row],[CO2_Tonnes]]/(qry_Master_Clean__2[[#This Row],[Population_Millions]]*1000000) -> 3.9760376 | N46: Lesotho | O46: 2.3 | P46: 2.3 | Q46: 30360 | R46: 0.013412608 | S46: 2571767 | T46: 1000 | U46: 0.0058315685 | V46: Lower middle income | W46: 1118159.6
A47: China | B47: 1409 | C47: 18743.8 | D47: 9388210 | E47: 170.57928 | F47: 12289037000 | G47: =(qry_Master_Clean__2[[#This Row],[GDP_Billions]]*1000/qry_Master_Clean__2[[#This Row],[Population_Millions]]) -> 13302.91 | H47: =IF(qry_Master_Clean__2[[#This Row],[Population_Millions]]=0,"",qry_Master_Clean__2[[#This Row],[Energy_QuadBTU]]/qry_Master_Clean__2[[#This Row],[Population_Millions]]) -> 0.12106407 | I47: =_xlfn.XLOOKUP(qry_Master_Clean__2[[#This Row],[Country]],Metadata!$E:$E,Metadata!$C:$C,"Not Found") -> Upper middle income | J47: =(F47/C47) -> 655632.1 | K47: =_xlfn.XLOOKUP( qry_Master_Clean__2[[#This Row],[Country]], Renewable!$A$2:$A$267, Renewable!$BN$2:$BN$267, "" ) -> 15.2 | L47: =qry_Master_Clean__2[[#This Row],[CO2_Tonnes]]/(qry_Master_Clean__2[[#This Row],[Population_Millions]]*1000000) -> 8.7218148 | N47: Uzbekistan | O47: 36.4 | P47: 115 | Q47: 440653 | R47: 2.2949954 | S47: 139234180 | T47: 3159.3407 | U47: 0.063049325 | V47: Lower middle income | W47: 1210732
A48: Colombia | B48: 52.9 | C48: 418.8 | D48: 1109500 | E48: 1.7899856 | F48: 92659384 | G48: =(qry_Master_Clean__2[[#This Row],[GDP_Billions]]*1000/qry_Master_Clean__2[[#This Row],[Population_Millions]]) -> 7916.8242 | H48: =IF(qry_Master_Clean__2[[#This Row],[Population_Millions]]=0,"",qry_Master_Clean__2[[#This Row],[Energy_QuadBTU]]/qry_Master_Clean__2[[#This Row],[Population_Millions]]) -> 0.033837158 | I48: =_xlfn.XLOOKUP(qry_Master_Clean__2[[#This Row],[Country]],Metadata!$E:$E,Metadata!$C:$C,"Not Found") -> Upper middle income | J48: =(F48/C48) -> 221249.72 | K48: =_xlfn.XLOOKUP( qry_Master_Clean__2[[#This Row],[Country]], Renewable!$A$2:$A$267, Renewable!$BN$2:$BN$267, "" ) -> 29.7 | L48: =qry_Master_Clean__2[[#This Row],[CO2_Tonnes]]/(qry_Master_Clean__2[[#This Row],[Population_Millions]]*1000000) -> 1.7515952 | N48: Libya | O48: 7.4 | P48: 48.5 | Q48: 1759540 | R48: 0.84024977 | S48: 65260070 | T48: 6554.0541 | U48: 0.11354727 | V48: Upper middle income | W48: 1345568.5
A49: Comoros | B49: 0.9 | C49: 1.4 | D49: 1861 | E49: 0.00538552 | F49: 551650 | G49: =(qry_Master_Clean__2[[#This Row],[GDP_Billions]]*1000/qry_Master_Clean__2[[#This Row],[Population_Millions]]) -> 1555.5556 | H49: =IF(qry_Master_Clean__2[[#This Row],[Population_Millions]]=0,"",qry_Master_Clean__2[[#This Row],[Energy_QuadBTU]]/qry_Master_Clean__2[[#This Row],[Population_Millions]]) -> 0.0059839111 | I49: =_xlfn.XLOOKUP(qry_Master_Clean__2[[#This Row],[Country]],Metadata!$E:$E,Metadata!$C:$C,"Not Found") -> Lower middle income | J49: =(F49/C49) -> 394035.71 | K49: =_xlfn.XLOOKUP( qry_Master_Clean__2[[#This Row],[Country]], Renewable!$A$2:$A$267, Renewable!$BN$2:$BN$267, "" ) -> 41.2 | L49: =qry_Master_Clean__2[[#This Row],[CO2_Tonnes]]/(qry_Master_Clean__2[[#This Row],[Population_Millions]]*1000000) -> 0.61294444 | N49: Trinidad and Tobago | O49: 1.4 | P49: 25.6 | Q49: 5130 | R49: 0.62714262 | S49: 34576280 | T49: 18285.714 | U49: 0.44795902 | V49: High income | W49: 1350635.9
A50: Congo, Dem. Rep. | B50: 109.3 | C50: 71 | D50: 2267050 | E50: 0 | F50: 0 | G50: =(qry_Master_Clean__2[[#This Row],[GDP_Billions]]*1000/qry_Master_Clean__2[[#This Row],[Population_Millions]]) -> 649.58829 | H50: =IF(qry_Master_Clean__2[[#This Row],[Population_Millions]]=0,"",qry_Master_Clean__2[[#This Row],[Energy_QuadBTU]]/qry_Master_Clean__2[[#This Row],[Population_Millions]]) -> 0 | I50: =_xlfn.XLOOKUP(qry_Master_Clean__2[[#This Row],[Country]],Metadata!$E:$E,Metadata!$C:$C,"Not Found") -> Low income | J50: =(qry_Master_Clean__2[[#This Row],[CO2_Tonnes]]/(qry_Master_Clean__2[[#This Row],[GDP_Billions]]/1000000000)) -> 0 | K50: =_xlfn.XLOOKUP( qry_Master_Clean__2[[#This Row],[Country]], Renewable!$A$2:$A$267, Renewable!$BN$2:$BN$267, "" ) -> 96.3 | L50: =qry_Master_Clean__2[[#This Row],[CO2_Tonnes]]/(qry_Master_Clean__2[[#This Row],[Population_Millions]]*1000000) -> 0 | N50: Turkmenistan | O50: 7.5 | P50: 51.4 | Q50: 469930 | R50: 1.8509342 | S50: 81005550 | T50: 6853.3333 | U50: 0.24679123 | V50: Upper middle income | W50: 1575983.5
A51: Congo, Rep. | B51: 6.3 | C51: 15.7 | D51: 341500 | E51: 0 | F51: 0 | G51: =(qry_Master_Clean__2[[#This Row],[GDP_Billions]]*1000/qry_Master_Clean__2[[#This Row],[Population_Millions]]) -> 2492.0635 | H51: =IF(qry_Master_Clean__2[[#This Row],[Population_Millions]]=0,"",qry_Master_Clean__2[[#This Row],[Energy_QuadBTU]]/qry_Master_Clean__2[[#This Row],[Population_Millions]]) -> 0 | I51: =_xlfn.XLOOKUP(qry_Master_Clean__2[[#This Row],[Country]],Metadata!$E:$E,Metadata!$C:$C,"Not Found") -> Lower middle income | J51: =(qry_Master_Clean__2[[#This Row],[CO2_Tonnes]]/(qry_Master_Clean__2[[#This Row],[GDP_Billions]]/1000000000)) -> 0 | K51: =_xlfn.XLOOKUP( qry_Master_Clean__2[[#This Row],[Country]], Renewable!$A$2:$A$267, Renewable!$BN$2:$BN$267, "" ) -> 71.4 | L51: =qry_Master_Clean__2[[#This Row],[CO2_Tonnes]]/(qry_Master_Clean__2[[#This Row],[Population_Millions]]*1000000) -> 0 | N51: Mongolia | O51: 3.5 | P51: 23.8 | Q51: 1557507 | R51: 0.26216838 | S51: 44693890 | T51: 6800 | U51: 0.07490525 | V51: Upper middle income | W51: 1877894.5
A52: Costa Rica | B52: 5.1 | C52: 95.4 | D52: 51060 | E52: 0.16851419 | F52: 8760451 | G52: =(qry_Master_Clean__2[[#This Row],[GDP_Billions]]*1000/qry_Master_Clean__2[[#This Row],[Population_Millions]]) -> 18705.882 | H52: =IF(qry_Master_Clean__2[[#This Row],[Population_Millions]]=0,"",qry_Master_Clean__2[[#This Row],[Energy_QuadBTU]]/qry_Master_Clean__2[[#This Row],[Population_Millions]]) -> 0.033041998 | I52: =_xlfn.XLOOKUP(qry_Master_Clean__2[[#This Row],[Country]],Metadata!$E:$E,Metadata!$C:$C,"Not Found") -> High income | J52: =(F52/C52) -> 91828.627 | K52: =_xlfn.XLOOKUP( qry_Master_Clean__2[[#This Row],[Country]], Renewable!$A$2:$A$267, Renewable!$BN$2:$BN$267, "" ) -> 34.2 | L52: =qry_Master_Clean__2[[#This Row],[CO2_Tonnes]]/(qry_Master_Clean__2[[#This Row],[Population_Millions]]*1000000) -> 1.7177355
A53: Cote d'Ivoire | B53: 31.9 | C53: 87.1 | D53: 318000 | E53: 0.28462303 | F53: 14828585 | G53: =(qry_Master_Clean__2[[#This Row],[GDP_Billions]]*1000/qry_Master_Clean__2[[#This Row],[Population_Millions]]) -> 2730.4075 | H53: =IF(qry_Master_Clean__2[[#This Row],[Population_Millions]]=0,"",qry_Master_Clean__2[[#This Row],[Energy_QuadBTU]]/qry_Master_Clean__2[[#This Row],[Population_Millions]]) -> 0.0089223519 | I53: Lower middle income | J53: =(F53/C53) -> 170247.82 | K53: =_xlfn.XLOOKUP( qry_Master_Clean__2[[#This Row],[Country]], Renewable!$A$2:$A$267, Renewable!$BN$2:$BN$267, "" ) -> 58.2 | L53: =qry_Master_Clean__2[[#This Row],[CO2_Tonnes]]/(qry_Master_Clean__2[[#This Row],[Population_Millions]]*1000000) -> 0.46484592
A54: Croatia | B54: 3.9 | C54: 93 | D54: 55960 | E54: 0.31737729 | F54: 18464850 | G54: =(qry_Master_Clean__2[[#This Row],[GDP_Billions]]*1000/qry_Master_Clean__2[[#This Row],[Population_Millions]]) -> 23846.154 | H54: =IF(qry_Master_Clean__2[[#This Row],[Population_Millions]]=0,"",qry_Master_Clean__2[[#This Row],[Energy_QuadBTU]]/qry_Master_Clean__2[[#This Row],[Population_Millions]]) -> 0.081378793 | I54: =_xlfn.XLOOKUP(qry_Master_Clean__2[[#This Row],[Country]],Metadata!$E:$E,Metadata!$C:$C,"Not Found") -> High income | J54: =(F54/C54) -> 198546.77 | K54: =_xlfn.XLOOKUP( qry_Master_Clean__2[[#This Row],[Country]], Renewable!$A$2:$A$267, Renewable!$BN$2:$BN$267, "" ) -> 34.1 | L54: =qry_Master_Clean__2[[#This Row],[CO2_Tonnes]]/(qry_Master_Clean__2[[#This Row],[Population_Millions]]*1000000) -> 4.7345769
A55: Curacao | B55: 0.2 | C55: 3.6 | D55: 444 | E55: 0 | F55: 2289628 | G55: =(qry_Master_Clean__2[[#This Row],[GDP_Billions]]*1000/qry_Master_Clean__2[[#This Row],[Population_Millions]]) -> 18000 | H55: =IF(qry_Master_Clean__2[[#This Row],[Population_Millions]]=0,"",qry_Master_Clean__2[[#This Row],[Energy_QuadBTU]]/qry_Master_Clean__2[[#This Row],[Population_Millions]]) -> 0 | I55: High income | J55: =(F55/C55) -> 636007.78 | K55: =_xlfn.XLOOKUP( qry_Master_Clean__2[[#This Row],[Country]], Renewable!$A$2:$A$267, Renewable!$BN$2:$BN$267, "" ) -> 2.8 | L55: =qry_Master_Clean__2[[#This Row],[CO2_Tonnes]]/(qry_Master_Clean__2[[#This Row],[Population_Millions]]*1000000) -> 11.44814
A56: Cyprus | B56: 1.4 | C56: 37.6 | D56: 9240 | E56: 0.10319045 | F56: 7299328 | G56: =(qry_Master_Clean__2[[#This Row],[GDP_Billions]]*1000/qry_Master_Clean__2[[#This Row],[Population_Millions]]) -> 26857.143 | H56: =IF(qry_Master_Clean__2[[#This Row],[Population_Millions]]=0,"",qry_Master_Clean__2[[#This Row],[Energy_QuadBTU]]/qry_Master_Clean__2[[#This Row],[Population_Millions]]) -> 0.073707466 | I56: =_xlfn.XLOOKUP(qry_Master_Clean__2[[#This Row],[Country]],Metadata!$E:$E,Metadata!$C:$C,"Not Found") -> High income | J56: =(F56/C56) -> 194131.06 | K56: =_xlfn.XLOOKUP( qry_Master_Clean__2[[#This Row],[Country]], Renewable!$A$2:$A$267, Renewable!$BN$2:$BN$267, "" ) -> 15.6 | L56: =qry_Master_Clean__2[[#This Row],[CO2_Tonnes]]/(qry_Master_Clean__2[[#This Row],[Population_Millions]]*1000000) -> 5.2138057
A57: Czechia | B57: 10.9 | C57: 347 | D57: 77187 | E57: 1.4625075 | F57: 75623000 | G57: =(qry_Master_Clean__2[[#This Row],[GDP_Billions]]*1000/qry_Master_Clean__2[[#This Row],[Population_Millions]]) -> 31834.862 | H57: =IF(qry_Master_Clean__2[[#This Row],[Population_Millions]]=0,"",qry_Master_Clean__2[[#This Row],[Energy_QuadBTU]]/qry_Master_Clean__2[[#This Row],[Population_Millions]]) -> 0.134175 | I57: =_xlfn.XLOOKUP(qry_Master_Clean__2[[#This Row],[Country]],Metadata!$E:$E,Metadata!$C:$C,"Not Found") -> High income | J57: =(F57/C57) -> 217933.72 | K57: =_xlfn.XLOOKUP( qry_Master_Clean__2[[#This Row],[Country]], Renewable!$A$2:$A$267, Renewable!$BN$2:$BN$267, "" ) -> 17.2 | L57: =qry_Master_Clean__2[[#This Row],[CO2_Tonnes]]/(qry_Master_Clean__2[[#This Row],[Population_Millions]]*1000000) -> 6.9378899
A58: Denmark | B58: 6 | C58: 424.5 | D58: 40000 | E58: 0.57656862 | F58: 28369162 | G58: =(qry_Master_Clean__2[[#This Row],[GDP_Billions]]*1000/qry_Master_Clean__2[[#This Row],[Population_Millions]]) -> 70750 | H58: =IF(qry_Master_Clean__2[[#This Row],[Population_Millions]]=0,"",qry_Master_Clean__2[[#This Row],[Energy_QuadBTU]]/qry_Master_Clean__2[[#This Row],[Population_Millions]]) -> 0.09609477 | I58: =_xlfn.XLOOKUP(qry_Master_Clean__2[[#This Row],[Country]],Metadata!$E:$E,Metadata!$C:$C,"Not Found") -> High income | J58: =(F58/C58) -> 66829.592 | K58: =_xlfn.XLOOKUP( qry_Master_Clean__2[[#This Row],[Country]], Renewable!$A$2:$A$267, Renewable!$BN$2:$BN$267, "" ) -> 39.5 | L58: =qry_Master_Clean__2[[#This Row],[CO2_Tonnes]]/(qry_Master_Clean__2[[#This Row],[Population_Millions]]*1000000) -> 4.7281937
A59: Djibouti | B59: 1.2 | C59: 4.2 | D59: 23180 | E59: 0.01197106 | F59: 564084 | G59: =(qry_Master_Clean__2[[#This Row],[GDP_Billions]]*1000/qry_Master_Clean__2[[#This Row],[Population_Millions]]) -> 3500 | H59: =IF(qry_Master_Clean__2[[#This Row],[Population_Millions]]=0,"",qry_Master_Clean__2[[#This Row],[Energy_QuadBTU]]/qry_Master_Clean__2[[#This Row],[Population_Millions]]) -> 0.0099758831 | I59: =_xlfn.XLOOKUP(qry_Master_Clean__2[[#This Row],[Country]],Metadata!$E:$E,Metadata!$C:$C,"Not Found") -> Lower middle income | J59: =(F59/C59) -> 134305.71 | K59: =_xlfn.XLOOKUP( qry_Master_Clean__2[[#This Row],[Country]], Renewable!$A$2:$A$267, Renewable!$BN$2:$BN$267, "" ) -> 26.6 | L59: =qry_Master_Clean__2[[#This Row],[CO2_Tonnes]]/(qry_Master_Clean__2[[#This Row],[Population_Millions]]*1000000) -> 0.47007 | O59: KPIS TABLE
A60: Dominica | B60: 0.1 | C60: 0.7 | D60: 750 | E60: 0.002642263 | F60: 170858 | G60: =(qry_Master_Clean__2[[#This Row],[GDP_Billions]]*1000/qry_Master_Clean__2[[#This Row],[Population_Millions]]) -> 7000 | H60: =IF(qry_Master_Clean__2[[#This Row],[Population_Millions]]=0,"",qry_Master_Clean__2[[#This Row],[Energy_QuadBTU]]/qry_Master_Clean__2[[#This Row],[Population_Millions]]) -> 0.02642263 | I60: =_xlfn.XLOOKUP(qry_Master_Clean__2[[#This Row],[Country]],Metadata!$E:$E,Metadata!$C:$C,"Not Found") -> Upper middle income | J60: =(F60/C60) -> 244082.86 | K60: =_xlfn.XLOOKUP( qry_Master_Clean__2[[#This Row],[Country]], Renewable!$A$2:$A$267, Renewable!$BN$2:$BN$267, "" ) -> 8.8 | L60: =qry_Master_Clean__2[[#This Row],[CO2_Tonnes]]/(qry_Master_Clean__2[[#This Row],[Population_Millions]]*1000000) -> 1.70858 | O60: Countries / Economies Analysed | P60: =COUNTA(qry_Master_Clean__2[Country]) -> 212
A61: Dominican Republic | B61: 11.4 | C61: 124.3 | D61: 48198 | E61: 0.47776897 | F61: 33130818 | G61: =(qry_Master_Clean__2[[#This Row],[GDP_Billions]]*1000/qry_Master_Clean__2[[#This Row],[Population_Millions]]) -> 10903.509 | H61: =IF(qry_Master_Clean__2[[#This Row],[Population_Millions]]=0,"",qry_Master_Clean__2[[#This Row],[Energy_QuadBTU]]/qry_Master_Clean__2[[#This Row],[Population_Millions]]) -> 0.041909559 | I61: =_xlfn.XLOOKUP(qry_Master_Clean__2[[#This Row],[Country]],Metadata!$E:$E,Metadata!$C:$C,"Not Found") -> Upper middle income | J61: =(F61/C61) -> 266539.16 | K61: =_xlfn.XLOOKUP( qry_Master_Clean__2[[#This Row],[Country]], Renewable!$A$2:$A$267, Renewable!$BN$2:$BN$267, "" ) -> 14.8 | L61: =qry_Master_Clean__2[[#This Row],[CO2_Tonnes]]/(qry_Master_Clean__2[[#This Row],[Population_Millions]]*1000000) -> 2.9062121 | O61: Average GDP per Capita | P61: =_xlfn.AGGREGATE(1,6,qry_Master_Clean__2[GDP per Capita (US$)]) -> 19447.404
A62: Ecuador | B62: 18.1 | C62: 124.7 | D62: 248360 | E62: 0.66814865 | F62: 45979548 | G62: =(qry_Master_Clean__2[[#This Row],[GDP_Billions]]*1000/qry_Master_Clean__2[[#This Row],[Population_Millions]]) -> 6889.5028 | H62: =IF(qry_Master_Clean__2[[#This Row],[Population_Millions]]=0,"",qry_Master_Clean__2[[#This Row],[Energy_QuadBTU]]/qry_Master_Clean__2[[#This Row],[Population_Millions]]) -> 0.03691429 | I62: =_xlfn.XLOOKUP(qry_Master_Clean__2[[#This Row],[Country]],Metadata!$E:$E,Metadata!$C:$C,"Not Found") -> Upper middle income | J62: =(F62/C62) -> 368721.32 | K62: =_xlfn.XLOOKUP( qry_Master_Clean__2[[#This Row],[Country]], Renewable!$A$2:$A$267, Renewable!$BN$2:$BN$267, "" ) -> 18.9 | L62: =qry_Master_Clean__2[[#This Row],[CO2_Tonnes]]/(qry_Master_Clean__2[[#This Row],[Population_Millions]]*1000000) -> 2.5403065 | O62: Average CO₂ Emissions per Capita | P62: =_xlfn.AGGREGATE(1,6,qry_Master_Clean__2[Emissions Per Capita (tonnes per person)]) -> 3.7043236
A63: Egypt, Arab Rep. | B63: 116.5 | C63: 389.1 | D63: 995450 | E63: 0 | F63: 0 | G63: =(qry_Master_Clean__2[[#This Row],[GDP_Billions]]*1000/qry_Master_Clean__2[[#This Row],[Population_Millions]]) -> 3339.9142 | H63: =IF(qry_Master_Clean__2[[#This Row],[Population_Millions]]=0,"",qry_Master_Clean__2[[#This Row],[Energy_QuadBTU]]/qry_Master_Clean__2[[#This Row],[Population_Millions]]) -> 0 | I63: =_xlfn.XLOOKUP(qry_Master_Clean__2[[#This Row],[Country]],Metadata!$E:$E,Metadata!$C:$C,"Not Found") -> Lower middle income | J63: =(qry_Master_Clean__2[[#This Row],[CO2_Tonnes]]/(qry_Master_Clean__2[[#This Row],[GDP_Billions]]/1000000000)) -> 0 | K63: =_xlfn.XLOOKUP( qry_Master_Clean__2[[#This Row],[Country]], Renewable!$A$2:$A$267, Renewable!$BN$2:$BN$267, "" ) -> 6.1 | L63: =qry_Master_Clean__2[[#This Row],[CO2_Tonnes]]/(qry_Master_Clean__2[[#This Row],[Population_Millions]]*1000000) -> 0 | O63: Average Renewable Energy Share | P63: =AVERAGE(qry_Master_Clean__2[Renewalble]) -> 28.632075
A64: El Salvador | B64: 6.3 | C64: 35.4 | D64: 20720 | E64: 0.15973014 | F64: 8972291 | G64: =(qry_Master_Clean__2[[#This Row],[GDP_Billions]]*1000/qry_Master_Clean__2[[#This Row],[Population_Millions]]) -> 5619.0476 | H64: =IF(qry_Master_Clean__2[[#This Row],[Population_Millions]]=0,"",qry_Master_Clean__2[[#This Row],[Energy_QuadBTU]]/qry_Master_Clean__2[[#This Row],[Population_Millions]]) -> 0.025353991 | I64: =_xlfn.XLOOKUP(qry_Master_Clean__2[[#This Row],[Country]],Metadata!$E:$E,Metadata!$C:$C,"Not Found") -> Upper middle income | J64: =(F64/C64) -> 253454.55 | K64: =_xlfn.XLOOKUP( qry_Master_Clean__2[[#This Row],[Country]], Renewable!$A$2:$A$267, Renewable!$BN$2:$BN$267, "" ) -> 21.9 | L64: =qry_Master_Clean__2[[#This Row],[CO2_Tonnes]]/(qry_Master_Clean__2[[#This Row],[Population_Millions]]*1000000) -> 1.4241732
A65: Equatorial Guinea | B65: 1.9 | C65: 12.8 | D65: 28050 | E65: 0.10600865 | F65: 7010352 | G65: =(qry_Master_Clean__2[[#This Row],[GDP_Billions]]*1000/qry_Master_Clean__2[[#This Row],[Population_Millions]]) -> 6736.8421 | H65: =IF(qry_Master_Clean__2[[#This Row],[Population_Millions]]=0,"",qry_Master_Clean__2[[#This Row],[Energy_QuadBTU]]/qry_Master_Clean__2[[#This Row],[Population_Millions]]) -> 0.055794027 | I65: =_xlfn.XLOOKUP(qry_Master_Clean__2[[#This Row],[Country]],Metadata!$E:$E,Metadata!$C:$C,"Not Found") -> Upper middle income | J65: =(F65/C65) -> 547683.75 | K65: =_xlfn.XLOOKUP( qry_Master_Clean__2[[#This Row],[Country]], Renewable!$A$2:$A$267, Renewable!$BN$2:$BN$267, "" ) -> 5.2 | L65: =qry_Master_Clean__2[[#This Row],[CO2_Tonnes]]/(qry_Master_Clean__2[[#This Row],[Population_Millions]]*1000000) -> 3.6896589
A66: Estonia | B66: 1.4 | C66: 43.1 | D66: 42750 | E66: 0.098743208 | F66: 8306777 | G66: =(qry_Master_Clean__2[[#This Row],[GDP_Billions]]*1000/qry_Master_Clean__2[[#This Row],[Population_Millions]]) -> 30785.714 | H66: =IF(qry_Master_Clean__2[[#This Row],[Population_Millions]]=0,"",qry_Master_Clean__2[[#This Row],[Energy_QuadBTU]]/qry_Master_Clean__2[[#This Row],[Population_Millions]]) -> 0.070530863 | I66: =_xlfn.XLOOKUP(qry_Master_Clean__2[[#This Row],[Country]],Metadata!$E:$E,Metadata!$C:$C,"Not Found") -> High income | J66: =(F66/C66) -> 192732.65 | K66: =_xlfn.XLOOKUP( qry_Master_Clean__2[[#This Row],[Country]], Renewable!$A$2:$A$267, Renewable!$BN$2:$BN$267, "" ) -> 38 | L66: =qry_Master_Clean__2[[#This Row],[CO2_Tonnes]]/(qry_Master_Clean__2[[#This Row],[Population_Millions]]*1000000) -> 5.9334121
A67: Eswatini | B67: 1.2 | C67: 4.9 | D67: 17200 | E67: 0.023776695 | F67: 1044644 | G67: =(qry_Master_Clean__2[[#This Row],[GDP_Billions]]*1000/qry_Master_Clean__2[[#This Row],[Population_Millions]]) -> 4083.3333 | H67: =IF(qry_Master_Clean__2[[#This Row],[Population_Millions]]=0,"",qry_Master_Clean__2[[#This Row],[Energy_QuadBTU]]/qry_Master_Clean__2[[#This Row],[Population_Millions]]) -> 0.019813913 | I67: =_xlfn.XLOOKUP(qry_Master_Clean__2[[#This Row],[Country]],Metadata!$E:$E,Metadata!$C:$C,"Not Found") -> Lower middle income | J67: =(F67/C67) -> 213192.65 | K67: =_xlfn.XLOOKUP( qry_Master_Clean__2[[#This Row],[Country]], Renewable!$A$2:$A$267, Renewable!$BN$2:$BN$267, "" ) -> 65.4 | L67: =qry_Master_Clean__2[[#This Row],[CO2_Tonnes]]/(qry_Master_Clean__2[[#This Row],[Population_Millions]]*1000000) -> 0.87053667
A68: Ethiopia | B68: 132.1 | C68: 149.7 | D68: 1128506 | E68: 0.30898441 | F68: 17837292 | G68: =(qry_Master_Clean__2[[#This Row],[GDP_Billions]]*1000/qry_Master_Clean__2[[#This Row],[Population_Millions]]) -> 1133.2324 | H68: =IF(qry_Master_Clean__2[[#This Row],[Population_Millions]]=0,"",qry_Master_Clean__2[[#This Row],[Energy_QuadBTU]]/qry_Master_Clean__2[[#This Row],[Population_Millions]]) -> 0.002339019 | I68: Low income | J68: =(F68/C68) -> 119153.59 | K68: =_xlfn.XLOOKUP( qry_Master_Clean__2[[#This Row],[Country]], Renewable!$A$2:$A$267, Renewable!$BN$2:$BN$267, "" ) -> 90.6 | L68: =qry_Master_Clean__2[[#This Row],[CO2_Tonnes]]/(qry_Master_Clean__2[[#This Row],[Population_Millions]]*1000000) -> 0.13502871
A69: Faroe Islands | B69: 0.1 | C69: 4.1 | D69: 1370 | E69: 0.012223593 | F69: 725388 | G69: =(qry_Master_Clean__2[[#This Row],[GDP_Billions]]*1000/qry_Master_Clean__2[[#This Row],[Population_Millions]]) -> 41000 | H69: =IF(qry_Master_Clean__2[[#This Row],[Population_Millions]]=0,"",qry_Master_Clean__2[[#This Row],[Energy_QuadBTU]]/qry_Master_Clean__2[[#This Row],[Population_Millions]]) -> 0.12223593 | I69: =_xlfn.XLOOKUP(qry_Master_Clean__2[[#This Row],[Country]],Metadata!$E:$E,Metadata!$C:$C,"Not Found") -> High income | J69: =(F69/C69) -> 176923.9 | K69: =_xlfn.XLOOKUP( qry_Master_Clean__2[[#This Row],[Country]], Renewable!$A$2:$A$267, Renewable!$BN$2:$BN$267, "" ) -> 5.1 | L69: =qry_Master_Clean__2[[#This Row],[CO2_Tonnes]]/(qry_Master_Clean__2[[#This Row],[Population_Millions]]*1000000) -> 7.25388
A70: Fiji | B70: 0.9 | C70: 6 | D70: 18270 | E70: 0.034703587 | F70: 1445316 | G70: =(qry_Master_Clean__2[[#This Row],[GDP_Billions]]*1000/qry_Master_Clean__2[[#This Row],[Population_Millions]]) -> 6666.6667 | H70: =IF(qry_Master_Clean__2[[#This Row],[Population_Millions]]=0,"",qry_Master_Clean__2[[#This Row],[Energy_QuadBTU]]/qry_Master_Clean__2[[#This Row],[Population_Millions]]) -> 0.038559541 | I70: =_xlfn.XLOOKUP(qry_Master_Clean__2[[#This Row],[Country]],Metadata!$E:$E,Metadata!$C:$C,"Not Found") -> Upper middle income | J70: =(F70/C70) -> 240886 | K70: =_xlfn.XLOOKUP( qry_Master_Clean__2[[#This Row],[Country]], Renewable!$A$2:$A$267, Renewable!$BN$2:$BN$267, "" ) -> 29.7 | L70: =qry_Master_Clean__2[[#This Row],[CO2_Tonnes]]/(qry_Master_Clean__2[[#This Row],[Population_Millions]]*1000000) -> 1.6059067
A71: Finland | B71: 5.6 | C71: 298.7 | D71: 303948 | E71: 0.99926488 | F71: 29775000 | G71: =(qry_Master_Clean__2[[#This Row],[GDP_Billions]]*1000/qry_Master_Clean__2[[#This Row],[Population_Millions]]) -> 53339.286 | H71: =IF(qry_Master_Clean__2[[#This Row],[Population_Millions]]=0,"",qry_Master_Clean__2[[#This Row],[Energy_QuadBTU]]/qry_Master_Clean__2[[#This Row],[Population_Millions]]) -> 0.17844016 | I71: =_xlfn.XLOOKUP(qry_Master_Clean__2[[#This Row],[Country]],Metadata!$E:$E,Metadata!$C:$C,"Not Found") -> High income | J71: =(F71/C71) -> 99681.955 | K71: =_xlfn.XLOOKUP( qry_Master_Clean__2[[#This Row],[Country]], Renewable!$A$2:$A$267, Renewable!$BN$2:$BN$267, "" ) -> 50.2 | L71: =qry_Master_Clean__2[[#This Row],[CO2_Tonnes]]/(qry_Master_Clean__2[[#This Row],[Population_Millions]]*1000000) -> 5.3169643
A72: France | B72: 68.6 | C72: 3160.4 | D72: 538950 | E72: 8.5626572 | F72: 264155620 | G72: =(qry_Master_Clean__2[[#This Row],[GDP_Billions]]*1000/qry_Master_Clean__2[[#This Row],[Population_Millions]]) -> 46069.971 | H72: =IF(qry_Master_Clean__2[[#This Row],[Population_Millions]]=0,"",qry_Master_Clean__2[[#This Row],[Energy_QuadBTU]]/qry_Master_Clean__2[[#This Row],[Population_Millions]]) -> 0.12482008 | I72: =_xlfn.XLOOKUP(qry_Master_Clean__2[[#This Row],[Country]],Metadata!$E:$E,Metadata!$C:$C,"Not Found") -> High income | J72: =(F72/C72) -> 83582.971 | K72: =_xlfn.XLOOKUP( qry_Master_Clean__2[[#This Row],[Country]], Renewable!$A$2:$A$267, Renewable!$BN$2:$BN$267, "" ) -> 16.2 | L72: =qry_Master_Clean__2[[#This Row],[CO2_Tonnes]]/(qry_Master_Clean__2[[#This Row],[Population_Millions]]*1000000) -> 3.850665
A73: French Polynesia | B73: 0.3 | C73: 6.3 | D73: 3471 | E73: 0.019533245 | F73: 922867 | G73: =(qry_Master_Clean__2[[#This Row],[GDP_Billions]]*1000/qry_Master_Clean__2[[#This Row],[Population_Millions]]) -> 21000 | H73: =IF(qry_Master_Clean__2[[#This Row],[Population_Millions]]=0,"",qry_Master_Clean__2[[#This Row],[Energy_QuadBTU]]/qry_Master_Clean__2[[#This Row],[Population_Millions]]) -> 0.065110818 | I73: =_xlfn.XLOOKUP(qry_Master_Clean__2[[#This Row],[Country]],Metadata!$E:$E,Metadata!$C:$C,"Not Found") -> High income | J73: =(F73/C73) -> 146486.83 | K73: =_xlfn.XLOOKUP( qry_Master_Clean__2[[#This Row],[Country]], Renewable!$A$2:$A$267, Renewable!$BN$2:$BN$267, "" ) -> 7.4 | L73: =qry_Master_Clean__2[[#This Row],[CO2_Tonnes]]/(qry_Master_Clean__2[[#This Row],[Population_Millions]]*1000000) -> 3.0762233
A74: Gabon | B74: 2.5 | C74: 20.9 | D74: 257670 | E74: 0.058592767 | F74: 5398794 | G74: =(qry_Master_Clean__2[[#This Row],[GDP_Billions]]*1000/qry_Master_Clean__2[[#This Row],[Population_Millions]]) -> 8360 | H74: =IF(qry_Master_Clean__2[[#This Row],[Population_Millions]]=0,"",qry_Master_Clean__2[[#This Row],[Energy_QuadBTU]]/qry_Master_Clean__2[[#This Row],[Population_Millions]]) -> 0.023437107 | I74: =_xlfn.XLOOKUP(qry_Master_Clean__2[[#This Row],[Country]],Metadata!$E:$E,Metadata!$C:$C,"Not Found") -> Upper middle income | J74: =(F74/C74) -> 258315.5 | K74: =_xlfn.XLOOKUP( qry_Master_Clean__2[[#This Row],[Country]], Renewable!$A$2:$A$267, Renewable!$BN$2:$BN$267, "" ) -> 91.3 | L74: =qry_Master_Clean__2[[#This Row],[CO2_Tonnes]]/(qry_Master_Clean__2[[#This Row],[Population_Millions]]*1000000) -> 2.1595176
A75: Gambia, The | B75: 2.8 | C75: 2.4 | D75: 10120 | E75: 0.0078507186 | F75: 0 | G75: =(qry_Master_Clean__2[[#This Row],[GDP_Billions]]*1000/qry_Master_Clean__2[[#This Row],[Population_Millions]]) -> 857.14286 | H75: =IF(qry_Master_Clean__2[[#This Row],[Population_Millions]]=0,"",qry_Master_Clean__2[[#This Row],[Energy_QuadBTU]]/qry_Master_Clean__2[[#This Row],[Population_Millions]]) -> 0.0028038281 | I75: =_xlfn.XLOOKUP(qry_Master_Clean__2[[#This Row],[Country]],Metadata!$E:$E,Metadata!$C:$C,"Not Found") -> Low income | J75: =(qry_Master_Clean__2[[#This Row],[CO2_Tonnes]]/(qry_Master_Clean__2[[#This Row],[GDP_Billions]]/1000000000)) -> 0 | K75: =_xlfn.XLOOKUP( qry_Master_Clean__2[[#This Row],[Country]], Renewable!$A$2:$A$267, Renewable!$BN$2:$BN$267, "" ) -> 48.6 | L75: =qry_Master_Clean__2[[#This Row],[CO2_Tonnes]]/(qry_Master_Clean__2[[#This Row],[Population_Millions]]*1000000) -> 0
A76: Georgia | B76: 3.7 | C76: 34.2 | D76: 69490 | E76: 0.24423145 | F76: 11784258 | G76: =(qry_Master_Clean__2[[#This Row],[GDP_Billions]]*1000/qry_Master_Clean__2[[#This Row],[Population_Millions]]) -> 9243.2432 | H76: =IF(qry_Master_Clean__2[[#This Row],[Population_Millions]]=0,"",qry_Master_Clean__2[[#This Row],[Energy_QuadBTU]]/qry_Master_Clean__2[[#This Row],[Population_Millions]]) -> 0.0660085 | I76: =_xlfn.XLOOKUP(qry_Master_Clean__2[[#This Row],[Country]],Metadata!$E:$E,Metadata!$C:$C,"Not Found") -> Upper middle income | J76: =(F76/C76) -> 344568.95 | K76: =_xlfn.XLOOKUP( qry_Master_Clean__2[[#This Row],[Country]], Renewable!$A$2:$A$267, Renewable!$BN$2:$BN$267, "" ) -> 25.2 | L76: =qry_Master_Clean__2[[#This Row],[CO2_Tonnes]]/(qry_Master_Clean__2[[#This Row],[Population_Millions]]*1000000) -> 3.1849346
A77: Germany | B77: 83.5 | C77: 4685.6 | D77: 349390 | E77: 9.9248548 | F77: 572319170 | G77: =(qry_Master_Clean__2[[#This Row],[GDP_Billions]]*1000/qry_Master_Clean__2[[#This Row],[Population_Millions]]) -> 56114.97 | H77: =IF(qry_Master_Clean__2[[#This Row],[Population_Millions]]=0,"",qry_Master_Clean__2[[#This Row],[Energy_QuadBTU]]/qry_Master_Clean__2[[#This Row],[Population_Millions]]) -> 0.11886054 | I77: =_xlfn.XLOOKUP(qry_Master_Clean__2[[#This Row],[Country]],Metadata!$E:$E,Metadata!$C:$C,"Not Found") -> High income | J77: =(F77/C77) -> 122144.27 | K77: =_xlfn.XLOOKUP( qry_Master_Clean__2[[#This Row],[Country]], Renewable!$A$2:$A$267, Renewable!$BN$2:$BN$267, "" ) -> 17.6 | L77: =qry_Master_Clean__2[[#This Row],[CO2_Tonnes]]/(qry_Master_Clean__2[[#This Row],[Population_Millions]]*1000000) -> 6.8541218 | N77: Row Labels | O77: Sum of GDP_Billions | P77: Sum of GDP per Capita (US$)
A78: Ghana | B78: 34.4 | C78: 82.3 | D78: 227533 | E78: 0.38334874 | F78: 21021874 | G78: =(qry_Master_Clean__2[[#This Row],[GDP_Billions]]*1000/qry_Master_Clean__2[[#This Row],[Population_Millions]]) -> 2392.4419 | H78: =IF(qry_Master_Clean__2[[#This Row],[Population_Millions]]=0,"",qry_Master_Clean__2[[#This Row],[Energy_QuadBTU]]/qry_Master_Clean__2[[#This Row],[Population_Millions]]) -> 0.011143859 | I78: =_xlfn.XLOOKUP(qry_Master_Clean__2[[#This Row],[Country]],Metadata!$E:$E,Metadata!$C:$C,"Not Found") -> Lower middle income | J78: =(F78/C78) -> 255429.82 | K78: =_xlfn.XLOOKUP( qry_Master_Clean__2[[#This Row],[Country]], Renewable!$A$2:$A$267, Renewable!$BN$2:$BN$267, "" ) -> 39 | L78: =qry_Master_Clean__2[[#This Row],[CO2_Tonnes]]/(qry_Master_Clean__2[[#This Row],[Population_Millions]]*1000000) -> 0.61110099 | N78: United States | O78: 28751 | P78: 84536.901
A79: Greece | B79: 10.4 | C79: 256.2 | D79: 128900 | E79: 1.0292269 | F79: 53360840 | G79: =(qry_Master_Clean__2[[#This Row],[GDP_Billions]]*1000/qry_Master_Clean__2[[#This Row],[Population_Millions]]) -> 24634.615 | H79: =IF(qry_Master_Clean__2[[#This Row],[Population_Millions]]=0,"",qry_Master_Clean__2[[#This Row],[Energy_QuadBTU]]/qry_Master_Clean__2[[#This Row],[Population_Millions]]) -> 0.098964125 | I79: =_xlfn.XLOOKUP(qry_Master_Clean__2[[#This Row],[Country]],Metadata!$E:$E,Metadata!$C:$C,"Not Found") -> High income | J79: =(F79/C79) -> 208278.06 | K79: =_xlfn.XLOOKUP( qry_Master_Clean__2[[#This Row],[Country]], Renewable!$A$2:$A$267, Renewable!$BN$2:$BN$267, "" ) -> 21.5 | L79: =qry_Master_Clean__2[[#This Row],[CO2_Tonnes]]/(qry_Master_Clean__2[[#This Row],[Population_Millions]]*1000000) -> 5.13085 | N79: China | O79: 18743.8 | P79: 13302.91
A80: Greenland | B80: 0.1 | C80: 3.3 | D80: 410450 | E80: 0.0092138636 | F80: 618963 | G80: =(qry_Master_Clean__2[[#This Row],[GDP_Billions]]*1000/qry_Master_Clean__2[[#This Row],[Population_Millions]]) -> 33000 | H80: =IF(qry_Master_Clean__2[[#This Row],[Population_Millions]]=0,"",qry_Master_Clean__2[[#This Row],[Energy_QuadBTU]]/qry_Master_Clean__2[[#This Row],[Population_Millions]]) -> 0.092138636 | I80: =_xlfn.XLOOKUP(qry_Master_Clean__2[[#This Row],[Country]],Metadata!$E:$E,Metadata!$C:$C,"Not Found") -> High income | J80: =(F80/C80) -> 187564.55 | K80: =_xlfn.XLOOKUP( qry_Master_Clean__2[[#This Row],[Country]], Renewable!$A$2:$A$267, Renewable!$BN$2:$BN$267, "" ) -> 11.6 | L80: =qry_Master_Clean__2[[#This Row],[CO2_Tonnes]]/(qry_Master_Clean__2[[#This Row],[Population_Millions]]*1000000) -> 6.18963 | N80: Germany | O80: 4685.6 | P80: 56114.97
A81: Grenada | B81: 0.1 | C81: 1.4 | D81: 340 | E81: 0.0057281602 | F81: 376971 | G81: =(qry_Master_Clean__2[[#This Row],[GDP_Billions]]*1000/qry_Master_Clean__2[[#This Row],[Population_Millions]]) -> 14000 | H81: =IF(qry_Master_Clean__2[[#This Row],[Population_Millions]]=0,"",qry_Master_Clean__2[[#This Row],[Energy_QuadBTU]]/qry_Master_Clean__2[[#This Row],[Population_Millions]]) -> 0.057281602 | I81: =_xlfn.XLOOKUP(qry_Master_Clean__2[[#This Row],[Country]],Metadata!$E:$E,Metadata!$C:$C,"Not Found") -> Upper middle income | J81: =(F81/C81) -> 269265 | K81: =_xlfn.XLOOKUP( qry_Master_Clean__2[[#This Row],[Country]], Renewable!$A$2:$A$267, Renewable!$BN$2:$BN$267, "" ) -> 10.2 | L81: =qry_Master_Clean__2[[#This Row],[CO2_Tonnes]]/(qry_Master_Clean__2[[#This Row],[Population_Millions]]*1000000) -> 3.76971 | N81: Japan | O81: 4027.6 | P81: 32480.645
A82: Guam | B82: 0.2 | C82: 6.9 | D82: 540 | E82: 0.019062506 | F82: 0 | G82: =(qry_Master_Clean__2[[#This Row],[GDP_Billions]]*1000/qry_Master_Clean__2[[#This Row],[Population_Millions]]) -> 34500 | H82: =IF(qry_Master_Clean__2[[#This Row],[Population_Millions]]=0,"",qry_Master_Clean__2[[#This Row],[Energy_QuadBTU]]/qry_Master_Clean__2[[#This Row],[Population_Millions]]) -> 0.095312531 | I82: =_xlfn.XLOOKUP(qry_Master_Clean__2[[#This Row],[Country]],Metadata!$E:$E,Metadata!$C:$C,"Not Found") -> High income | J82: =(qry_Master_Clean__2[[#This Row],[CO2_Tonnes]]/(qry_Master_Clean__2[[#This Row],[GDP_Billions]]/1000000000)) -> 0 | K82: =_xlfn.XLOOKUP( qry_Master_Clean__2[[#This Row],[Country]], Renewable!$A$2:$A$267, Renewable!$BN$2:$BN$267, "" ) -> 4.5 | L82: =qry_Master_Clean__2[[#This Row],[CO2_Tonnes]]/(qry_Master_Clean__2[[#This Row],[Population_Millions]]*1000000) -> 0 | N82: India | O82: 3909.9 | P82: 2694.8101
A83: Guatemala | B83: 18.4 | C83: 113.2 | D83: 107160 | E83: 0.34104447 | F83: 19880430 | G83: =(qry_Master_Clean__2[[#This Row],[GDP_Billions]]*1000/qry_Master_Clean__2[[#This Row],[Population_Millions]]) -> 6152.1739 | H83: =IF(qry_Master_Clean__2[[#This Row],[Population_Millions]]=0,"",qry_Master_Clean__2[[#This Row],[Energy_QuadBTU]]/qry_Master_Clean__2[[#This Row],[Population_Millions]]) -> 0.018535025 | I83: =_xlfn.XLOOKUP(qry_Master_Clean__2[[#This Row],[Country]],Metadata!$E:$E,Metadata!$C:$C,"Not Found") -> Upper middle income | J83: =(F83/C83) -> 175622.17 | K83: =_xlfn.XLOOKUP( qry_Master_Clean__2[[#This Row],[Country]], Renewable!$A$2:$A$267, Renewable!$BN$2:$BN$267, "" ) -> 62.1 | L83: =qry_Master_Clean__2[[#This Row],[CO2_Tonnes]]/(qry_Master_Clean__2[[#This Row],[Population_Millions]]*1000000) -> 1.0804582 | N83: United Kingdom | O83: 3686 | P83: 53265.896
A84: Guinea | B84: 14.8 | C84: 25 | D84: 245720 | E84: 0.074685896 | F84: 4026185 | G84: =(qry_Master_Clean__2[[#This Row],[GDP_Billions]]*1000/qry_Master_Clean__2[[#This Row],[Population_Millions]]) -> 1689.1892 | H84: =IF(qry_Master_Clean__2[[#This Row],[Population_Millions]]=0,"",qry_Master_Clean__2[[#This Row],[Energy_QuadBTU]]/qry_Master_Clean__2[[#This Row],[Population_Millions]]) -> 0.0050463443 | I84: =_xlfn.XLOOKUP(qry_Master_Clean__2[[#This Row],[Country]],Metadata!$E:$E,Metadata!$C:$C,"Not Found") -> Lower middle income | J84: =(F84/C84) -> 161047.4 | K84: =_xlfn.XLOOKUP( qry_Master_Clean__2[[#This Row],[Country]], Renewable!$A$2:$A$267, Renewable!$BN$2:$BN$267, "" ) -> 66.8 | L84: =qry_Master_Clean__2[[#This Row],[CO2_Tonnes]]/(qry_Master_Clean__2[[#This Row],[Population_Millions]]*1000000) -> 0.27203953 | N84: France | O84: 3160.4 | P84: 46069.971
A85: Guinea-Bissau | B85: 2.2 | C85: 2.2 | D85: 28120 | E85: 0.0052019959 | F85: 342189 | G85: =(qry_Master_Clean__2[[#This Row],[GDP_Billions]]*1000/qry_Master_Clean__2[[#This Row],[Population_Millions]]) -> 1000 | H85: =IF(qry_Master_Clean__2[[#This Row],[Population_Millions]]=0,"",qry_Master_Clean__2[[#This Row],[Energy_QuadBTU]]/qry_Master_Clean__2[[#This Row],[Population_Millions]]) -> 0.0023645436 | I85: =_xlfn.XLOOKUP(qry_Master_Clean__2[[#This Row],[Country]],Metadata!$E:$E,Metadata!$C:$C,"Not Found") -> Low income | J85: =(F85/C85) -> 155540.45 | K85: =_xlfn.XLOOKUP( qry_Master_Clean__2[[#This Row],[Country]], Renewable!$A$2:$A$267, Renewable!$BN$2:$BN$267, "" ) -> 87.4 | L85: =qry_Master_Clean__2[[#This Row],[CO2_Tonnes]]/(qry_Master_Clean__2[[#This Row],[Population_Millions]]*1000000) -> 0.15554045 | N85: Italy | O85: 2380.8 | P85: 40352.542
A86: Guyana | B86: 0.8 | C86: 24.7 | D86: 211140 | E86: 0.056118265 | F86: 4510330 | G86: =(qry_Master_Clean__2[[#This Row],[GDP_Billions]]*1000/qry_Master_Clean__2[[#This Row],[Population_Millions]]) -> 30875 | H86: =IF(qry_Master_Clean__2[[#This Row],[Population_Millions]]=0,"",qry_Master_Clean__2[[#This Row],[Energy_QuadBTU]]/qry_Master_Clean__2[[#This Row],[Population_Millions]]) -> 0.070147832 | I86: =_xlfn.XLOOKUP(qry_Master_Clean__2[[#This Row],[Country]],Metadata!$E:$E,Metadata!$C:$C,"Not Found") -> High income | J86: =(F86/C86) -> 182604.45 | K86: =_xlfn.XLOOKUP( qry_Master_Clean__2[[#This Row],[Country]], Renewable!$A$2:$A$267, Renewable!$BN$2:$BN$267, "" ) -> 13.2 | L86: =qry_Master_Clean__2[[#This Row],[CO2_Tonnes]]/(qry_Master_Clean__2[[#This Row],[Population_Millions]]*1000000) -> 5.6379125 | N86: Canada | O86: 2243.6 | P86: 54324.455
A87: Haiti | B87: 11.8 | C87: 25.2 | D87: 27560 | E87: 0.024193538 | F87: 2970693 | G87: =(qry_Master_Clean__2[[#This Row],[GDP_Billions]]*1000/qry_Master_Clean__2[[#This Row],[Population_Millions]]) -> 2135.5932 | H87: =IF(qry_Master_Clean__2[[#This Row],[Population_Millions]]=0,"",qry_Master_Clean__2[[#This Row],[Energy_QuadBTU]]/qry_Master_Clean__2[[#This Row],[Population_Millions]]) -> 0.0020502998 | I87: =_xlfn.XLOOKUP(qry_Master_Clean__2[[#This Row],[Country]],Metadata!$E:$E,Metadata!$C:$C,"Not Found") -> Lower middle income | J87: =(F87/C87) -> 117884.64 | K87: =_xlfn.XLOOKUP( qry_Master_Clean__2[[#This Row],[Country]], Renewable!$A$2:$A$267, Renewable!$BN$2:$BN$267, "" ) -> 76.7 | L87: =qry_Master_Clean__2[[#This Row],[CO2_Tonnes]]/(qry_Master_Clean__2[[#This Row],[Population_Millions]]*1000000) -> 0.25175364 | N87: Brazil | O87: 2185.8 | P87: 10310.377
A88: Honduras | B88: 10.8 | C88: 37.1 | D88: 111890 | E88: 0.19362043 | F88: 12854842 | G88: =(qry_Master_Clean__2[[#This Row],[GDP_Billions]]*1000/qry_Master_Clean__2[[#This Row],[Population_Millions]]) -> 3435.1852 | H88: =IF(qry_Master_Clean__2[[#This Row],[Population_Millions]]=0,"",qry_Master_Clean__2[[#This Row],[Energy_QuadBTU]]/qry_Master_Clean__2[[#This Row],[Population_Millions]]) -> 0.017927818 | I88: =_xlfn.XLOOKUP(qry_Master_Clean__2[[#This Row],[Country]],Metadata!$E:$E,Metadata!$C:$C,"Not Found") -> Lower middle income | J88: =(F88/C88) -> 346491.7 | K88: =_xlfn.XLOOKUP( qry_Master_Clean__2[[#This Row],[Country]], Renewable!$A$2:$A$267, Renewable!$BN$2:$BN$267, "" ) -> 45.9 | L88: =qry_Master_Clean__2[[#This Row],[CO2_Tonnes]]/(qry_Master_Clean__2[[#This Row],[Population_Millions]]*1000000) -> 1.1902631 | N88: Grand Total | O88: 73774.5 | P88: 393453.48
A89: Hong Kong SAR, China | B89: 7.5 | C89: 406.9 | D89: 1050 | E89: 0 | F89: 0 | G89: =(qry_Master_Clean__2[[#This Row],[GDP_Billions]]*1000/qry_Master_Clean__2[[#This Row],[Population_Millions]]) -> 54253.333 | H89: =IF(qry_Master_Clean__2[[#This Row],[Population_Millions]]=0,"",qry_Master_Clean__2[[#This Row],[Energy_QuadBTU]]/qry_Master_Clean__2[[#This Row],[Population_Millions]]) -> 0 | I89: =_xlfn.XLOOKUP(qry_Master_Clean__2[[#This Row],[Country]],Metadata!$E:$E,Metadata!$C:$C,"Not Found") -> High income | J89: =(qry_Master_Clean__2[[#This Row],[CO2_Tonnes]]/(qry_Master_Clean__2[[#This Row],[GDP_Billions]]/1000000000)) -> 0 | K89: =_xlfn.XLOOKUP( qry_Master_Clean__2[[#This Row],[Country]], Renewable!$A$2:$A$267, Renewable!$BN$2:$BN$267, "" ) -> 0.4 | L89: =qry_Master_Clean__2[[#This Row],[CO2_Tonnes]]/(qry_Master_Clean__2[[#This Row],[Population_Millions]]*1000000) -> 0
A90: Hungary | B90: 9.6 | C90: 222.7 | D90: 91260 | E90: 0.94389699 | F90: 40017292 | G90: =(qry_Master_Clean__2[[#This Row],[GDP_Billions]]*1000/qry_Master_Clean__2[[#This Row],[Population_Millions]]) -> 23197.917 | H90: =IF(qry_Master_Clean__2[[#This Row],[Population_Millions]]=0,"",qry_Master_Clean__2[[#This Row],[Energy_QuadBTU]]/qry_Master_Clean__2[[#This Row],[Population_Millions]]) -> 0.098322603 | I90: =_xlfn.XLOOKUP(qry_Master_Clean__2[[#This Row],[Country]],Metadata!$E:$E,Metadata!$C:$C,"Not Found") -> High income | J90: =(F90/C90) -> 179691.48 | K90: =_xlfn.XLOOKUP( qry_Master_Clean__2[[#This Row],[Country]], Renewable!$A$2:$A$267, Renewable!$BN$2:$BN$267, "" ) -> 15.3 | L90: =qry_Master_Clean__2[[#This Row],[CO2_Tonnes]]/(qry_Master_Clean__2[[#This Row],[Population_Millions]]*1000000) -> 4.1684679
A91: Iceland | B91: 0.4 | C91: 33.3 | D91: 100830 | E91: 0.11202451 | F91: 3803011 | G91: =(qry_Master_Clean__2[[#This Row],[GDP_Billions]]*1000/qry_Master_Clean__2[[#This Row],[Population_Millions]]) -> 83250 | H91: =IF(qry_Master_Clean__2[[#This Row],[Population_Millions]]=0,"",qry_Master_Clean__2[[#This Row],[Energy_QuadBTU]]/qry_Master_Clean__2[[#This Row],[Population_Millions]]) -> 0.28006128 | I91: =_xlfn.XLOOKUP(qry_Master_Clean__2[[#This Row],[Country]],Metadata!$E:$E,Metadata!$C:$C,"Not Found") -> High income | J91: =(F91/C91) -> 114204.53 | K91: =_xlfn.XLOOKUP( qry_Master_Clean__2[[#This Row],[Country]], Renewable!$A$2:$A$267, Renewable!$BN$2:$BN$267, "" ) -> 82.4 | L91: =qry_Master_Clean__2[[#This Row],[CO2_Tonnes]]/(qry_Master_Clean__2[[#This Row],[Population_Millions]]*1000000) -> 9.5075275
A92: India | B92: 1450.9 | C92: 3909.9 | D92: 2973190 | E92: 37.490302 | F92: 3193478100 | G92: =(qry_Master_Clean__2[[#This Row],[GDP_Billions]]*1000/qry_Master_Clean__2[[#This Row],[Population_Millions]]) -> 2694.8101 | H92: =IF(qry_Master_Clean__2[[#This Row],[Population_Millions]]=0,"",qry_Master_Clean__2[[#This Row],[Energy_QuadBTU]]/qry_Master_Clean__2[[#This Row],[Population_Millions]]) -> 0.025839343 | I92: =_xlfn.XLOOKUP(qry_Master_Clean__2[[#This Row],[Country]],Metadata!$E:$E,Metadata!$C:$C,"Not Found") -> Lower middle income | J92: =(F92/C92) -> 816767.21 | K92: =_xlfn.XLOOKUP( qry_Master_Clean__2[[#This Row],[Country]], Renewable!$A$2:$A$267, Renewable!$BN$2:$BN$267, "" ) -> 34.9 | L92: =qry_Master_Clean__2[[#This Row],[CO2_Tonnes]]/(qry_Master_Clean__2[[#This Row],[Population_Millions]]*1000000) -> 2.2010325
A93: Indonesia | B93: 283.5 | C93: 1396.3 | D93: 1892555 | E93: 11.37704 | F93: 812220200 | G93: =(qry_Master_Clean__2[[#This Row],[GDP_Billions]]*1000/qry_Master_Clean__2[[#This Row],[Population_Millions]]) -> 4925.2205 | H93: =IF(qry_Master_Clean__2[[#This Row],[Population_Millions]]=0,"",qry_Master_Clean__2[[#This Row],[Energy_QuadBTU]]/qry_Master_Clean__2[[#This Row],[Population_Millions]]) -> 0.040130652 | I93: =_xlfn.XLOOKUP(qry_Master_Clean__2[[#This Row],[Country]],Metadata!$E:$E,Metadata!$C:$C,"Not Found") -> Upper middle income | J93: =(F93/C93) -> 581694.62 | K93: =_xlfn.XLOOKUP( qry_Master_Clean__2[[#This Row],[Country]], Renewable!$A$2:$A$267, Renewable!$BN$2:$BN$267, "" ) -> 20.2 | L93: =qry_Master_Clean__2[[#This Row],[CO2_Tonnes]]/(qry_Master_Clean__2[[#This Row],[Population_Millions]]*1000000) -> 2.8649743
A94: Iran, Islamic Rep. | B94: 91.6 | C94: 475.3 | D94: 1622500 | E94: 0 | F94: 0 | G94: =(qry_Master_Clean__2[[#This Row],[GDP_Billions]]*1000/qry_Master_Clean__2[[#This Row],[Population_Millions]]) -> 5188.8646 | H94: =IF(qry_Master_Clean__2[[#This Row],[Population_Millions]]=0,"",qry_Master_Clean__2[[#This Row],[Energy_QuadBTU]]/qry_Master_Clean__2[[#This Row],[Population_Millions]]) -> 0 | I94: =_xlfn.XLOOKUP(qry_Master_Clean__2[[#This Row],[Country]],Metadata!$E:$E,Metadata!$C:$C,"Not Found") -> Upper middle income | J94: =(qry_Master_Clean__2[[#This Row],[CO2_Tonnes]]/(qry_Master_Clean__2[[#This Row],[GDP_Billions]]/1000000000)) -> 0 | K94: =_xlfn.XLOOKUP( qry_Master_Clean__2[[#This Row],[Country]], Renewable!$A$2:$A$267, Renewable!$BN$2:$BN$267, "" ) -> 0.9 | L94: =qry_Master_Clean__2[[#This Row],[CO2_Tonnes]]/(qry_Master_Clean__2[[#This Row],[Population_Millions]]*1000000) -> 0
A95: Iraq | B95: 46 | C95: 279.6 | D95: 434130 | E95: 2.9150554 | F95: 233635500 | G95: =(qry_Master_Clean__2[[#This Row],[GDP_Billions]]*1000/qry_Master_Clean__2[[#This Row],[Population_Millions]]) -> 6078.2609 | H95: =IF(qry_Master_Clean__2[[#This Row],[Population_Millions]]=0,"",qry_Master_Clean__2[[#This Row],[Energy_QuadBTU]]/qry_Master_Clean__2[[#This Row],[Population_Millions]]) -> 0.063370769 | I95: =_xlfn.XLOOKUP(qry_Master_Clean__2[[#This Row],[Country]],Metadata!$E:$E,Metadata!$C:$C,"Not Found") -> Upper middle income | J95: =(F95/C95) -> 835606.22 | K95: =_xlfn.XLOOKUP( qry_Master_Clean__2[[#This Row],[Country]], Renewable!$A$2:$A$267, Renewable!$BN$2:$BN$267, "" ) -> 1.1 | L95: =qry_Master_Clean__2[[#This Row],[CO2_Tonnes]]/(qry_Master_Clean__2[[#This Row],[Population_Millions]]*1000000) -> 5.0790326
A96: Ireland | B96: 5.4 | C96: 609.2 | D96: 68890 | E96: 0.60220082 | F96: 33310624 | G96: =(qry_Master_Clean__2[[#This Row],[GDP_Billions]]*1000/qry_Master_Clean__2[[#This Row],[Population_Millions]]) -> 112814.81 | H96: =IF(qry_Master_Clean__2[[#This Row],[Population_Millions]]=0,"",qry_Master_Clean__2[[#This Row],[Energy_QuadBTU]]/qry_Master_Clean__2[[#This Row],[Population_Millions]]) -> 0.11151867 | I96: =_xlfn.XLOOKUP(qry_Master_Clean__2[[#This Row],[Country]],Metadata!$E:$E,Metadata!$C:$C,"Not Found") -> High income | J96: =(F96/C96) -> 54679.291 | K96: =_xlfn.XLOOKUP( qry_Master_Clean__2[[#This Row],[Country]], Renewable!$A$2:$A$267, Renewable!$BN$2:$BN$267, "" ) -> 12.7 | L96: =qry_Master_Clean__2[[#This Row],[CO2_Tonnes]]/(qry_Master_Clean__2[[#This Row],[Population_Millions]]*1000000) -> 6.1686341
A97: Isle of Man | B97: 0.1 | C97: 7.4 | D97: 570 | E97: 0 | F97: 0 | G97: =(qry_Master_Clean__2[[#This Row],[GDP_Billions]]*1000/qry_Master_Clean__2[[#This Row],[Population_Millions]]) -> 74000 | H97: =IF(qry_Master_Clean__2[[#This Row],[Population_Millions]]=0,"",qry_Master_Clean__2[[#This Row],[Energy_QuadBTU]]/qry_Master_Clean__2[[#This Row],[Population_Millions]]) -> 0 | I97: =_xlfn.XLOOKUP(qry_Master_Clean__2[[#This Row],[Country]],Metadata!$E:$E,Metadata!$C:$C,"Not Found") -> High income | J97: =(qry_Master_Clean__2[[#This Row],[CO2_Tonnes]]/(qry_Master_Clean__2[[#This Row],[GDP_Billions]]/1000000000)) -> 0 | K97: =_xlfn.XLOOKUP( qry_Master_Clean__2[[#This Row],[Country]], Renewable!$A$2:$A$267, Renewable!$BN$2:$BN$267, "" ) -> 3.2 | L97: =qry_Master_Clean__2[[#This Row],[CO2_Tonnes]]/(qry_Master_Clean__2[[#This Row],[Population_Millions]]*1000000) -> 0
A98: Israel | B98: 10 | C98: 540.4 | D98: 21640 | E98: 1.0420164 | F98: 52637136 | G98: =(qry_Master_Clean__2[[#This Row],[GDP_Billions]]*1000/qry_Master_Clean__2[[#This Row],[Population_Millions]]) -> 54040 | H98: =IF(qry_Master_Clean__2[[#This Row],[Population_Millions]]=0,"",qry_Master_Clean__2[[#This Row],[Energy_QuadBTU]]/qry_Master_Clean__2[[#This Row],[Population_Millions]]) -> 0.10420164 | I98: =_xlfn.XLOOKUP(qry_Master_Clean__2[[#This Row],[Country]],Metadata!$E:$E,Metadata!$C:$C,"Not Found") -> High income | J98: =(F98/C98) -> 97404.027 | K98: =_xlfn.XLOOKUP( qry_Master_Clean__2[[#This Row],[Country]], Renewable!$A$2:$A$267, Renewable!$BN$2:$BN$267, "" ) -> 6.2 | L98: =qry_Master_Clean__2[[#This Row],[CO2_Tonnes]]/(qry_Master_Clean__2[[#This Row],[Population_Millions]]*1000000) -> 5.2637136
A99: Italy | B99: 59 | C99: 2380.8 | D99: 295717 | E99: 5.5713747 | F99: 301929760 | G99: =(qry_Master_Clean__2[[#This Row],[GDP_Billions]]*1000/qry_Master_Clean__2[[#This Row],[Population_Millions]]) -> 40352.542 | H99: =IF(qry_Master_Clean__2[[#This Row],[Population_Millions]]=0,"",qry_Master_Clean__2[[#This Row],[Energy_QuadBTU]]/qry_Master_Clean__2[[#This Row],[Population_Millions]]) -> 0.09443008 | I99: =_xlfn.XLOOKUP(qry_Master_Clean__2[[#This Row],[Country]],Metadata!$E:$E,Metadata!$C:$C,"Not Found") -> High income | J99: =(F99/C99) -> 126818.62 | K99: =_xlfn.XLOOKUP( qry_Master_Clean__2[[#This Row],[Country]], Renewable!$A$2:$A$267, Renewable!$BN$2:$BN$267, "" ) -> 17.5 | L99: =qry_Master_Clean__2[[#This Row],[CO2_Tonnes]]/(qry_Master_Clean__2[[#This Row],[Population_Millions]]*1000000) -> 5.1174536
A100: Jamaica | B100: 2.8 | C100: 22 | D100: 10830 | E100: 0.12113942 | F100: 8401763 | G100: =(qry_Master_Clean__2[[#This Row],[GDP_Billions]]*1000/qry_Master_Clean__2[[#This Row],[Population_Millions]]) -> 7857.1429 | H100: =IF(qry_Master_Clean__2[[#This Row],[Population_Millions]]=0,"",qry_Master_Clean__2[[#This Row],[Energy_QuadBTU]]/qry_Master_Clean__2[[#This Row],[Population_Millions]]) -> 0.043264079 | I100: =_xlfn.XLOOKUP(qry_Master_Clean__2[[#This Row],[Country]],Metadata!$E:$E,Metadata!$C:$C,"Not Found") -> Upper middle income | J100: =(F100/C100) -> 381898.32 | K100: =_xlfn.XLOOKUP( qry_Master_Clean__2[[#This Row],[Country]], Renewable!$A$2:$A$267, Renewable!$BN$2:$BN$267, "" ) -> 10.5 | L100: =qry_Master_Clean__2[[#This Row],[CO2_Tonnes]]/(qry_Master_Clean__2[[#This Row],[Population_Millions]]*1000000) -> 3.0006296
...

Sheet Data_Dictionary
A1: Dataset | B1: Source | C1: Unit | D1: Frequency | E1: Years | F1: Primary Key
A2: Population | B2: World Bank | C2: Millions | D2: Annual | E2: 2020–2024 | F2: Country + Year
A3: GDP | B3: World Bank | C3: Billions USD | D3: Annual | E3: 2015–2024 | F3: Country + Year
A4: Land Area | B4: World Bank | C4: km² | D4: Static | E4: Latest | F4: Country
A5: Energy Consumption | B5: EIA | C5: Quad BTU | D5: Annual | E5: 1980–2024 | F5: Country + Year
A6: CO₂ Emissions | B6: Our World in Data / World Bank | C6: Tonnes | D6: Annual | E6: 1949–2024 | F6: Country + Year

Sheet Audit dataset
A1: Dataset | B1: Rows | C1: Missing Values | D1: Issues
A2: Countries | B2: 214 | C2: 0
A3: Population
A4: GDP | B4: 215 | C4: 4 | D4: Some missing GDP values
A5: Population | B5: 215 | C5: 0 | D5: OK
A6: Energy | B6: 215 | C6: 12 | D6: Missing for some countries
A7: Emissions | B7: 215 | C7: 6 | D7: Country names need checking

Sheet Countries_Population
A1: Country | B1: Population_2000_Millions | C1: Population_2024_Millions | D1: Population_Growth_2000_2024_Pct | E1: Age_0_14_2024_Pct | F1: Age_15_64_2024_Pct | G1: Age_65_Plus_2024_Pct | H1: Dependency_Young_2024_Pct | I1: Dependency_Old_2024_Pct | J1: Death_Rate_2024 | K1: Birth_Rate_2024
A2: Afghanistan | B2: 20.1 | C2: 42.6 | D2: 3.1 | E2: 43 | F2: 55 | G2: 2 | H2: 78 | I2: 4 | J2: 6 | K2: 35
A3: Albania | B3: 3.1 | C3: 2.4 | D3: -1.1 | E3: 17 | F3: 66 | G3: 17 | H3: 25 | I3: 26 | J3: 8 | K3: 10
A4: Algeria | B4: 30.9 | C4: 46.8 | D4: 1.7 | E4: 30 | F4: 63 | G4: 7 | H4: 48 | I4: 10 | J4: 5 | K4: 19
A5: American Samoa | B5: 0.1 | C5: 0 | D5: -0.8 | E5: 27 | F5: 65 | G5: 8 | H5: 42 | I5: 12 | J5: 7 | K5: 15
A6: Andorra | B6: 0.1 | C6: 0.1 | D6: 0.9 | E6: 12 | F6: 72 | G6: 16 | H6: 16 | I6: 22 | J6: 6 | K6: 7
A7: Angola | B7: 16.2 | C7: 37.9 | D7: 3.5 | E7: 44 | F7: 53 | G7: 3 | H7: 84 | I7: 5 | J7: 7 | K7: 37
A8: Antigua and Barbuda | B8: 0.1 | C8: 0.1 | D8: 0.9 | E8: 18 | F8: 70 | G8: 12 | H8: 25 | I8: 17 | J8: 7 | K8: 12
A9: Argentina | B9: 37.2 | C9: 45.7 | D9: 0.9 | E9: 22 | F9: 66 | G9: 12 | H9: 33 | I9: 19 | J9: 8 | K9: 11
A10: Armenia | B10: 3.2 | C10: 3 | D10: -0.3 | E10: 19 | F10: 67 | G10: 14 | H10: 29 | I10: 20 | J10: 8 | K10: 11
A11: Aruba | B11: 0.1 | C11: 0.1 | D11: 0.7 | E11: 17 | F11: 66 | G11: 17 | H11: 25 | I11: 26 | J11: 8 | K11: 8
A12: Australia | B12: 19 | C12: 27.2 | D12: 1.5 | E12: 18 | F12: 64 | G12: 18 | H12: 28 | I12: 28 | J12: 7 | K12: 11
A13: Austria | B13: 8 | C13: 9.2 | D13: 0.6 | E13: 14 | F13: 65 | G13: 21 | H13: 22 | I13: 32 | J13: 10 | K13: 8
... A215: Zimbabwe | B215: 11.9 | C215: 16.6 | D215: 1.4 | E215: 41 | F215: 56 | G215: 4 | H215: 74 | I215: 6 | J215: 7 | K215: 30
A216: =COUNTA(A2:A215) -> 214
A218: World | B218: 6161.9 | C218: 8141.8 | D218: 1.2 | E218: 25 | F218: 65 | G218: 10 | H218: 38 | I218: 16 | J218: 8 | K218: 16
A219: East Asia & Pacific | B219: 2050.1 | C219: 2388.3 | D219: 0.6 | E219: 18 | F219: 68 | G219: 14 | H219: 26 | I219: 20 | J219: 8 | K219: 9
A220: Europe & Central Asia | B220: 865.4 | C220: 928.3 | D220: 0.3 | E220: 17 | F220: 64 | G220: 18 | H220: 27 | I220: 28 | J220: 10 | K220: 10
A221: Latin America & Caribbean | B221: 520.3 | C221: 662.2 | D221: 1 | E221: 23 | F221: 68 | G221: 10 | H221: 33 | I221: 15 | J221: 7 | K221: 14
A222: Middle East, North Africa, Afghanistan & Pakistan | B222: 494.9 | C222: 813.1 | D222: 2.1 | E222: 32 | F222: 63 | G222: 5 | H222: 51 | I222: 8 | J222: 5 | K222: 23
A223: North America | B223: 312.9 | C223: 381.5 | D223: 0.8 | E223: 17 | F223: 65 | G223: 18 | H223: 26 | I223: 28 | J223: 9 | K223: 10
A224: South Asia | B224: 1237.2 | C224: 1677.4 | D224: 1.3 | E224: 25 | F224: 68 | G224: 7 | H224: 37 | I224: 11 | J224: 6 | K224: 16
A225: Sub-Saharan Africa | B225: 681.1 | C225: 1291 | D225: 2.7 | E225: 41 | F225: 56 | G225: 3 | H225: 73 | I225: 6 | J225: 8 | K225: 33
A226: Low income | B226: 322.7 | C226: 624.6 | D226: 2.8 | E226: 42 | F226: 55 | G226: 3 | H226: 75 | I226: 6 | J226: 7 | K226: 35
A227: Lower middle income | B227: 2126.6 | C227: 3121 | D227: 1.6 | E227: 30 | F227: 64 | G227: 6 | H227: 46 | I227: 9 | J227: 7 | K227: 21
A228: Upper middle income | B228: 2365 | C228: 2817.9 | D228: 0.7 | E228: 20 | F228: 68 | G228: 12 | H228: 29 | I228: 18 | J228: 7 | K228: 10
A229: High income | B229: 1255.7 | C229: 1417.8 | D229: 0.5 | E229: 16 | F229: 65 | G229: 20 | H229: 24 | I229: 30 | J229: 10 | K229: 9
A233: Most Recent Value (MRV) if data for the specified year or full period are not available; or growth rate is calculated for less than the full period.
A235: 2.1 Population dynamics
A237: World Development Indicators , THE WORLD BANK
A238: Last updated date 04/08/2026
A240: About the Data
A242: Population, total
A243: Long definition
A244: Total population is based on the de facto definition of population, which counts all residents regardless of legal status or citizenship. The values shown are midyear estimates.
A246: Source
A247: World Population Prospects, United Nations (UN), uri: https://population.un.org/wpp/, publisher: UN Population Division; Statistical databases and publications from national statistical offices, National Statistical Offices, uri: https://unstats.un.org/home/nso_sites/, publisher: National Statistical Offices; Eurostat: Demographic Statistics, Eurostat (ESTAT), uri: https://ec.europa.eu/eurostat/data/database?node_code=earn_ses_monthly, publisher: Eurostat; Population and Vital Statistics Report (various years), United Nations (UN), uri: https://unstats.un.org, publisher: UN Statistics Division
A249: Population ages 0-14 (% of total population)
A250: Long definition
... A299: Please see the online table at http://wdi.worldbank.org/table/2.1 for observation-level metadata, which can be downloaded in Excel.

Sheet Countires_Land
A1: Country | B1: Rural_Population_2022 | C1: Rural__Population_Growth_(Annual_%)_2022 | D1: Land_Area_(Sq_Km)_2021 | E1: Forest_Area__(%_Of_Land_Area)_2021 | F1: Permanent_Cropland_(%_Of_Land_Area)_2021 | G1: Arable_Land_(%_Of_Land_Area)_2021 | H1: Arable_Land_(Hectares_Per_Person)_2021
A2: Afghanistan | B2: 30274.28 | C2: 1.37 | D2: 652230 | E2: 1.85 | F2: 0.41 | G2: 12 | H2: 0.2
A3: Albania | B3: 1033.01 | C3: -2.39 | D3: 27400 | E3: 28.79 | F3: 3.2 | G3: 21.89 | H3: 0.24
A4: Algeria | B4: 11742.45 | C4: -0.56 | D4: 2381740 | E4: 0.82 | F4: 0.39 | G4: 3.16 | H4: 0.17
A5: American Samoa | B5: 8.8 | C5: 0.51 | D5: 200 | E5: 85.5 | F5: 9.65 | G5: 4.85 | H5: 0.02
A6: Andorra | B6: 8.96 | C6: 0.89 | D6: 470 | E6: 34.04 | F6: 0.02 | G6: 1.59 | H6: 0.01
A7: Angola | B7: 11028.82 | C7: 0.6 | D7: 1246700 | E7: 52.98 | F7: 0.25 | G7: 4.29 | H7: 0.15
A8: Antigua and Barbuda | B8: 70.08 | C8: 0.62 | D8: 440 | E8: 18.3 | F8: 2.27 | G8: 9.09 | H8: 0.04
A9: Argentina | B9: 3581.4 | C9: -0.84 | D9: 2736690 | E9: 10.4 | F9: 0.39 | G9: 15.43 | H9: 0.93
A10: Armenia | B10: 1022.52 | C10: -0.36 | D10: 28197.09 | E10: 11.64 | F10: 2.14 | G10: 15.73 | H10: 0.15
A11: Aruba | B11: 40.91 | C11: -0.24 | D11: 180 | E11: 2.33 | F11: .. | G11: 11.11 | H11: 0.02
A12: Australia | B12: 3295.45 | C12: 0.51 | D12: 7692020 | E12: 17.42 | F12: 0.05 | G12: 4.06 | H12: 1.22
A13: Austria | B13: 2803.15 | C13: 0.23 | D13: 82520 | E13: 47.17 | F13: 0.82 | G13: 16.03 | H13: 0.15
A14: Azerbaijan | B14: 4215.09 | C14: -0.13 | D14: 82650 | E14: 13.83 | F14: 3.32 | G14: 25.28 | H14: 0.21
A15: Bahamas, The | B15: 74.26 | C15: 1.14 | D15: 10010 | E15: 50.94 | F15: 0.3 | G15: 0.8 | H15: 0.02
A16: Bahrain | B16: 0 | C16: .. | D16: 790 | E16: 0.91 | F16: 2.53 | G16: 2.66 | H16: 0
A17: Bangladesh | B17: 115734.37 | C17: 0.62 | D17: 130170 | E17: 14.47 | F17: 7.25 | G17: 60.49 | H17: 0.05
A18: Barbados | B18: 114.75 | C18: -0.02 | D18: 430 | E18: 14.65 | F18: 2.33 | G18: 16.28 | H18: 0.02
A19: Belarus | B19: 1986.5 | C19: -2.38 | D19: 202950 | E19: 43.27 | F19: 0.47 | G19: 27.71 | H19: 0.6
A20: Belgium | B20: 1461.29 | C20: 0.34 | D20: 30494 | E20: 22.6 | F20: 0.78 | G20: 28.39 | H20: 0.07
A21: Belize | B21: 233.03 | C21: 2.29 | D21: 22810 | E21: 55.5 | F21: 1.4 | G21: 4.38 | H21: 0.25
A22: Benin | B22: 6747.29 | C22: 1 | D22: 112760 | E22: 27.36 | F22: 5.2 | G22: 30.92 | H22: 0.26
A23: Bermuda | B23: 0 | C23: .. | D23: 54 | E23: 18.52 | F23: .. | G23: 5.56 | H23: 0
A24: Bhutan | B24: 461.24 | C24: -0.36 | D24: 38140 | E24: 71.5 | F24: 0.26 | G24: 2.54 | H24: 0.13
A25: Bolivia | B25: 3546.43 | C25: 0.18 | D25: 1083300 | E25: 46.73 | F25: 0.23 | G25: 4.99 | H25: 0.45
A26: Bosnia and Herzegovina | B26: 1569.66 | C26: -2.32 | D26: 51200 | E26: 42.73 | F26: 2.11 | G26: 19.69 | H26: 0.31
A27: Botswana | B27: 815.19 | C27: 1.38 | D27: 566730 | E27: 26.71 | F27: 0 | G27: 0.46 | H27: 0.11
A28: Brazil | B28: 26604.7 | C28: -1.31 | D28: 8358140 | E28: 59.27 | F28: 0.93 | G28: 6.66 | H28: 0.27
A29: British Virgin Islands | B29: 17.32 | C29: -0.46 | D29: 150 | E29: 24.13 | F29: 6.67 | G29: 6.67 | H29: 0.03
A30: Brunei Darussalam | B30: 114.86 | C30: 0.76 | D30: 5270 | E30: 72.11 | F30: 1.14 | G30: 0.76 | H30: 0.01
A31: Bulgaria | B31: 1714.55 | C31: -1.15 | D31: 108560 | E31: 35.98 | F31: 1.37 | G31: 32.24 | H31: 0.54
A32: Burkina Faso | B32: 16368.77 | C32: 1.67 | D32: 273600 | E32: 22.54 | F32: 2.3 | G32: 28.44 | H32: 0.35
A33: Burundi | B33: 10347.8 | C33: 1.16 | D33: 25680 | E33: 10.89 | F33: 13.63 | G33: 49.45 | H33: 0.1
A34: Cabo Verde | B34: 129.76 | C34: -2.84 | D34: 4030 | E34: 11.42 | F34: 0.99 | G34: 12.41 | H34: 0.1
A35: Cambodia | B35: 10256.59 | C35: 0.89 | D35: 176520 | E35: 44.83 | F35: 2.86 | G35: 23.34 | H35: 0.24
... A37: Canada | B37: 6872.16 | C37: 0.83 | D37: 8788700 | E37: 39.47 | F37: 0.02 | G37: 4.35 | H37: 1
A38: Cayman Islands | B38: 0 | C38: .. | D38: 240 | E38: 52.75 | F38: 2.08 | G38: 0.83 | H38: 0
A39: Central African Republic | B39: 2891.85 | C39: -1.01 | D39: 622980 | E39: 35.75 | F39: 1.32 | G39: 2.89 | H39: 0.35
A40: Chad | B40: 13700.57 | C40: 2.74 | D40: 1259200 | E40: 3.34 | F40: 0.03 | G40: 4.21 | H40: 0.3
A41: Channel Islands | B41: 112.38 | C41: 0.32 | D41: 198 | E41: 5.15 | F41: .. | G41: .. | H41: ..
A42: Chile | B42: 2221.32 | C42: -1.02 | D42: 742831.64 | E42: 24.68 | F42: 0.72 | G42: 2.02 | H42: 0.08
A43: China | B43: 491187.85 | C43: -1.43 | D43: 9388210 | E43: 23.63 | F43: 1.98 | G43: 11.61 | H43: 0.08
A44: Hong Kong SAR, China | B44: 0 | C44: .. | D44: 1050 | E44: .. | F44: 0.95 | G44: 1.9 | H44: 0
A45: Macao SAR, China | B45: 0 | C45: .. | D45: 33 | E45: .. | F45: .. | G45: .. | H45: ..
A46: Colombia | B46: 11358.31 | C46: 0.1 | D46: 1109500 | E46: 53.13 | F46: 2.16 | G46: 2.16 | H46: 0.05
A47: Comoros | B47: 560.79 | C47: 1.4 | D47: 1861 | E47: 17.45 | F47: 28.48 | G47: 34.93 | H47: 0.08
A48: Congo, Dem. Rep. | B48: 57338.94 | C48: 2.56 | D48: 2267050 | E48: 55.16 | F48: 0.87 | G48: 6.05 | H48: 0.14
A49: Congo, Rep. | B49: 2194.23 | C49: 2.33 | D49: 341500 | E49: 64.22 | F49: 0.36 | G49: 1.61 | H49: 0.09
A50: Costa Rica | B50: 1095.6 | C50: -1.65 | D50: 51060 | E50: 59.76 | F50: 7.39 | G50: 3.27 | H50: 0.03
A51: Cote d'Ivoire | B51: 14331.47 | C51: 1.4 | D51: 318000 | E51: 8.57 | F51: 26.41 | G51: 13.8 | H51: 0.15
A52: Croatia | B52: 1658.01 | C52: -1.14 | D52: 55960 | E52: 34.7 | F52: 1.41 | G52: 15.31 | H52: 0.22
A53: Cuba | B53: 2532.08 | C53: -0.59 | D53: 103800 | E53: 31.23 | F53: 6.29 | G53: 28.02 | H53: 0.26
A54: Curacao | B54: 13.18 | C54: -0.51 | D54: 444 | E54: 0.16 | F54: .. | G54: .. | H54: ..
A55: Cyprus | B55: 443.75 | C55: 1.07 | D55: 9240 | E55: 18.67 | F55: 2.8 | G55: 10.12 | H55: 0.07
A56: Czechia | B56: 2913.83 | C56: 1.51 | D56: 77186.83 | E56: 34.71 | F56: 0.63 | G56: 32.07 | H56: 0.24
A57: Denmark | B57: 685.46 | C57: -0.29 | D57: 40000 | E57: 15.73 | F57: 0.68 | G57: 58.93 | H57: 0.4
A58: Djibouti | B58: 311.44 | C58: 0.23 | D58: 23180 | E58: 0.25 | F58: 0.03 | G58: 0.13 | H58: 0
A59: Dominica | B59: 18.26 | C59: -2.09 | D59: 750 | E59: 63.83 | F59: 22.67 | G59: 8 | H59: 0.09
A60: Dominican Republic | B60: 3097.4 | C60: 2.8 | D60: 48198.02 | E60: 44.65 | F60: 9.89 | G60: 18.74 | H60: 0.08
A61: Ecuador | B61: 6578.77 | C61: 0.79 | D61: 248360 | E61: 50.06 | F61: 5.73 | G61: 4.12 | H61: 0.06
A62: Egypt, Arab Rep. | B62: 64606.26 | C62: 1.37 | D62: 995450 | E62: 0.05 | F62: 0.96 | G62: 3.09 | H62: 0.03
A63: El Salvador | B63: 1623.68 | C63: -1.38 | D63: 20720 | E63: 27.96 | F63: 7.72 | G63: 34.8 | H63: 0.12
A64: Equatorial Guinea | B64: 524.99 | C64: 1.67 | D64: 28050 | E64: 86.99 | F64: 1.68 | G64: 1.89 | H64: 0.03
A65: Eritrea | B65: 2221.36 | C65: 1.97 | D65: 121178.2 | E65: 8.68 | F65: 0.02 | G65: 5.69 | H65: 0.21
A66: Estonia | B66: 398.05 | C66: 0.29 | D66: 42750 | E66: 57.04 | F66: 0.12 | G66: 16.37 | H66: 0.53
... A68: Ethiopia | B68: 96875.95 | C68: 1.81 | D68: 1128505.6 | E68: 15.06 | F68: 2.07 | G68: 14.56 | H68: 0.13
A69: Faroe Islands | B69: 32.89 | C69: 0.84 | D69: 1370 | E69: 0.06 | F69: .. | G69: 0.05 | H69: 0
A70: Fiji | B70: 384.91 | C70: -0.83 | D70: 18270 | E70: 62.76 | F70: 3.38 | G70: 4.2 | H70: 0.08
A71: Finland | B71: 1461.44 | C71: -0.96 | D71: 303947.7 | E71: 73.73 | F71: 0.01 | G71: 7.38 | H71: 0.4
A72: France | B72: 14482.93 | C72: 0.4 | D72: 538950 | E72: 32.17 | F72: 1.91 | G72: 31.56 | H72: 0.25
A73: French Polynesia | B73: 107.41 | C73: 0.34 | D73: 3471 | E73: 43.06 | F73: 7.49 | G73: 0.72 | H73: 0.01
A74: Gabon | B74: 213.31 | C74: -2.6 | D74: 257670 | E74: 91.27 | F74: 0.66 | G74: 1.26 | H74: 0.14
A75: Gambia, The | B75: 967.93 | C75: 0.88 | D75: 10120 | E75: 23.41 | F75: 0.69 | G75: 43.48 | H75: 0.17
A76: Georgia | B76: 1484.62 | C76: -1.34 | D76: 69490 | E76: 40.62 | F76: 1.84 | G76: 4.49 | H76: 0.08
A77: Germany | B77: 15149.35 | C77: -0.87 | D77: 349390 | E77: 32.68 | F77: 0.58 | G77: 33.37 | H77: 0.14
A78: Ghana | B78: 14171.06 | C78: 0.63 | D78: 227533 | E78: 35.13 | F78: 11.9 | G78: 20.7 | H78: 0.14
A79: Gibraltar | B79: 0 | C79: .. | D79: 10 | E79: 0 | F79: .. | G79: .. | H79: ..
A80: Greece | B80: 2238.69 | C80: -2.01 | D80: 128900 | E80: 30.27 | F80: 7.99 | G80: 14.06 | H80: 0.17
A81: Greenland | B81: 6.91 | C81: -2.09 | D81: 410450 | E81: 0 | F81: .. | G81: .. | H81: ..
A82: Grenada | B82: 74.39 | C82: 0.06 | D82: 340 | E82: 52.06 | F82: 11.76 | G82: 8.82 | H82: 0.03
A83: Guam | B83: 9.73 | C83: 0.57 | D83: 540 | E83: 51.85 | F83: 12.96 | G83: 1.85 | H83: 0.01
A84: Guatemala | B84: 7985.48 | C84: 0.62 | D84: 107160 | E84: 32.81 | F84: 11.04 | G84: 14.5 | H84: 0.09
A85: Guinea | B85: 8821.22 | C85: 1.87 | D85: 245720 | E85: 25.02 | F85: 5.65 | G85: 21.35 | H85: 0.38
A86: Guinea-Bissau | B86: 1154.62 | C86: 1.46 | D86: 28120 | E86: 70.11 | F86: 8.89 | G86: 14.02 | H86: 0.19
A87: Guyana | B87: 604.28 | C87: 0.74 | D87: 211140 | E87: 87.18 | F87: 0.14 | G87: 0.46 | H87: 0.12
A88: Haiti | B88: 5308.63 | C88: -0.18 | D88: 27560 | E88: 12.49 | F88: 10.89 | G88: 36.47 | H88: 0.09
A89: Honduras | B89: 4411.94 | C89: 0.54 | D89: 111890 | E89: 56.65 | F89: 5.36 | G89: 9.1 | H89: 0.1
A90: Hungary | B90: 2866.3 | C90: -0.11 | D90: 91260 | E90: 22.48 | F90: 1.64 | G90: 45.36 | H90: 0.43
A91: Iceland | B91: 22.24 | C91: 3.07 | D91: 100830 | E91: 0.52 | F91: .. | G91: 1.2 | H91: 0.32
A92: India | B92: 930009.29 | C92: 0.31 | D92: 2973190 | E92: 24.36 | F92: 4.7 | G92: 51.85 | H92: 0.11
A93: Indonesia | B93: 118521.18 | C93: -0.7 | D93: 1892555.5 | E93: 48.36 | F93: 13.74 | G93: 9.4 | H93: 0.06
A94: Iran, Islamic Rep. | B94: 21186.61 | C94: -0.23 | D94: 1622500 | E94: 6.64 | F94: 1.17 | G94: 9.68 | H94: 0.18
A95: Iraq | B95: 13279.21 | C95: 2.29 | D95: 434130 | E95: 1.9 | F95: 1.22 | G95: 11.45 | H95: 0.12
A96: Ireland | B96: 1882.25 | C96: 1.39 | D96: 68890 | E96: 11.41 | F96: 0.01 | G96: 6.33 | H96: 0.09
A97: Isle of Man | B97: 40.22 | C97: 0.04 | D97: 570 | E97: 6.07 | F97: .. | G97: 40.7 | H97: 0.28
A98: Israel | B98: 812.58 | C98: 2.41 | D98: 21640 | E98: 6.47 | F98: 4.74 | G98: 12.59 | H98: 0.03
A99: Italy | B99: 18008.62 | C99: -0.21 | D99: 295717 | E99: 32.53 | F99: 7.33 | G99: 24.32 | H99: 0.12
A100: Jamaica | B100: 1192.78 | C100: -1.01 | D100: 10830 | E100: 55.47 | F100: 6.28 | G100: 11.08 | H100: 0.04
A101: Japan | B101: 10037.96 | C101: -1.73 | D101: 364500 | E101: 68.41 | F101: 0.72 | G101: 11.21 | H101: 0.03
A102: Jordan | B102: 854.93 | C102: -2.01 | D102: 88794 | E102: 1.1 | F102: 0.92 | G102: 2.24 | H102: 0.02
...

Sheet GDP
A1: Column1 | B1: GDP_$_Billions_2015 | C1: GDP_$ Billions_2024 | D1: Agriculture_% _Of_GDP_2015 | E1: Agriculture_% _Of_GDP_2024 | F1: Industry_% Of GDP_2015 | G1: Industry_% Of GDP_2024 | H1: Manufacturing% Of GDP_2015 | I1: Manufacturing% Of GDP2024 | J1: Services% Of GDP_2015 | K1: Services% Of GDP_2024
A2: Afghanistan | B2: 19.1 | C2: 17.2 | D2: 20.6 | E2: 34.7 | F2: 22.1 | G2: 13.4 | H2: 11.4 | I2: 7.5 | J2: 53.2 | K2: 46.4
A3: Albania | B3: 11.5 | C3: 27 | D3: 18.7 | E3: 15.5 | F3: 24.5 | G3: 22.4 | H3: 6.3 | I3: 6.5 | J3: 42.9 | K3: 48.7
A4: Algeria | B4: 187.5 | C4: 269.3 | D4: 10.5 | E4: 14 | F4: 32.8 | G4: 36.2 | H4: 7.1 | I4: 9.5 | J4: 52.1 | K4: 46.8
A5: American Samoa | B5: 0.7 | C5: 0.9 | D5: .. | E5: .. | F5: .. | G5: .. | H5: .. | I5: .. | J5: .. | K5: ..
A6: Andorra | B6: 2.8 | C6: 4 | D6: 0.5 | E6: 0.5 | F6: 10 | G6: 12.8 | H6: 3.7 | I6: 3.4 | J6: 78.7 | K6: 77.6
A7: Angola | B7: 102.5 | C7: 101 | D7: 13.7 | E7: 22.1 | F7: 36.7 | G7: 34.6 | H7: 5.2 | I7: 7.6 | J7: 48 | K7: 41.1
A8: Antigua and Barbuda | B8: 1.4 | C8: 2.2 | D8: 1.4 | E8: 1.9 | F8: 15.9 | G8: 19 | H8: 2.8 | I8: 2.6 | J8: 73.1 | K8: 69.1
A9: Argentina | B9: 594.7 | C9: 638.4 | D9: 5.2 | E9: 5.8 | F9: 23.2 | G9: 24 | H9: 14.2 | I9: 15.2 | J9: 55.8 | K9: 53.7
A10: Armenia | B10: 10.6 | C10: 26 | D10: 17.2 | E10: 7.8 | F10: 25.7 | G10: 22.9 | H10: 9.2 | I10: 10.2 | J10: 48.2 | K10: 62
A11: Aruba | B11: 3 | C11: 4.3 | D11: 0 | E11: 0 | F11: 12.5 | G11: 9.7 | H11: 3.6 | I11: 2.6 | J11: 79.1 | K11: 79
A12: Australia | B12: 1356.8 | C12: 1757 | D12: 2.4 | E12: 2 | F12: 23.7 | G12: 25.5 | H12: 6.2 | I12: 5.4 | J12: 67.2 | K12: 66.1
A13: Austria | B13: 379.5 | C13: 534.8 | D13: 1.1 | E13: 1.2 | F13: 25.5 | G13: 24.6 | H13: 17.2 | I13: 15.1 | J13: 62.2 | K13: 64
A14: Azerbaijan | B14: 53.1 | C14: 74.3 | D14: 6.2 | E14: 5.7 | F14: 44.9 | G14: 42.6 | H14: 5 | I14: 5.2 | J14: 40.7 | K14: 42.3
A15: Bahamas, The | B15: 11.8 | C15: 15.8 | D15: 0.8 | E15: 0.5 | F15: 11.2 | G15: 9.6 | H15: 2.5 | I15: 0.6 | J15: 76.8 | K15: 77.2
A16: Bahrain | B16: 32.5 | C16: 47.1 | D16: 0.3 | E16: 0.2 | F16: 39.1 | G16: 42.3 | H16: 17.2 | I16: 19.9 | J16: 59.7 | K16: 53.2
A17: Bangladesh | B17: 195.1 | C17: 450.1 | D17: 14.8 | E17: 11.2 | F17: 26.8 | G17: 34.1 | H17: 16.8 | I17: 21.9 | J17: 53.7 | K17: 51.4
... A29: Brunei Darussalam | B29: 12.9 | C29: 15.3 | D29: 1.1 | E29: 1.2 | F29: 61.4 | G29: 61.7 | H29: 1.6 | I29: 10.7 | J29: 39.4 | K29: 39
A30: Bulgaria | B30: 50.8 | C30: 113.3 | D30: 4.1 | E30: 2.4 | F30: 24 | G30: 21.1 | H30: .. | I30: .. | J30: 58.3 | K30: 63.8
A31: Burkina Faso | B31: 11.8 | C31: 23.1 | D31: 22.6 | E31: 20.9 | F31: 24.4 | G31: 26.5 | H31: 11.7 | I31: 9.5 | J31: 44.1 | K31: 43.9
A32: Burundi | B32: 2.8 | C32: 3.1 | D32: 35.2 | E32: 34.9 | F32: 15.4 | G32: 17.7 | H32: 10.9 | I32: 11.5 | J32: 43.4 | K32: 43.2
A33: Cabo Verde | B33: 1.7 | C33: 2.7 | D33: 6.4 | E33: 4.9 | F33: 14.6 | G33: 10.7 | H33: 4.9 | I33: 5.1 | J33: 67.2 | K33: 68.7
A34: Cambodia | B34: 24.2 | C34: 46.4 | D34: 20.1 | E34: 16.6 | F34: 31.5 | G34: 41.8 | H34: 22.5 | I34: 27.8 | J34: 42.2 | K34: 35.6
A35: Cameroon | B35: 32.2 | C35: 53.3 | D35: 17.2 | E35: 18.5 | F35: 25.1 | G35: 23.2 | H35: 14.4 | I35: 12.9 | J35: 49.6 | K35: 50.7
A36: Canada | B36: 1556.5 | C36: 2243.6 | D36: 1.9 | E36: .. | F36: 24.4 | G36: .. | H36: 10 | I36: .. | J36: 67 | K36: ..
A37: Cayman Islands | B37: 4.7 | C37: 7.2 | D37: 0.4 | E37: 0.4 | F37: 7 | G37: 7.8 | H37: 0.8 | I37: 1 | J37: 87.4 | K37: 86
A38: Central African Republic | B38: 1.7 | C38: 2.8 | D38: 31.5 | E38: 27.9 | F38: 22.1 | G38: 20 | H38: 19.7 | I38: 18 | J38: 43.2 | K38: 42.1
A39: Chad | B39: 14.6 | C39: 19.5 | D39: 33.6 | E39: 37.7 | F39: 33.9 | G39: 28.7 | H39: 6.9 | I39: 7.1 | J39: 30.5 | K39: 29.8
A40: Channel Islands | B40: 10.1 | C40: 12.5 | D40: 0.8 | E40: 0.6 | F40: 7.7 | G40: 8.2 | H40: 0.9 | I40: 0.8 | J40: 91.7 | K40: 91.2
A41: Chile | B41: 242.5 | C41: 330.3 | D41: 3.7 | E41: 3.9 | F41: 27.9 | G41: 30.1 | H41: 10.4 | I41: 9 | J41: 58.3 | K41: 56.1
A42: China | B42: 11280.8 | C42: 18743.8 | D42: 8.2 | E42: 6.8 | F42: 40 | G42: 36.5 | H42: 28.4 | I42: 24.9 | J42: 51.7 | K42: 56.7
A43: Hong Kong SAR, China | B43: 309.4 | C43: 406.9 | D43: 0.1 | E43: 0 | F43: 7.1 | G43: 6.2 | H43: 1.1 | I43: 0.9 | J43: 89.8 | K43: 91.8
A44: Macao SAR, China | B44: 44.9 | C44: 49.5 | D44: .. | E44: .. | F44: 7.7 | G44: 5.4 | H44: 0.6 | I44: 0.8 | J44: 91.8 | K44: 90.9
A45: Colombia | B45: 293.5 | C45: 418.8 | D45: 6 | E45: 9.3 | F45: 28.6 | G45: 23.1 | H45: 12.4 | I45: 10.1 | J45: 56.2 | K45: 58.1
A46: Comoros | B46: 1 | C46: 1.4 | D46: 30.6 | E46: 36.6 | F46: 10.4 | G46: 9.6 | H46: .. | I46: .. | J46: 54.9 | K46: 50.1
A47: Congo, Dem. Rep. | B47: 40.2 | C47: 71 | D47: 12.5 | E47: 9.6 | F47: 40.5 | G47: 39.9 | H47: 16.8 | I47: 8.2 | J47: 42.4 | K47: 46.6
A48: Congo, Rep. | B48: 12.4 | C48: 15.7 | D48: 5.8 | E48: 9.4 | F48: 48.7 | G48: 40.1 | H48: 8.4 | I48: .. | J48: 39.2 | K48: 45
A49: Costa Rica | B49: 56.4 | C49: 95.4 | D49: 4.7 | E49: 3.6 | F49: 20 | G49: 19.7 | H49: 11.6 | I49: 13 | J49: 67.3 | K49: 68.8
A50: Cote d'Ivoire | B50: 45.8 | C50: 87.1 | D50: 18.4 | E50: 15.9 | F50: 20.1 | G50: 24 | H50: 11.4 | I50: 12.9 | J50: 54.1 | K50: 51.9
A51: Croatia | B51: 51 | C51: 93 | D51: 3 | E51: 2.9 | F51: 20.4 | G51: 19.2 | H51: 12.7 | I51: 10.5 | J51: 59.3 | K51: 60.8
A52: Cuba | B52: 87.1 | C52: .. | D52: 3.8 | E52: 1.2 | F52: 22.4 | G52: 23.8 | H52: 14.9 | I52: 10.7 | J52: 72.8 | K52: 73.4
A53: Curacao | B53: 3.1 | C53: 3.6 | D53: 0.2 | E53: 0.3 | F53: 16.5 | G53: 12.2 | H53: 8.6 | I53: 2.9 | J53: 71.6 | K53: 72.3
A54: Cyprus | B54: 19.9 | C54: 37.6 | D54: 1.9 | E54: 1.2 | F54: 10.2 | G54: 11.1 | H54: 4.3 | I54: 4.5 | J54: 75.5 | K54: 76.5
A55: Czechia | B55: 189.1 | C55: 347 | D55: 2.3 | E55: 1.9 | F55: 33.5 | G55: 29.2 | H55: 23.7 | I55: 19.9 | J55: 54.3 | K55: 60.2
A56: Denmark | B56: 301.8 | C56: 424.5 | D56: 0.9 | E56: 0.9 | F56: 19.6 | G56: 24.1 | H56: 12.5 | I56: 17.9 | J56: 66.3 | K56: 63.5
A57: Djibouti | B57: 2.4 | C57: 4.2 | D57: 1.1 | E57: 2.5 | F57: 11.4 | G57: 15.9 | H57: 2.7 | I57: 5.3 | J57: 80.3 | K57: 76.1
A58: Dominica | B58: 0.6 | C58: 0.7 | D58: 13.5 | E58: 12.2 | F58: 11.9 | G58: 13.9 | H58: 4.4 | I58: 4.7 | J58: 59.9 | K58: 56.9
A59: Dominican Republic | B59: 71 | C59: 124.3 | D59: 5.1 | E59: 4.5 | F59: 26.9 | G59: 28.7 | H59: 13.1 | I59: 12.5 | J59: 61 | K59: 59.8
A60: Ecuador | B60: 97.2 | C60: 124.7 | D60: 8 | E60: 9.5 | F60: 28.1 | G60: 26.5 | H60: 14.3 | I60: 12.9 | J60: 57.6 | K60: 57.2
A61: Egypt, Arab Rep. | B61: 329.4 | C61: 389.1 | D61: 11.4 | E61: 13.7 | F61: 36.6 | G61: 32.6 | H61: 16.7 | I61: 13.9 | J61: 53.2 | K61: 48.9
A62: El Salvador | B62: 23.4 | C62: 35.4 | D62: 5.5 | E62: 4.4 | F62: 25.3 | G62: 22.4 | H62: 16.4 | I62: 12 | J62: 60 | K62: 61
A63: Equatorial Guinea | B63: 13.2 | C63: 12.8 | D63: 1.9 | E63: 3.1 | F63: 59.1 | G63: 45.8 | H63: 17.8 | I63: 24.8 | J63: 39.1 | K63: 51.1
A64: Eritrea | B64: .. | C64: .. | D64: .. | E64: .. | F64: .. | G64: .. | H64: .. | I64: .. | J64: .. | K64: ..
A65: Estonia | B65: 23.3 | C65: 43.1 | D65: 2.8 | E65: 1.8 | F65: 23.1 | G65: 20.1 | H65: 13.7 | I65: 10.8 | J65: 60.7 | K65: 65.7
A66: Eswatini | B66: 3.9 | C66: 4.9 | D66: 7.4 | E66: 6.5 | F66: 37 | G66: 34.7 | H66: 31.7 | I66: 29.1 | J66: 49.2 | K66: 51.4
A67: Ethiopia | B67: 62.1 | C67: 149.7 | D67: 36.1 | E67: 34.8 | F67: 16.3 | G67: 25.4 | H67: 4.4 | I67: 4.4 | J67: 39.5 | K67: 37.5
A68: Faroe Islands | B68: 2.6 | C68: 4.1 | D68: 15.7 | E68: 16.1 | F68: 16.5 | G68: 18.3 | H68: 9.3 | I68: 9.5 | J68: 56.9 | K68: 53.8
A69: Fiji | B69: 4.7 | C69: 6 | D69: 7.9 | E69: 13.2 | F69: 15.2 | G69: 16.5 | H69: 10.5 | I69: 11.3 | J69: 55.4 | K69: 54.6
A70: Finland | B70: 233.2 | C70: 298.7 | D70: 2.1 | E70: 2.5 | F70: 23.3 | G70: 22.8 | H70: 14.8 | I70: 14.2 | J70: 60.9 | K70: 62.2
A71: France | B71: 2442.5 | C71: 3160.4 | D71: 1.5 | E71: 1.3 | F71: 17.2 | G71: 17.2 | H71: 10.3 | I71: 9.6 | J71: 70.3 | K71: 70.9
A72: French Polynesia | B72: 5.3 | C72: 6.3 | D72: 3.2 | E72: .. | F72: 10.8 | G72: .. | H72: 5.1 | I72: .. | J72: 75.8 | K72: ..
A73: Gabon | B73: 14.4 | C73: 20.9 | D73: 4.3 | E73: 6.6 | F73: 48.2 | G73: 52.9 | H73: 16.7 | I73: 19.5 | J73: 39 | K73: 36.8
A74: Gambia, The | B74: 1.4 | C74: 2.4 | D74: 22.2 | E74: 20.4 | F74: 17.1 | G74: 15.3 | H74: 6.3 | I74: 1.5 | J74: 51.9 | K74: 56.8
A75: Georgia | B75: 15.2 | C75: 34.2 | D75: 8.5 | E75: 5.5 | F75: 19.8 | G75: 19.6 | H75: 9.2 | I75: 8.4 | J75: 60.4 | K75: 62
A76: Germany | B76: 3425.1 | C76: 4685.6 | D76: 0.7 | E76: 0.9 | F76: 25.9 | G76: 25.6 | H76: 20.1 | I76: 18 | J76: 62.6 | K76: 64
A77: Ghana | B77: 49.4 | C77: 82.3 | D77: 20 | E77: 20.9 | F77: 31.1 | G77: 31.5 | H77: 11.1 | I77: 9.8 | J77: 40.5 | K77: 40.9
A78: Greece | B78: 194.6 | C78: 256.2 | D78: 3.8 | E78: 3.8 | F78: 14.4 | G78: 15 | H78: 8.3 | I78: 9.1 | J78: 70 | K78: 68
A79: Greenland | B79: 2.5 | C79: 3.3 | D79: 17 | E79: 16.6 | F79: 17 | G79: 18.4 | H79: 4.1 | I79: 2.7 | J79: 62.9 | K79: 61
A80: Grenada | B80: 1 | C80: 1.4 | D80: 7.4 | E80: 2.9 | F80: 12.3 | G80: 15.2 | H80: 3.4 | I80: 3.8 | J80: 66.8 | K80: 65.7
A81: Guam | B81: 5.8 | C81: 6.9 | D81: .. | E81: .. | F81: .. | G81: .. | H81: .. | I81: .. | J81: .. | K81: ..
A82: Guatemala | B82: 62.2 | C82: 113.2 | D82: 10 | E82: 9.8 | F82: 22.7 | G82: 21.7 | H82: 14.3 | I82: 13.6 | J82: 61.4 | K82: 61.8
A83: Guinea | B83: 8.8 | C83: 25 | D83: 18.5 | E83: 31 | F83: 26.3 | G83: 25.1 | H83: 12.1 | I83: 12.7 | J83: 45.5 | K83: 36.3
A84: Guinea-Bissau | B84: 1.2 | C84: 2.2 | D84: 35.2 | E84: 42.2 | F84: 12.9 | G84: 15.6 | H84: 8.9 | I84: 8.7 | J84: 45.1 | K84: 37.9
A85: Guyana | B85: 4.3 | C85: 24.7 | D85: 25.4 | E85: 7.6 | F85: 24.7 | G85: 76 | H85: 5.9 | I85: 1.7 | J85: 44.1 | K85: 14.5
A86: Haiti | B86: 14.8 | C86: 25.2 | D86: 17.2 | E86: 15.9 | F86: 26.1 | G86: 33.4 | H86: 17 | I86: 26.2 | J86: 52.4 | K86: 48.3
A87: Honduras | B87: 21 | C87: 37.1 | D87: 12.2 | E87: 11.2 | F87: 25.6 | G87: 26.1 | H87: 17.5 | I87: 14.9 | J87: 58.8 | K87: 58.4
A88: Hungary | B88: 125.2 | C88: 222.7 | D88: 3.8 | E88: 2.7 | F88: 26.4 | G88: 23.7 | H88: 20.2 | I88: 15.8 | J88: 54.1 | K88: 59.5
A89: Iceland | B89: 17.7 | C89: 33.3 | D89: 5.3 | E89: 4 | F89: 19.9 | G89: 20.1 | H89: 10.7 | I89: 8.6 | J89: 64.6 | K89: 64.9
A90: India | B90: 2103.6 | C90: 3909.9 | D90: 16.2 | E90: 16.3 | F90: 27.3 | G90: 24.6 | H90: 15.6 | I90: 12.6 | J90: 47.8 | K90: 49.9
A91: Indonesia | B91: 860.9 | C91: 1396.3 | D91: 13.5 | E91: 12.6 | F91: 40 | G91: 39.3 | H91: 21 | I91: 19 | J91: 43.3 | K91: 43.8
A92: Iran, Islamic Rep. | B92: 409.2 | C92: 475.3 | D92: 10.1 | E92: 10.8 | F92: 32.2 | G92: 36.1 | H92: 13.5 | I92: 20.6 | J92: 55.2 | K92: 49.8
A93: Iraq | B93: 166.8 | C93: 279.6 | D93: 4.2 | E93: 3.4 | F93: 45.3 | G93: 51.6 | H93: 2.2 | I93: 4.1 | J93: 51.2 | K93: 45.8
... A103: Kiribati | B103: 0.2 | C103: 0.3 | D103: 22.9 | E103: 27.2 | F103: 14.7 | G103: 11.5 | H103: 4.6 | I103: 4.7 | J103: 60.1 | K103: 67.1
A104: Korea, Dem. People's Rep. | B104: .. | C104: .. | D104: .. | E104: .. | F104: .. | G104: .. | H104: .. | I104: .. | J104: .. | K104: ..
A105: Korea, Rep. | B105: 1539.2 | C105: 1875.4 | D105: 1.9 | E105: 1.5 | F105: 35.1 | G105: 33.9 | H105: 27.8 | I105: 26.6 | J105: 55.1 | K105: 57.5
A106: Kosovo | B106: 6.3 | C106: 11.2 | D106: 7.7 | E106: 7.3 | F106: 26.9 | G106: 25.8 | H106: 13.3 | I106: 12.6 | J106: 46.6 | K106: 45.7
A107: Kuwait | B107: 114.6 | C107: 160.2 | D107: 0.5 | E107: 0.5 | F107: 55.9 | G107: 57.1 | H107: 7 | I107: 8 | J107: 58.4 | K107: 55.9
A108: Kyrgyz Republic | B108: 6.7 | C108: 17.5 | D108: 14.1 | E108: 8.6 | F108: 25.1 | G108: 24.7 | H108: 14.1 | I108: 12.6 | J108: 52.1 | K108: 52.1
A109: Lao PDR | B109: 14.4 | C109: 16.5 | D109: 17.6 | E109: 16.8 | F109: 27.7 | G109: 29 | H109: 8.2 | I109: 9.1 | J109: 44.2 | K109: 43.5
A110: Latvia | B110: 26.3 | C110: 43.7 | D110: 3.6 | E110: 4 | F110: 19.8 | G110: 18.5 | H110: 10.8 | I110: 9.9 | J110: 64.1 | K110: 64.6
A111: Lebanon | B111: 49.9 | C111: 20.1 | D111: 3.3 | E111: 1 | F111: 15.7 | G111: 2.1 | H111: 8 | I111: .. | J111: 73.8 | K111: 42.4
A112: Lesotho | B112: 2.4 | C112: 2.3 | D112: 3.8 | E112: 6.5 | F112: 33.7 | G112: 30.9 | H112: 15.1 | I112: 13.5 | J112: 51.5 | K112: 48
A113: Liberia | B113: 3.2 | C113: 4.8 | D113: 35.9 | E113: 33.8 | F113: 16.8 | G113: 22.7 | H113: .. | I113: .. | J113: 44.5 | K113: 41.9
A114: Libya | B114: 48.7 | C114: 48.5 | D114: 4.4 | E114: 2.4 | F114: 34.8 | G114: 73.5 | H114: 4.1 | I114: .. | J114: 72.4 | K114: 28.3
A115: Liechtenstein | B115: 6.3 | C115: 8.2 | D115: 0.1 | E115: 0.2 | F115: 37.3 | G115: 39.1 | H115: 36.9 | I115: 34.2 | J115: 54.7 | K115: 57.4
A116: Lithuania | B116: 41.5 | C116: 84.9 | D116: 3.4 | E116: 2.6 | F116: 27 | G116: 23.4 | H116: 17.2 | I116: 14 | J116: 59.2 | K116: 63.6
A117: Luxembourg | B117: 60.1 | C117: 93.3 | D117: 0.2 | E117: 0.2 | F117: 11.5 | G117: 9.7 | H117: 5.5 | I117: 4 | J117: 79.7 | K117: 81.2
A118: Madagascar | B118: 11.3 | C118: 17.4 | D118: 25.7 | E118: 22.5 | F118: 19 | G118: 22.8 | H118: 8.5 | I118: 12.6 | J118: 50.8 | K118: 47.7
A119: Malawi | B119: 9.2 | C119: 11.3 | D119: 23 | E119: 31.8 | F119: 17.6 | G119: 17.1 | H119: 11.3 | I119: 11 | J119: 53.2 | K119: 44.2
A120: Malaysia | B120: 301.4 | C120: 422.2 | D120: 8.3 | E120: 8.1 | F120: 38.4 | G120: 37 | H120: 22.3 | I120: 22.5 | J120: 52 | K120: 53.7
...

Sheet Energy Consumption
A1: Report generated on: 06-27-2026 20:37:11
A2: API_Code | B2: Energy_Type | C2: 1980 | D2: 1981 | E2: 1982 | F2: 1983 | G2: 1984 | H2: 1985 | I2: 1986 | J2: 1987 | K2: 1988 | L2: 1989 | M2: 1990 | N2: 1991 | O2: 1992 | P2: 1993 | Q2: 1994 | R2: 1995 | S2: 1996 | T2: 1997 | U2: 1998 | V2: 1999 | W2: 2000 | X2: 2001 | Y2: 2002 | Z2: 2003 | AA2: 2004 | AB2: 2005 | AC2: 2006 | AD2: 2007 | AE2: 2008 | AF2: 2009 | AG2: 2010 | AH2: 2011 | AI2: 2012 | AJ2: 2013 | AK2: 2014 | AL2: 2015 | AM2: 2016 | AN2: 2017 | AO2: 2018 | AP2: 2019 | AQ2: 2020 | AR2: 2021 | AS2: 2022 | AT2: 2023 | AU2: 2024
B3: Afghanistan
A4: INTL.44-2-AFG-QBTU.A | B4: Consumption (quad Btu) | C4: 0.021623379 | D4: 0.024872997 | E4: 0.026919218 | F4: 0.033719327 | G4: 0.033882152 | H4: 0.03285812 | I4: 0.034096058 | J4: 0.057767973 | K4: 0.10607836 | L4: 0.10409964 | M4: 0.10303601 | N4: 0.042640902 | O4: 0.028003943 | P4: 0.02782721 | Q4: 0.026857007 | R4: 0.022505732 | S4: 0.022359263 | T4: 0.021483512 | U4: 0.021004098 | V4: 0.02098328 | W4: 0.018042878 | X4: 0.012450843 | Y4: 0.011357232 | Z4: 0.013540179 | AA4: 0.012682489 | AB4: 0.017109714 | AC4: 0.022283409 | AD4: 0.026472342 | AE4: 0.0513188 | AF4: 0.08618441 | AG4: 0.1100194 | AH4: 0.14123299 | AI4: 0.13314562 | AJ4: 0.10874241 | AK4: 0.090866072 | AL4: 0.10561779 | AM4: 0.095797059 | AN4: 0.12460259 | AO4: 0.15863904 | AP4: 0.16075122 | AQ4: 0.16006951 | AR4: 0.16231321 | AS4: 0.1539092 | AT4: 0.13744602 | AU4: 0.13461777
A5: INTL.4411-2-AFG-QBTU.A | B5: Coal (quad Btu) | C5: 0.0024792482 | D5: 0.0026042524 | E5: 0.0030209328 | F5: 0.0030209328 | G5: 0.0030834348 | H5: 0.0031459369 | I5: 0.0033334431 | J5: 0.0034792812 | K5: 0.0028750947 | L5: 0.0026459203 | M5: 0.0021875719 | N5: 0.0019583978 | O5: 0.00016667213 | P5: 0.00014583814 | Q5: 0.00012500415 | R5: 0.00010417016 | S5: 6.250198e-05 | T5: 4.1667986e-05 | U5: 4.1667986e-05 | V5: 2.0833993e-05 | W5: 2.0833993e-05 | X5: 0.00054168458 | Y5: 0.00043751442 | Z5: 0.00072919071 | AA5: 0.00070835671 | AB5: 0.00068752253 | AC5: 0.00072919071 | AD5: 0.0021212492 | AE5: 0.0035133077 | AF5: 0.0061791981 | AG5: 0.010345138 | AH5: 0.013110956 | AI5: 0.015876774 | AJ5: 0.017724885 | AK5: 0.014260951 | AL5: 0.013874091 | AM5: 0.019768281 | AN5: 0.021566236 | AO5: 0.023364191 | AP5: 0.025162146 | AQ5: 0.020746989 | AR5: 0.034876105 | AS5: 0.030549208 | AT5: 0.009931516 | AU5: 0.0056170529
A6: INTL.4413-2-AFG-QBTU.A | B6: Natural gas (quad Btu) | C6: 0.002094 | D6: 0.003141 | E6: 0.005235 | F6: 0.005235 | G6: 0.005235 | H6: 0 | I6: 0 | J6: 0.023034 | K6: 0.07329 | L6: 0.071196 | M6: 0.070150672 | N6: 0.011517 | O6: 0.011092441 | P6: 0.011092441 | Q6: 0.01108773 | R6: 0.00739182 | S6: 0.0085042051 | T6: 0.0085042051 | U6: 0.0085042051 | V6: 0.0085042051 | W6: 0.0085042051 | X6: 0.0018487403 | Y6: 0.0018487403 | Z6: 0.0007394961 | AA6: 0.0007394961 | AB6: 0.0007394961 | AC6: 0.0007394961 | AD6: 0.0014789922 | AE6: 0.0018487403 | AF6: 0.0011092441 | AG6: 0.0052466803 | AH6: 0.0059676828 | AI6: 0.0059270109 | AJ6: 0.0057125588 | AK6: 0.0052466803 | AL6: 0.0054056706 | AM6: 0.0061118833 | AN6: 0.0061118833 | AO6: 0.0059983378 | AP6: 0.0050390736 | AQ6: 0.003140122 | AR6: NA | AS6: NA | AT6: NA | AU6: NA
A7: INTL.4415-2-AFG-QBTU.A | B7: Petroleum and other liquids (quad Btu) | C7: 0.014624098 | D7: 0.01666759 | E7: 0.016250901 | F7: 0.022917937 | G7: 0.022980726 | H7: 0.027084834 | I7: 0.028329758 | J7: 0.028675112 | K7: 0.027374636 | L7: 0.027698618 | M7: 0.028118186 | N7: 0.026408512 | O7: 0.014683914 | P7: 0.014644024 | Q7: 0.013614067 | R7: 0.013194499 | S7: 0.012185452 | T7: 0.011497729 | U7: 0.011093382 | V7: 0.011093398 | W7: 0.0081291107 | X7: 0.0080370316 | Y7: 0.0068360389 | Z7: 0.0095806427 | AA7: 0.0089655761 | AB7: 0.013311272 | AC7: 0.017167204 | AD7: 0.018241911 | AE7: 0.041541548 | AF7: 0.072306945 | AG7: 0.085493838 | AH7: 0.11080152 | AI7: 0.098345426 | AJ7: 0.069950161 | AK7: 0.05528505 | AL7: 0.069916271 | AM7: 0.051517535 | AN7: 0.077478309 | AO7: 0.10897156 | AP7: 0.10943295 | AQ7: 0.11500772 | AR7: 0.10481883 | AS7: 0.10041746 | AT7: 0.10339067 | AU7: 0.10615736
A8: INTL.4419-2-AFG-QBTU.A | B8: Nuclear, renewables, and other (quad Btu) | C8: 0.0024260327 | D8: 0.0024601541 | E8: 0.0024123841 | F8: 0.0025454577 | G8: 0.0025829912 | H8: 0.0026273491 | I8: 0.002432857 | J8: 0.0025795791 | K8: 0.0025386334 | L8: 0.0025591062 | M8: 0.0025795791 | N8: 0.0027569927 | O8: 0.002060915 | P8: 0.0019449066 | Q8: 0.0020302061 | R8: 0.0018152424 | S8: 0.0016071031 | T8: 0.0014399096 | U8: 0.0013648425 | V8: 0.0013648425 | W8: 0.0013887282 | X8: 0.0020233865 | Y8: 0.0022349386 | Z8: 0.0024908492 | AA8: 0.00226906 | AB8: 0.0023714236 | AC8: 0.0036475182 | AD8: 0.0046301899 | AE8: 0.0044152048 | AF8: 0.0065890231 | AG8: 0.008933746 | AH8: 0.011352832 | AI8: 0.012996413 | AJ8: 0.015354808 | AK8: 0.016073391 | AL8: 0.016421761 | AM8: 0.01839936 | AN8: 0.019446166 | AO8: 0.020304949 | AP8: 0.021117049 | AQ8: 0.02117468 | AR8: 0.02261828 | AS8: 0.022942531 | AT8: 0.024123834 | AU8: 0.022843357
A9: INTL.4417-2-AFG-QBTU.A | B9: Nuclear (quad Btu) | C9: 0 | D9: 0 | E9: 0 | F9: 0 | G9: 0 | H9: 0 | I9: 0 | J9: 0 | K9: 0 | L9: 0 | M9: 0 | N9: 0 | O9: 0 | P9: 0 | Q9: 0 | R9: 0 | S9: 0 | T9: 0 | U9: 0 | V9: 0 | W9: 0 | X9: 0 | Y9: 0 | Z9: 0 | AA9: 0 | AB9: 0 | AC9: 0 | AD9: 0 | AE9: 0 | AF9: 0 | AG9: 0 | AH9: 0 | AI9: 0 | AJ9: 0 | AK9: 0 | AL9: 0 | AM9: 0 | AN9: 0 | AO9: 0 | AP9: 0 | AQ9: 0 | AR9: 0 | AS9: 0 | AT9: 0 | AU9: 0
A10: INTL.4418-2-AFG-QBTU.A | B10: Renewables and other (quad Btu) | C10: 0.0024260327 | D10: 0.0024601541 | E10: 0.0024123841 | F10: 0.0025454577 | G10: 0.0025829912 | H10: 0.0026273491 | I10: 0.002432857 | J10: 0.0025795791 | K10: 0.0025386334 | L10: 0.0025591062 | M10: 0.0025795791 | N10: 0.0027569927 | O10: 0.002060915 | P10: 0.0019449066 | Q10: 0.0020302061 | R10: 0.0018152424 | S10: 0.0016071031 | T10: 0.0014399096 | U10: 0.0013648425 | V10: 0.0013648425 | W10: 0.0013887282 | X10: 0.0020233865 | Y10: 0.0022349386 | Z10: 0.0024908492 | AA10: 0.00226906 | AB10: 0.0023714236 | AC10: 0.0036475182 | AD10: 0.0046301899 | AE10: 0.0044152048 | AF10: 0.0065890231 | AG10: 0.008933746 | AH10: 0.011352832 | AI10: 0.012996413 | AJ10: 0.015354808 | AK10: 0.016073391 | AL10: 0.016421761 | AM10: 0.01839936 | AN10: 0.019446166 | AO10: 0.020304949 | AP10: 0.021117049 | AQ10: 0.02117468 | AR10: 0.02261828 | AS10: 0.022942531 | AT10: 0.024123834 | AU10: 0.022843357
B11: Albania
A12: INTL.44-2-ALB-QBTU.A | B12: Consumption (quad Btu) | C12: 0.14261928 | D12: 0.14079517 | E12: 0.14106563 | F12: 0.14682521 | G12: 0.14762843 | H12: 0.1467357 | I12: 0.14240644 | J12: 0.13876024 | K12: 0.14292714 | L12: 0.1333422 | M12: 0.095133926 | N12: 0.071859591 | O12: 0.06210578 | P12: 0.051204863 | Q12: 0.044406117 | R12: 0.048832473 | S12: 0.046068598 | T12: 0.044092001 | U12: 0.050786685 | V12: 0.039812941 | W12: 0.067161628 | X12: 0.068568842 | Y12: 0.077141979 | Z12: 0.079172688 | AA12: 0.085351607 | AB12: 0.084436041 | AC12: 0.080273998 | AD12: 0.078962765 | AE12: 0.081529918 | AF12: 0.08222285 | AG12: 0.075775112 | AH12: 0.081782366 | AI12: 0.07673134 | AJ12: 0.089938222 | AK12: 0.087853264 | AL12: 0.082019821 | AM12: 0.091312362 | AN12: 0.099942583 | AO12: 0.095516638 | AP12: 0.084954345 | AQ12: 0.072063291 | AR12: 0.08698439 | AS12: 0.088269056 | AT12: 0.083192132 | AU12: 0.087328996
A13: INTL.4411-2-ALB-QBTU.A | B13: Coal (quad Btu) | C13: 0.024317315 | D13: 0.025770486 | E13: 0.029070075 | F13: 0.031462709 | G13: 0.033997866 | H13: 0.036247979 | I13: 0.035668553 | J13: 0.037287487 | K13: 0.037487993 | L13: 0.037114724 | M13: 0.032372911 | N13: 0.018421888 | O13: 0.0052350049 | P13: 0.0034656701 | Q13: 0.0028128737 | R13: 0.0021198445 | S13: 0.0016644756 | T13: 0.0012322477 | U13: 0.00075395684 | V13: 0.00090344544 | W13: 0.0010978101 | X13: 0.0012482907 | Y13: 0.00094882682 | Z13: 0.00094876716 | AA13: 0.00090293214 | AB13: 0.00081909191 | AC13: 0.0016219844 | AD13: 0.0023592009 | AE13: 0.0028584824 | AF13: 0.0039230022 | AG13: 0.0035249442 | AH13: 0.0033113417 | AI13: 0.0029688883 | AJ13: 0.0026425202 | AK13: 0.0033396836 | AL13: 0.0028222553 | AM13: 0.0022553832 | AN13: 0.0026038898 | AO13: 0.0034145212 | AP13: 0.0040931699 | AQ13: 0.0046198789 | AR13: 0.0066735653 | AS13: 0.0072524042 | AT13: 0.0057310824 | AU13: 0.0068458282
A14: INTL.4413-2-ALB-QBTU.A | B14: Natural gas (quad Btu) | C14: 0.01047 | D14: 0.011517 | E14: 0.01047 | F14: 0.011517 | G14: 0.011517 | H14: 0.01047 | I14: 0.014658 | J14: 0.016752 | K14: 0.026175 | L14: 0.026175 | M14: 0.0094251534 | N14: 0.00522 | O14: 0.003760488 | P14: 0.001105596 | Q14: 0.00110664 | R14: 0.00110664 | S14: 0.0011060658 | T14: 0.0007373772 | U14: 0.0011060658 | V14: 0.0007373772 | W14: 0.0011060658 | X14: 0.0011060658 | Y14: 0.0011060658 | Z14: 0.0011060658 | AA14: 0.0011060658 | AB14: 0.0011060658 | AC14: 0.0011060658 | AD14: 0.0003644508 | AE14: 0.0010647473 | AF14: 0.0010647473 | AG14: 0.0003503248 | AH14: 0.0003503248 | AI14: 0.00059555216 | AJ14: 0.00066561712 | AK14: 0.0011210394 | AL14: 0.0012261368 | AM14: 0.0015764482 | AN14: 0.0017516091 | AO14: 0.0015036782 | AP14: 0.0027300139 | AQ14: 0.0019624276 | AR14: 0.0020756912 | AS14: 0.0017882392 | AT14: 0.0017591421 | AU14: 0.0019091265
A15: INTL.4415-2-ALB-QBTU.A | B15: Petroleum and other liquids (quad Btu) | C15: 0.099297277 | D15: 0.094720496 | E15: 0.092567758 | F15: 0.094720496 | G15: 0.092821368 | H15: 0.090415019 | I15: 0.082449886 | J15: 0.072966858 | K15: 0.068141514 | L15: 0.058063178 | M15: 0.043014162 | N15: 0.03854419 | O15: 0.043791663 | P15: 0.035639668 | Q15: 0.027742255 | R15: 0.031145343 | S15: 0.024568785 | T15: 0.025573471 | U15: 0.031009561 | V15: 0.01910171 | W15: 0.045761196 | X15: 0.048300987 | Y15: 0.055914566 | Z15: 0.056532534 | AA15: 0.063251986 | AB15: 0.06309585 | AC15: 0.058567703 | AD15: 0.057138346 | AE15: 0.05647564 | AF15: 0.054445616 | AG15: 0.052663621 | AH15: 0.0521623 | AI15: 0.046020699 | AJ15: 0.054955503 | AK15: 0.056805568 | AL15: 0.053080053 | AM15: 0.05483 | AN15: 0.070199116 | AO15: 0.064531253 | AP15: 0.05215828 | AQ15: 0.03958554 | AR15: 0.0496106 | AS15: 0.05229012 | AT15: 0.0481105 | AU15: 0.04898003
A16: INTL.4419-2-ALB-QBTU.A | B16: Nuclear, renewables, and other (quad Btu) | C16: 0.0085346897 | D16: 0.0087871918 | E16: 0.0089578024 | F16: 0.0091250009 | G16: 0.0092921993 | H16: 0.0096027018 | I16: 0.0096300049 | J16: 0.011753894 | K16: 0.011122636 | L16: 0.011989303 | M16: 0.010321699 | N16: 0.0096735133 | O16: 0.0093186234 | P16: 0.010993929 | Q16: 0.012744349 | R16: 0.014460645 | S16: 0.018729271 | T16: 0.016548905 | U16: 0.017917102 | V16: 0.019070409 | W16: 0.019196556 | X16: 0.017913498 | Y16: 0.01917252 | Z16: 0.020585321 | AA16: 0.020090622 | AB16: 0.019415033 | AC16: 0.018978245 | AD16: 0.019100767 | AE16: 0.021131048 | AF16: 0.022789485 | AG16: 0.019236222 | AH16: 0.025958399 | AI16: 0.0271462 | AJ16: 0.031674582 | AK16: 0.026586973 | AL16: 0.024891375 | AM16: 0.03265053 | AN16: 0.025387968 | AO16: 0.026067185 | AP16: 0.025972881 | AQ16: 0.025895444 | AR16: 0.028624534 | AS16: 0.026938293 | AT16: 0.027591407 | AU16: 0.029594011
A17: INTL.4417-2-ALB-QBTU.A | B17: Nuclear (quad Btu) | C17: 0 | D17: 0 | E17: 0 | F17: 0 | G17: 0 | H17: 0 | I17: 0 | J17: 0 | K17: 0 | L17: 0 | M17: 0 | N17: 0 | O17: 0 | P17: 0 | Q17: 0 | R17: 0 | S17: 0 | T17: 0 | U17: 0 | V17: 0 | W17: 0 | X17: 0 | Y17: 0 | Z17: 0 | AA17: 0 | AB17: 0 | AC17: 0 | AD17: 0 | AE17: 0 | AF17: 0 | AG17: 0 | AH17: 0 | AI17: 0 | AJ17: 0 | AK17: 0 | AL17: 0 | AM17: 0 | AN17: 0 | AO17: 0 | AP17: 0 | AQ17: 0 | AR17: 0 | AS17: 0 | AT17: 0 | AU17: 0
A18: INTL.4418-2-ALB-QBTU.A | B18: Renewables and other (quad Btu) | C18: 0.0085346897 | D18: 0.0087871918 | E18: 0.0089578024 | F18: 0.0091250009 | G18: 0.0092921993 | H18: 0.0096027018 | I18: 0.0096300049 | J18: 0.011753894 | K18: 0.011122636 | L18: 0.011989303 | M18: 0.010321699 | N18: 0.0096735133 | O18: 0.0093186234 | P18: 0.010993929 | Q18: 0.012744349 | R18: 0.014460645 | S18: 0.018729271 | T18: 0.016548905 | U18: 0.017917102 | V18: 0.019070409 | W18: 0.019196556 | X18: 0.017913498 | Y18: 0.01917252 | Z18: 0.020585321 | AA18: 0.020090622 | AB18: 0.019415033 | AC18: 0.018978245 | AD18: 0.019100767 | AE18: 0.021131048 | AF18: 0.022789485 | AG18: 0.019236222 | AH18: 0.025958399 | AI18: 0.0271462 | AJ18: 0.031674582 | AK18: 0.026586973 | AL18: 0.024891375 | AM18: 0.03265053 | AN18: 0.025387968 | AO18: 0.026067185 | AP18: 0.025972881 | AQ18: 0.025895444 | AR18: 0.028624534 | AS18: 0.026938293 | AT18: 0.027591407 | AU18: 0.029594011
B19: Algeria
A20: INTL.44-2-DZA-QBTU.A | B20: Consumption (quad Btu) | C20: 0.77896515 | D20: 0.66084253 | E20: 0.94885027 | F20: 1.0689057 | G20: 1.1271603 | H20: 1.041923 | I20: 1.0645636 | J20: 1.1348783 | K20: 1.2118683 | L20: 1.1734362 | M20: 1.2167381 | N20: 1.3519853 | O20: 1.3004524 | P20: 1.1947832 | Q20: 1.232021 | R20: 1.288023 | S20: 1.2627396 | T20: 1.2032296 | U20: 1.2493542 | V20: 1.2447268 | W20: 1.2737811 | X20: 1.2751082 | Y20: 1.307076 | Z20: 1.3213626 | AA20: 1.2937721 | AB20: 1.48685 | AC20: 1.5582835 | AD20: 1.5482965 | AE20: 1.6756164 | AF20: 1.782202 | AG20: 1.7766686 | AH20: 1.9348566 | AI20: 2.0944432 | AJ20: 2.0355805 | AK20: 2.2983579 | AL20: 2.3508421 | AM20: 2.3340512 | AN20: 2.3623007 | AO20: 2.5018518 | AP20: 2.6123987 | AQ20: 2.4712632 | AR20: 2.6516639 | AS20: 2.7683456 | AT20: 2.8363267 | AU20: 2.8879649
A21: INTL.4411-2-DZA-QBTU.A | B21: Coal (quad Btu) | C21: 0.002547398 | D21: 0.0076550645 | E21: 0.020475801 | F21: 0.033213824 | G21: 0.034235723 | H21: 0.034242132 | I21: 0.034610211 | J21: 0.035079318 | K21: 0.035599908 | L21: 0.036081886 | M21: 0.033572055 | N21: 0.031062224 | O21: 0.02879373 | P21: 0.022609952 | Q21: 0.02304864 | R21: 0.013759894 | S21: 0.014334636 | T21: 0.015455786 | U21: 0.017403199 | V21: 0.017394738 | W21: 0.016194829 | X21: 0.015033806 | Y21: 0.0086720379 | Z21: 0.010163584 | AA21: 0.010488812 | AB21: 0.010358057 | AC21: 0.0068578448 | AD21: 0.0070119256 | AE21: 0.0071719146 | AF21: 0.0045679124 | AG21: 4.6554579e-05 | AH21: 5.4955601e-05 | AI21: 0.00043341783 | AJ21: 0.0012596215 | AK21: 0.00083532786 | AL21: 0.00057692229 | AM21: 0.00057521875 | AN21: 0.00092422507 | AO21: 0.00041041788 | AP21: 0.00040543564 | AQ21: 0.00065843711 | AR21: 0.00094109007 | AS21: 0.00049843141 | AT21: 6.8371275e-05 | AU21: 0.00019027978
A22: INTL.4413-2-DZA-QBTU.A | B22: Natural gas (quad Btu) | C22: 0.5428 | D22: 0.40828 | E22: 0.65254 | F22: 0.77408 | G22: 0.8024 | H22: 0.68912 | I22: 0.71036 | J22: 0.77408 | K22: 0.84016 | L22: 0.7788 | M22: 0.80358 | N22: 0.9145 | O22: 0.8614 | P22: 0.77300974 | Q22: 0.8146838 | R22: 0.8755246 | S22: 0.85888411 | T22: 0.8023681 | U22: 0.8298301 | V22: 0.84813811 | W22: 0.8182881 | X22: 0.8135121 | Y22: 0.8123181 | Z22: 0.8166961 | AA22: 0.7673441 | AB22: 0.95380712 | AC22: 1.0188801 | AD22: 0.99225735 | AE22: 1.0379379 | AF22: 1.0784803 | AG22: 1.0808806 | AH22: 1.2331489 | AI22: 1.3443124 | AJ22: 1.2356993 | AK22: 1.4666146 | AL22: 1.485967 | AM22: 1.4914801 | AN22: 1.5479989 | AO22: 1.6805569 | AP22: 1.7353812 | AQ22: 1.6766936 | AR22: 1.8362838 | AS22: 1.9209327 | AT22: 1.9610747 | AU22: 1.9933189
A23: INTL.4415-2-DZA-QBTU.A | B23: Petroleum and other liquids (quad Btu) | C23: 0.23274084 | D23: 0.24361427 | E23: 0.27430583 | F23: 0.26087827 | G23: 0.2885217 | H23: 0.31650673 | I23: 0.31880859 | J23: 0.32421421 | K23: 0.33539135 | L23: 0.35782738 | M23: 0.37942809 | N23: 0.40768201 | O23: 0.41277114 | P23: 0.40205261 | Q23: 0.39756274 | R23: 0.39902293 | S23: 0.38860475 | T23: 0.38432427 | U23: 0.40055648 | V23: 0.37812934 | W23: 0.4381881 | X23: 0.44413405 | Y23: 0.48359572 | Z23: 0.49182341 | AA23: 0.51340502 | AB23: 0.5180272 | AC23: 0.52863203 | AD23: 0.54412094 | AE23: 0.62547819 | AF23: 0.69180226 | AG23: 0.68578305 | AH23: 0.68814866 | AI23: 0.73594742 | AJ23: 0.79023202 | AK23: 0.82407984 | AL23: 0.859255 | AM23: 0.838878 | AN23: 0.80475498 | AO23: 0.81036911 | AP23: 0.8642612 | AQ23: 0.78490192 | AR23: 0.80615825 | AS23: 0.84877352 | AT23: 0.87395676 | AU23: 0.89463257
A24: INTL.4419-2-DZA-QBTU.A | B24: Nuclear, renewables, and other (quad Btu) | C24: 0.00087691913 | D24: 0.0012931993 | E24: 0.0015286431 | F24: 0.000733613 | G24: 0.0020029171 | H24: 0.0020541145 | I24: 0.00078479498 | J24: 0.0015047615 | K24: 0.00071706447 | L24: 0.00072695656 | M24: 0.00015793202 | N24: -0.0012589631 | O24: -0.0025124988 | P24: -0.0028891158 | Q24: -0.0032741441 | R24: -0.00028443931 | S24: 0.0009160715 | T24: 0.0010814613 | U24: 0.0015643955 | V24: 0.0010646523 | W24: 0.0011100684 | X24: 0.0024282655 | Y24: 0.0024900904 | Z24: 0.0026795171 | AA24: 0.0025342111 | AB24: 0.0046576438 | AC24: 0.0039134466 | AD24: 0.0049063284 | AE24: 0.0050284177 | AF24: 0.0073515413 | AG24: 0.009958467 | AH24: 0.013504068 | AI24: 0.013749985 | AJ24: 0.0083896068 | AK24: 0.0068280558 | AL24: 0.0050432192 | AM24: 0.0031178451 | AN24: 0.008622518 | AO24: 0.010515368 | AP24: 0.012350853 | AQ24: 0.0090092634 | AR24: 0.0082807762 | AS24: -0.0018590505 | AT24: 0.0012268304 | AU24: -0.00017686801
A25: INTL.4417-2-DZA-QBTU.A | B25: Nuclear (quad Btu) | C25: 0 | D25: 0 | E25: 0 | F25: 0 | G25: 0 | H25: 0 | I25: 0 | J25: 0 | K25: 0 | L25: 0 | M25: 0 | N25: 0 | O25: 0 | P25: 0 | Q25: 0 | R25: 0 | S25: 0 | T25: 0 | U25: 0 | V25: 0 | W25: 0 | X25: 0 | Y25: 0 | Z25: 0 | AA25: 0 | AB25: 0 | AC25: 0 | AD25: 0 | AE25: 0 | AF25: 0 | AG25: 0 | AH25: 0 | AI25: 0 | AJ25: 0 | AK25: 0 | AL25: 0 | AM25: 0 | AN25: 0 | AO25: 0 | AP25: 0 | AQ25: 0 | AR25: 0 | AS25: 0 | AT25: 0 | AU25: 0
A26: INTL.4418-2-DZA-QBTU.A | B26: Renewables and other (quad Btu) | C26: 0.00087691913 | D26: 0.0012931993 | E26: 0.0015286431 | F26: 0.000733613 | G26: 0.0020029171 | H26: 0.0020541145 | I26: 0.00078479498 | J26: 0.0015047615 | K26: 0.00071706447 | L26: 0.00072695656 | M26: 0.00015793202 | N26: -0.0012589631 | O26: -0.0025124988 | P26: -0.0028891158 | Q26: -0.0032741441 | R26: -0.00028443931 | S26: 0.0009160715 | T26: 0.0010814613 | U26: 0.0015643955 | V26: 0.0010646523 | W26: 0.0011100684 | X26: 0.0024282655 | Y26: 0.0024900904 | Z26: 0.0026795171 | AA26: 0.0025342111 | AB26: 0.0046576438 | AC26: 0.0039134466 | AD26: 0.0049063284 | AE26: 0.0050284177 | AF26: 0.0073515413 | AG26: 0.009958467 | AH26: 0.013504068 | AI26: 0.013749985 | AJ26: 0.0083896068 | AK26: 0.0068280558 | AL26: 0.0050432192 | AM26: 0.0031178451 | AN26: 0.008622518 | AO26: 0.010515368 | AP26: 0.012350853 | AQ26: 0.0090092634 | AR26: 0.0082807762 | AS26: -0.0018590505 | AT26: 0.0012268304 | AU26: -0.00017686801
B27: American Samoa
A28: INTL.44-2-ASM-QBTU.A | B28: Consumption (quad Btu) | C28: 0.0058931124 | D28: 0.0069264773 | E28: 0.0096550895 | F28: 0.0060869042 | G28: 0.0069454539 | H28: 0.0065066908 | I28: 0.006716584 | J28: 0.0069730089 | K28: 0.0067788142 | L28: 0.0078061913 | M28: 0.0082105383 | N28: 0.0082105383 | O28: 0.0084455187 | P28: 0.0082161958 | Q28: 0.0080035833 | R28: 0.0077909708 | S28: 0.0078116067 | T28: 0.0080035833 | U28: 0.0080035833 | V28: 0.0080035935 | W28: 0.0078371031 | X28: 0.0078371031 | Y28: 0.0079673116 | Z28: 0.0079673116 | AA28: 0.0079673116 | AB28: 0.0084634813 | AC28: 0.0086069555 | AD28: 0.0086069555 | AE28: 0.0086305362 | AF28: 0.0086069555 | AG28: 0.0080896489 | AH28: 0.0067264395 | AI28: 0.0067653685 | AJ28: 0.0067289184 | AK28: 0.0063782652 | AL28: 0.0063782652 | AM28: 0.0063991333 | AN28: 0.0063885016 | AO28: 0.0063889253 | AP28: 0.006414998 | AQ28: 0.0062204737 | AR28: 0.0063204758 | AS28: 0.0063205953 | AT28: 0.0064353701 | AU28: 0.0079105991
A29: INTL.4411-2-ASM-QBTU.A | B29: Coal (quad Btu) | C29: 0 | D29: 0 | E29: 0 | F29: 0 | G29: 0 | H29: 0 | I29: 0 | J29: 0 | K29: 0 | L29: 0 | M29: 0 | N29: 0 | O29: 0 | P29: 0 | Q29: 0 | R29: 0 | S29: 0 | T29: 0 | U29: 0 | V29: 0 | W29: 0 | X29: 0 | Y29: 0 | Z29: 0 | AA29: 0 | AB29: 0 | AC29: 0 | AD29: 0 | AE29: 0 | AF29: 0 | AG29: 0 | AH29: 0 | AI29: 0 | AJ29: 0 | AK29: 0 | AL29: 0 | AM29: 0 | AN29: 0 | AO29: 0 | AP29: 0 | AQ29: 0 | AR29: 0 | AS29: 0 | AT29: 0 | AU29: 0
A30: INTL.4413-2-ASM-QBTU.A | B30: Natural gas (quad Btu) | C30: 0 | D30: 0 | E30: 0 | F30: 0 | G30: 0 | H30: 0 | I30: 0 | J30: 0 | K30: 0 | L30: 0 | M30: 0 | N30: 0 | O30: 0 | P30: 0 | Q30: 0 | R30: 0 | S30: 0 | T30: 0 | U30: 0 | V30: 0 | W30: 0 | X30: 0 | Y30: 0 | Z30: 0 | AA30: 0 | AB30: 0 | AC30: 0 | AD30: 0 | AE30: 0 | AF30: 0 | AG30: 0 | AH30: 0 | AI30: 0 | AJ30: 0 | AK30: 0 | AL30: 0 | AM30: 0 | AN30: 0 | AO30: 0 | AP30: 0 | AQ30: 0 | AR30: 0 | AS30: 0 | AT30: 0 | AU30: 0
A31: INTL.4415-2-ASM-QBTU.A | B31: Petroleum and other liquids (quad Btu) | C31: 0.0058931124 | D31: 0.0069264773 | E31: 0.0096550895 | F31: 0.0060869042 | G31: 0.0069454539 | H31: 0.0065066908 | I31: 0.006716584 | J31: 0.0069730089 | K31: 0.0067788142 | L31: 0.0078061913 | M31: 0.0082105383 | N31: 0.0082105383 | O31: 0.0084455187 | P31: 0.0082161958 | Q31: 0.0080035833 | R31: 0.0077909708 | S31: 0.0078116067 | T31: 0.0080035833 | U31: 0.0080035833 | V31: 0.0080035935 | W31: 0.0078371031 | X31: 0.0078371031 | Y31: 0.0079673116 | Z31: 0.0079673116 | AA31: 0.0079673116 | AB31: 0.0084634813 | AC31: 0.0086069555 | AD31: 0.0086069555 | AE31: 0.0086305362 | AF31: 0.0086069555 | AG31: 0.0080896489 | AH31: 0.0067264395 | AI31: 0.0067622975 | AJ31: 0.0067220941 | AK31: 0.0063714409 | AL31: 0.0063714409 | AM31: 0.0063888969 | AN31: 0.0063714409 | AO31: 0.0063718646 | AP31: 0.0063979373 | AQ31: 0.006203413 | AR31: 0.0063034151 | AS31: 0.0063033737 | AT31: 0.0064183094 | AU31: 0.0078911403
A32: INTL.4419-2-ASM-QBTU.A | B32: Nuclear, renewables, and other (quad Btu) | C32: 0 | D32: 0 | E32: 0 | F32: 0 | G32: 0 | H32: 0 | I32: 0 | J32: 0 | K32: 0 | L32: 0 | M32: 0 | N32: 0 | O32: 0 | P32: 0 | Q32: 0 | R32: 0 | S32: 0 | T32: 0 | U32: 0 | V32: 0 | W32: 0 | X32: 0 | Y32: 0 | Z32: 0 | AA32: 0 | AB32: 0 | AC32: 0 | AD32: 0 | AE32: 0 | AF32: 0 | AG32: 0 | AH32: 0 | AI32: 3.0709275e-06 | AJ32: 6.8242833e-06 | AK32: 6.8242833e-06 | AL32: 6.8242833e-06 | AM32: 1.0236425e-05 | AN32: 1.7060708e-05 | AO32: 1.7060708e-05 | AP32: 1.7060708e-05 | AQ32: 1.7060708e-05 | AR32: 1.7060708e-05 | AS32: 1.7221591e-05 | AT32: 1.7060708e-05 | AU32: 1.9458799e-05
A33: INTL.4417-2-ASM-QBTU.A | B33: Nuclear (quad Btu) | C33: 0 | D33: 0 | E33: 0 | F33: 0 | G33: 0 | H33: 0 | I33: 0 | J33: 0 | K33: 0 | L33: 0 | M33: 0 | N33: 0 | O33: 0 | P33: 0 | Q33: 0 | R33: 0 | S33: 0 | T33: 0 | U33: 0 | V33: 0 | W33: 0 | X33: 0 | Y33: 0 | Z33: 0 | AA33: 0 | AB33: 0 | AC33: 0 | AD33: 0 | AE33: 0 | AF33: 0 | AG33: 0 | AH33: 0 | AI33: 0 | AJ33: 0 | AK33: 0 | AL33: 0 | AM33: 0 | AN33: 0 | AO33: 0 | AP33: 0 | AQ33: 0 | AR33: 0 | AS33: 0 | AT33: 0 | AU33: 0
A34: INTL.4418-2-ASM-QBTU.A | B34: Renewables and other (quad Btu) | C34: 0 | D34: 0 | E34: 0 | F34: 0 | G34: 0 | H34: 0 | I34: 0 | J34: 0 | K34: 0 | L34: 0 | M34: 0 | N34: 0 | O34: 0 | P34: 0 | Q34: 0 | R34: 0 | S34: 0 | T34: 0 | U34: 0 | V34: 0 | W34: 0 | X34: 0 | Y34: 0 | Z34: 0 | AA34: 0 | AB34: 0 | AC34: 0 | AD34: 0 | AE34: 0 | AF34: 0 | AG34: 0 | AH34: 0 | AI34: 3.0709275e-06 | AJ34: 6.8242833e-06 | AK34: 6.8242833e-06 | AL34: 6.8242833e-06 | AM34: 1.0236425e-05 | AN34: 1.7060708e-05 | AO34: 1.7060708e-05 | AP34: 1.7060708e-05 | AQ34: 1.7060708e-05 | AR34: 1.7060708e-05 | AS34: 1.7221591e-05 | AT34: 1.7060708e-05 | AU34: 1.9458799e-05
B35: Angola
A36: INTL.44-2-AGO-QBTU.A | B36: Consumption (quad Btu) | C36: 0.054668941 | D36: 0.054132032 | E36: 0.057782781 | F36: 0.062032281 | G36: 0.055677986 | H36: 0.069545781 | I36: 0.068210909 | J36: 0.070510952 | K36: 0.072933422 | L36: 0.070301203 | M36: 0.074589916 | N36: 0.078419053 | O36: 0.0789026 | P36: 0.077047029 | Q36: 0.074985037 | R36: 0.080846745 | S36: 0.077265802 | T36: 0.088026916 | U36: 0.077410363 | V36: 0.088318518 | W36: 0.10461774 | X36: 0.11328804 | Y36: 0.12049765 | Z36: 0.13396147 | AA36: 0.14584816 | AB36: 0.11947128 | AC36: 0.15128957 | AD36: 0.1780525 | AE36: 0.20753551 | AF36: 0.23998387 | AG36: 0.26062387 | AH36: 0.27259565 | AI36: 0.29378279 | AJ36: 0.31874726 | AK36: 0.35222567 | AL36: 0.3701853 | AM36: 0.3316892 | AN36: 0.28619098 | AO36: 0.32081652 | AP36: 0.3334736 | AQ36: 0.26553584 | AR36: 0.29810412 | AS36: 0.33307822 | AT36: 0.33733648 | AU36: 0.34382359
A37: INTL.4411-2-AGO-QBTU.A | B37: Coal (quad Btu) | C37: 0 | D37: 0 | E37: 0 | F37: 0 | G37: 0 | H37: 0 | I37: 0 | J37: 0 | K37: 0 | L37: 0 | M37: 0 | N37: 0 | O37: 0 | P37: 0 | Q37: 0 | R37: 0 | S37: 0 | T37: 0 | U37: 0 | V37: 0 | W37: 0 | X37: 0 | Y37: 0 | Z37: 0 | AA37: 0 | AB37: 0 | AC37: 0 | AD37: 0 | AE37: 0 | AF37: 0 | AG37: 0 | AH37: 0 | AI37: 0 | AJ37: 0 | AK37: 0 | AL37: 0 | AM37: 0 | AN37: 0 | AO37: 0 | AP37: 0 | AQ37: 0 | AR37: 0 | AS37: 0 | AT37: 0 | AU37: 0
A38: INTL.4413-2-AGO-QBTU.A | B38: Natural gas (quad Btu) | C38: 0.0096324 | D38: 0.0092136 | E38: 0.01047 | F38: 0.012564 | G38: 0.012564 | H38: 0.013611 | I38: 0.014658 | J38: 0.016752 | K38: 0.018846 | L38: 0.015705 | M38: 0.019892073 | N38: 0.02094 | O38: 0.021075639 | P38: 0.020705891 | Q38: 0.01922292 | R38: 0.020705891 | S38: 0.020705891 | T38: 0.021075639 | U38: 0.021445387 | V38: 0.020705891 | W38: 0.021075639 | X38: 0.019596647 | Y38: 0.022924379 | Z38: 0.024033623 | AA38: 0.027731104 | AB38: 0.024033623 | AC38: 0.025142867 | AD38: 0.030689088 | AE38: 0.025142867 | AF38: 0.025512615 | AG38: 0.027139507 | AH38: 0.027805053 | AI38: 0.028100852 | AJ38: 0.01508572 | AK38: 0.00854118 | AL38: 0.028581524 | AM38: 0.029690759 | AN38: 0.030060504 | AO38: 0.042686734 | AP38: 0.047838582 | AQ38: 0.045478624 | AR38: 0.043999644 | AS38: 0.043999644 | AT38: 0.043999644 | AU38: 0.044873093
A39: INTL.4415-2-AGO-QBTU.A | B39: Petroleum and other liquids (quad Btu) | C39: 0.043228106 | D39: 0.043109997 | E39: 0.045265496 | F39: 0.047420996 | G39: 0.041066701 | H39: 0.053887496 | I39: 0.051300896 | J39: 0.051506939 | K39: 0.051835409 | L39: 0.052320304 | M39: 0.052247925 | N39: 0.055039372 | O39: 0.05498806 | P39: 0.053335041 | Q39: 0.05273896 | R39: 0.057100637 | S39: 0.05343439 | T39: 0.063996363 | U39: 0.052385639 | V39: 0.064592882 | W39: 0.080430224 | X39: 0.090221248 | Y39: 0.093673197 | Z39: 0.10569338 | AA39: 0.11213216 | AB39: 0.087855878 | AC39: 0.11746622 | AD39: 0.138874 | AE39: 0.17165464 | AF39: 0.20331696 | AG39: 0.22081508 | AH39: 0.23108061 | AI39: 0.24697317 | AJ39: 0.28750846 | AK39: 0.32625411 | AL39: 0.32313824 | AM39: 0.2798125 | AN39: 0.2295137 | AO39: 0.24219739 | AP39: 0.2458237 | AQ39: 0.17638959 | AR39: 0.21043788 | AS39: 0.24408632 | AT39: 0.25316702 | AU39: 0.25913448
A40: INTL.4419-2-AGO-QBTU.A | B40: Nuclear, renewables, and other (quad Btu) | C40: 0.0018084351 | D40: 0.0018084351 | E40: 0.002047285 | F40: 0.002047285 | G40: 0.002047285 | H40: 0.002047285 | I40: 0.0022520135 | J40: 0.0022520135 | K40: 0.0022520135 | L40: 0.0022758985 | M40: 0.0024499177 | N40: 0.0024396813 | O40: 0.0028389018 | P40: 0.0030060968 | Q40: 0.0030231575 | R40: 0.0030402182 | S40: 0.0031255217 | T40: 0.0029549147 | U40: 0.0035793366 | V40: 0.0030197453 | W40: 0.0031118732 | X40: 0.003470148 | Y40: 0.0039000779 | Z40: 0.0042344678 | AA40: 0.0059848964 | AB40: 0.0075817787 | AC40: 0.0086804883 | AD40: 0.0084894084 | AE40: 0.01073801 | AF40: 0.011154291 | AG40: 0.012669282 | AH40: 0.013709985 | AI40: 0.018708773 | AJ40: 0.016153078 | AK40: 0.01743038 | AL40: 0.018465528 | AM40: 0.022185945 | AN40: 0.026616781 | AO40: 0.035932404 | AP40: 0.039811316 | AQ40: 0.043667623 | AR40: 0.0436666 | AS40: 0.044992255 | AT40: 0.040169815 | AU40: 0.039816015
A41: INTL.4417-2-AGO-QBTU.A | B41: Nuclear (quad Btu) | C41: 0 | D41: 0 | E41: 0 | F41: 0 | G41: 0 | H41: 0 | I41: 0 | J41: 0 | K41: 0 | L41: 0 | M41: 0 | N41: 0 | O41: 0 | P41: 0 | Q41: 0 | R41: 0 | S41: 0 | T41: 0 | U41: 0 | V41: 0 | W41: 0 | X41: 0 | Y41: 0 | Z41: 0 | AA41: 0 | AB41: 0 | AC41: 0 | AD41: 0 | AE41: 0 | AF41: 0 | AG41: 0 | AH41: 0 | AI41: 0 | AJ41: 0 | AK41: 0 | AL41: 0 | AM41: 0 | AN41: 0 | AO41: 0 | AP41: 0 | AQ41: 0 | AR41: 0 | AS41: 0 | AT41: 0 | AU41: 0
A42: INTL.4418-2-AGO-QBTU.A | B42: Renewables and other (quad Btu) | C42: 0.0018084351 | D42: 0.0018084351 | E42: 0.002047285 | F42: 0.002047285 | G42: 0.002047285 | H42: 0.002047285 | I42: 0.0022520135 | J42: 0.0022520135 | K42: 0.0022520135 | L42: 0.0022758985 | M42: 0.0024499177 | N42: 0.0024396813 | O42: 0.0028389018 | P42: 0.0030060968 | Q42: 0.0030231575 | R42: 0.0030402182 | S42: 0.0031255217 | T42: 0.0029549147 | U42: 0.0035793366 | V42: 0.0030197453 | W42: 0.0031118732 | X42: 0.003470148 | Y42: 0.0039000779 | Z42: 0.0042344678 | AA42: 0.0059848964 | AB42: 0.0075817787 | AC42: 0.0086804883 | AD42: 0.0084894084 | AE42: 0.01073801 | AF42: 0.011154291 | AG42: 0.012669282 | AH42: 0.013709985 | AI42: 0.018708773 | AJ42: 0.016153078 | AK42: 0.01743038 | AL42: 0.018465528 | AM42: 0.022185945 | AN42: 0.026616781 | AO42: 0.035932404 | AP42: 0.039811316 | AQ42: 0.043667623 | AR42: 0.0436666 | AS42: 0.044992255 | AT42: 0.040169815 | AU42: 0.039816015
B43: Antarctica
A44: INTL.44-2-ATA-QBTU.A | B44: Consumption (quad Btu) | C44: 0.00213195 | D44: 0.002126125 | E44: 0.002126125 | F44: 0.002126125 | G44: 0.002771535 | H44: 0.002976575 | I44: 0.0027639625 | J44: 0.0027639625 | K44: 0.00298473 | L44: 0.0027639625 | M44: 0.002976575 | N44: 0.002976575 | O44: 0.00298473 | P44: 0.002976575 | Q44: 0.002976575 | R44: 0.0031891875 | S44: 0.003197925 | T44: 0.0031891875 | U44: 0.0031891875 | V44: 0.0031891875 | W44: 0.0031721785 | X44: 0.0032590875 | Y44: 0.0032590875 | Z44: 0.0032590875 | AA44: 0.003302542 | AB44: 0.0033093663 | AC44: 0.0033093663 | AD44: 0.0033528208 | AE44: 0.00015523333 | AF44: 0.00020456759 | AG44: 0.00020456759 | AH44: 0.00020456759 | AI44: 0.00019314701 | AJ44: 0.00019262509 | AK44: 0.00019262509 | AL44: 0.00019282259 | AM44: 0.00019265774 | AN44: 0.00018650857 | AO44: 0.00018650857 | AP44: 0.0001865087 | AQ44: 0.00015701274 | AR44: 0.00016707917 | AS44: 0.00017593506 | AT44: 0.00019464814 | AU44: 0.00017339
A45: INTL.4411-2-ATA-QBTU.A | B45: Coal (quad Btu) | C45: 0 | D45: 0 | E45: 0 | F45: 0 | G45: 0 | H45: 0 | I45: 0 | J45: 0 | K45: 0 | L45: 0 | M45: 0 | N45: 0 | O45: 0 | P45: 0 | Q45: 0 | R45: 0 | S45: 0 | T45: 0 | U45: 0 | V45: 0 | W45: 0 | X45: 0 | Y45: 0 | Z45: 0 | AA45: 0 | AB45: 0 | AC45: 0 | AD45: 0 | AE45: 0 | AF45: 0 | AG45: 0 | AH45: 0 | AI45: 0 | AJ45: 0 | AK45: 0 | AL45: 0 | AM45: 0 | AN45: 0 | AO45: 0 | AP45: 0 | AQ45: 0 | AR45: 0 | AS45: 0 | AT45: 0 | AU45: 0
A46: INTL.4413-2-ATA-QBTU.A | B46: Natural gas (quad Btu) | C46: 0 | D46: 0 | E46: 0 | F46: 0 | G46: 0 | H46: 0 | I46: 0 | J46: 0 | K46: 0 | L46: 0 | M46: 0 | N46: 0 | O46: 0 | P46: 0 | Q46: 0 | R46: 0 | S46: 0 | T46: 0 | U46: 0 | V46: 0 | W46: 0 | X46: 0 | Y46: 0 | Z46: 0 | AA46: 0 | AB46: 0 | AC46: 0 | AD46: 0 | AE46: 0 | AF46: 0 | AG46: 0 | AH46: 0 | AI46: 0 | AJ46: 0 | AK46: 0 | AL46: 0 | AM46: 0 | AN46: 0 | AO46: 0 | AP46: 0 | AQ46: 0 | AR46: 0 | AS46: 0 | AT46: 0 | AU46: 0
A47: INTL.4415-2-ATA-QBTU.A | B47: Petroleum and other liquids (quad Btu) | C47: 0.00213195 | D47: 0.002126125 | E47: 0.002126125 | F47: 0.002126125 | G47: 0.002771535 | H47: 0.002976575 | I47: 0.0027639625 | J47: 0.0027639625 | K47: 0.00298473 | L47: 0.0027639625 | M47: 0.002976575 | N47: 0.002976575 | O47: 0.00298473 | P47: 0.002976575 | Q47: 0.002976575 | R47: 0.0031891875 | S47: 0.003197925 | T47: 0.0031891875 | U47: 0.0031891875 | V47: 0.0031891875 | W47: 0.0031721785 | X47: 0.0032590875 | Y47: 0.0032590875 | Z47: 0.0032590875 | AA47: 0.003302542 | AB47: 0.003302542 | AC47: 0.003302542 | AD47: 0.0033459965 | AE47: 0.00014840905 | AF47: 0.00019091902 | AG47: 0.00019091902 | AH47: 0.00019091902 | AI47: 0.00019144093 | AJ47: 0.00019091902 | AK47: 0.00019091902 | AL47: 0.00018941044 | AM47: 0.0001892456 | AN47: 0.00018650857 | AO47: 0.00018650857 | AP47: 0.0001865087 | AQ47: 0.00015701274 | AR47: 0.00016707917 | AS47: 0.00017593506 | AT47: 0.00017339 | AU47: 0.00017339
A48: INTL.4419-2-ATA-QBTU.A | B48: Nuclear, renewables, and other (quad Btu) | C48: 0 | D48: 0 | E48: 0 | F48: 0 | G48: 0 | H48: 0 | I48: 0 | J48: 0 | K48: 0 | L48: 0 | M48: 0 | N48: 0 | O48: 0 | P48: 0 | Q48: 0 | R48: 0 | S48: 0 | T48: 0 | U48: 0 | V48: 0 | W48: 0 | X48: 0 | Y48: 0 | Z48: 0 | AA48: 0 | AB48: 6.8242833e-06 | AC48: 6.8242833e-06 | AD48: 6.8242833e-06 | AE48: 6.8242833e-06 | AF48: 1.3648567e-05 | AG48: 1.3648567e-05 | AH48: 1.3648567e-05 | AI48: 1.7060708e-06 | AJ48: 1.7060708e-06 | AK48: 1.7060708e-06 | AL48: 3.4121416e-06 | AM48: 3.4121416e-06 | AN48: 0 | AO48: 0 | AP48: 0 | AQ48: 0 | AR48: 0 | AS48: 0 | AT48: 2.1258143e-05 | AU48: 0
A49: INTL.4417-2-ATA-QBTU.A | B49: Nuclear (quad Btu) | C49: 0 | D49: 0 | E49: 0 | F49: 0 | G49: 0 | H49: 0 | I49: 0 | J49: 0 | K49: 0 | L49: 0 | M49: 0 | N49: 0 | O49: 0 | P49: 0 | Q49: 0 | R49: 0 | S49: 0 | T49: 0 | U49: 0 | V49: 0 | W49: 0 | X49: 0 | Y49: 0 | Z49: 0 | AA49: 0 | AB49: 0 | AC49: 0 | AD49: 0 | AE49: 0 | AF49: 0 | AG49: 0 | AH49: 0 | AI49: 0 | AJ49: 0 | AK49: 0 | AL49: 0 | AM49: 0 | AN49: 0 | AO49: 0 | AP49: 0 | AQ49: 0 | AR49: 0 | AS49: 0 | AT49: 0 | AU49: 0
A50: INTL.4418-2-ATA-QBTU.A | B50: Renewables and other (quad Btu) | C50: 0 | D50: 0 | E50: 0 | F50: 0 | G50: 0 | H50: 0 | I50: 0 | J50: 0 | K50: 0 | L50: 0 | M50: 0 | N50: 0 | O50: 0 | P50: 0 | Q50: 0 | R50: 0 | S50: 0 | T50: 0 | U50: 0 | V50: 0 | W50: 0 | X50: 0 | Y50: 0 | Z50: 0 | AA50: 0 | AB50: 6.8242833e-06 | AC50: 6.8242833e-06 | AD50: 6.8242833e-06 | AE50: 6.8242833e-06 | AF50: 1.3648567e-05 | AG50: 1.3648567e-05 | AH50: 1.3648567e-05 | AI50: 1.7060708e-06 | AJ50: 1.7060708e-06 | AK50: 1.7060708e-06 | AL50: 3.4121416e-06 | AM50: 3.4121416e-06 | AN50: 0 | AO50: 0 | AP50: 0 | AQ50: 0 | AR50: 0 | AS50: 0 | AT50: 2.1258143e-05 | AU50: 0
B51: Antigua and Barbuda
A52: INTL.44-2-ATG-QBTU.A | B52: Consumption (quad Btu) | C52: 0.0058048554 | D52: 0.0051687457 | E52: 0.0070294941 | F52: 0.0041349966 | G52: 0.0045609578 | H52: 0.0045484962 | I52: 0.0046243941 | J52: 0.0057559174 | K52: 0.0057713112 | L52: 0.0057559174 | M52: 0.0059685299 | N52: 0.0059476519 | O52: 0.005963571 | P52: 0.0059476519 | Q52: 0.0063672194 | R52: 0.0067884294 | S52: 0.006806652 | T52: 0.0069953844 | U52: 0.0069953844 | V52: 0.0069954036 | W52: 0.0072893021 | X52: 0.0072893021 | Y52: 0.0078146679 | Z52: 0.008213775 | AA52: 0.0085191611 | AB52: 0.0086494501 | AC52: 0.0089145638 | AD52: 0.0093423981 | AE52: 0.0095569251 | AF52: 0.010013005 | AG52: 0.0096803086 | AH52: 0.0096512054 | AI52: 0.0099183601 | AJ52: 0.0099187013 | AK52: 0.010141497 | AL52: 0.010352856 | AM52: 0.010506393 | AN52: 0.0099873723 | AO52: 0.0099547014 | AP52: 0.010327558 | AQ52: 0.0099784343 | AR52: 0.010374957 | AS52: 0.010422149 | AT52: 0.01053152 | AU52: 0.010637457
A53: INTL.4411-2-ATG-QBTU.A | B53: Coal (quad Btu) | C53: 0 | D53: 0 | E53: 0 | F53: 0 | G53: 0 | H53: 0 | I53: 0 | J53: 0 | K53: 0 | L53: 0 | M53: 0 | N53: 0 | O53: 0 | P53: 0 | Q53: 0 | R53: 0 | S53: 0 | T53: 0 | U53: 0 | V53: 0 | W53: 0 | X53: 0 | Y53: 0 | Z53: 0 | AA53: 0 | AB53: 0 | AC53: 0 | AD53: 0 | AE53: 0 | AF53: 0 | AG53: 0 | AH53: 0 | AI53: 0 | AJ53: 0 | AK53: 0 | AL53: 0 | AM53: 0 | AN53: 0 | AO53: 0 | AP53: 0 | AQ53: 0 | AR53: 0 | AS53: 0 | AT53: 0 | AU53: 0
A54: INTL.4413-2-ATG-QBTU.A | B54: Natural gas (quad Btu) | C54: 0 | D54: 0 | E54: 0 | F54: 0 | G54: 0 | H54: 0 | I54: 0 | J54: 0 | K54: 0 | L54: 0 | M54: 0 | N54: 0 | O54: 0 | P54: 0 | Q54: 0 | R54: 0 | S54: 0 | T54: 0 | U54: 0 | V54: 0 | W54: 0 | X54: 0 | Y54: 0 | Z54: 0 | AA54: 0 | AB54: 0 | AC54: 0 | AD54: 0 | AE54: 0 | AF54: 0 | AG54: 0 | AH54: 0 | AI54: 0 | AJ54: 0 | AK54: 0 | AL54: 0 | AM54: 0 | AN54: 0 | AO54: 0 | AP54: 0 | AQ54: 0 | AR54: 0 | AS54: 0 | AT54: 0 | AU54: 0
A55: INTL.4415-2-ATG-QBTU.A | B55: Petroleum and other liquids (quad Btu) | C55: 0.0058048554 | D55: 0.0051687457 | E55: 0.0070294941 | F55: 0.0041349966 | G55: 0.0045609578 | H55: 0.0045484962 | I55: 0.0046243941 | J55: 0.0057559174 | K55: 0.0057713112 | L55: 0.0057559174 | M55: 0.0059685299 | N55: 0.0059476519 | O55: 0.005963571 | P55: 0.0059476519 | Q55: 0.0063672194 | R55: 0.0067884294 | S55: 0.006806652 | T55: 0.0069953844 | U55: 0.0069953844 | V55: 0.0069954036 | W55: 0.0072893021 | X55: 0.0072893021 | Y55: 0.0078146679 | Z55: 0.008213775 | AA55: 0.0085191611 | AB55: 0.0086494501 | AC55: 0.0089145638 | AD55: 0.0093423981 | AE55: 0.0095569251 | AF55: 0.010013005 | AG55: 0.0096796262 | AH55: 0.0096494993 | AI55: 0.009916654 | AJ55: 0.009916654 | AK55: 0.010139449 | AL55: 0.01033443 | AM55: 0.010489332 | AN55: 0.0099665582 | AO55: 0.00992058 | AP55: 0.0102832 | AQ55: 0.00992384 | AR55: 0.01030842 | AS55: 0.01034367 | AT55: 0.01045304 | AU55: 0.010547946
A56: INTL.4419-2-ATG-QBTU.A | B56: Nuclear, renewables, and other (quad Btu) | C56: 0 | D56: 0 | E56: 0 | F56: 0 | G56: 0 | H56: 0 | I56: 0 | J56: 0 | K56: 0 | L56: 0 | M56: 0 | N56: 0 | O56: 0 | P56: 0 | Q56: 0 | R56: 0 | S56: 0 | T56: 0 | U56: 0 | V56: 0 | W56: 0 | X56: 0 | Y56: 0 | Z56: 0 | AA56: 0 | AB56: 0 | AC56: 0 | AD56: 0 | AE56: 0 | AF56: 0 | AG56: 6.8242833e-07 | AH56: 1.7060708e-06 | AI56: 1.7060708e-06 | AJ56: 2.047285e-06 | AK56: 2.047285e-06 | AL56: 1.8425565e-05 | AM56: 1.7060708e-05 | AN56: 2.0814064e-05 | AO56: 3.4121416e-05 | AP56: 4.4357841e-05 | AQ56: 5.4594266e-05 | AR56: 6.6536762e-05 | AS56: 7.8479258e-05 | AT56: 7.8480312e-05 | AU56: 8.9510469e-05
A57: INTL.4417-2-ATG-QBTU.A | B57: Nuclear (quad Btu) | C57: 0 | D57: 0 | E57: 0 | F57: 0 | G57: 0 | H57: 0 | I57: 0 | J57: 0 | K57: 0 | L57: 0 | M57: 0 | N57: 0 | O57: 0 | P57: 0 | Q57: 0 | R57: 0 | S57: 0 | T57: 0 | U57: 0 | V57: 0 | W57: 0 | X57: 0 | Y57: 0 | Z57: 0 | AA57: 0 | AB57: 0 | AC57: 0 | AD57: 0 | AE57: 0 | AF57: 0 | AG57: 0 | AH57: 0 | AI57: 0 | AJ57: 0 | AK57: 0 | AL57: 0 | AM57: 0 | AN57: 0 | AO57: 0 | AP57: 0 | AQ57: 0 | AR57: 0 | AS57: 0 | AT57: 0 | AU57: 0
A58: INTL.4418-2-ATG-QBTU.A | B58: Renewables and other (quad Btu) | C58: 0 | D58: 0 | E58: 0 | F58: 0 | G58: 0 | H58: 0 | I58: 0 | J58: 0 | K58: 0 | L58: 0 | M58: 0 | N58: 0 | O58: 0 | P58: 0 | Q58: 0 | R58: 0 | S58: 0 | T58: 0 | U58: 0 | V58: 0 | W58: 0 | X58: 0 | Y58: 0 | Z58: 0 | AA58: 0 | AB58: 0 | AC58: 0 | AD58: 0 | AE58: 0 | AF58: 0 | AG58: 6.8242833e-07 | AH58: 1.7060708e-06 | AI58: 1.7060708e-06 | AJ58: 2.047285e-06 | AK58: 2.047285e-06 | AL58: 1.8425565e-05 | AM58: 1.7060708e-05 | AN58: 2.0814064e-05 | AO58: 3.4121416e-05 | AP58: 4.4357841e-05 | AQ58: 5.4594266e-05 | AR58: 6.6536762e-05 | AS58: 7.8479258e-05 | AT58: 7.8480312e-05 | AU58: 8.9510469e-05
B59: Argentina
A60: INTL.44-2-ARG-QBTU.A | B60: Consumption (quad Btu) | C60: 1.6174294 | D60: 1.5749029 | E60: 1.6397213 | F60: 1.66277 | G60: 1.7707733 | H60: 1.7030292 | I60: 1.8372851 | J60: 1.8405361 | K60: 1.8698282 | L60: 1.8799815 | M60: 1.7877184 | N60: 1.8681303 | O60: 1.9190324 | P60: 2.1047633 | Q60: 2.0463888 | R60: 2.1158194 | S60: 2.2471811 | T60: 2.302305 | U60: 2.4667711 | V60: 2.4137175 | W60: 2.5770681 | X60: 2.4766727 | Y60: 2.3321735 | Z60: 2.5783861 | AA60: 2.8255287 | AB60: 2.934261 | AC60: 3.0695186 | AD60: 3.2166659 | AE60: 3.3671244 | AF60: 3.2450423 | AG60: 3.4086194 | AH60: 3.4969442 | AI60: 3.5667223 | AJ60: 3.6054351 | AK60: 3.6194674 | AL60: 3.6843411 | AM60: 3.6954621 | AN60: 3.5162973 | AO60: 3.399836 | AP60: 3.5893896 | AQ60: 3.1936978 | AR60: 3.5213344 | AS60: 3.5810276 | AT60: 3.5008852 | AU60: 3.565998
A61: INTL.4411-2-ARG-QBTU.A | B61: Coal (quad Btu) | C61: 0.059209116 | D61: 0.051000648 | E61: 0.05418197 | F61: 0.049023168 | G61: 0.038002631 | H61: 0.053120068 | I61: 0.068062083 | J61: 0.072483771 | K61: 0.069226045 | L61: 0.079583941 | M61: 0.071234834 | N61: 0.056531257 | O61: 0.055898037 | P61: 0.046990011 | Q61: 0.057884088 | R61: 0.053612003 | S61: 0.05506655 | T61: 0.053321404 | U61: 0.053893331 | V61: 0.053508993 | W61: 0.046201216 | X61: 0.044493776 | Y61: 0.041339662 | Z61: 0.050477762 | AA61: 0.06234517 | AB61: 0.065320777 | AC61: 0.06245425 | AD61: 0.073087915 | AE61: 0.085735862 | AF61: 0.057883227 | AG61: 0.068433824 | AH61: 0.070676341 | AI61: 0.070946478 | AJ61: 0.079071062 | AK61: 0.077021582 | AL61: 0.07518055 | AM61: 0.065182632 | AN61: 0.068196627 | AO61: 0.063519004 | AP61: 0.043613605 | AQ61: 0.049035331 | AR61: 0.074452598 | AS61: 0.057088302 | AT61: 0.042040568 | AU61: 0.027356707
A62: INTL.4413-2-ARG-QBTU.A | B62: Natural gas (quad Btu) | C62: 0.368334 | D62: 0.371412 | E62: 0.467856 | F62: 0.460674 | G62: 0.586872 | H62: 0.593028 | I62: 0.64125 | J62: 0.62073 | K62: 0.731538 | L62: 0.821826 | M62: 0.73517004 | N62: 0.81594645 | O62: 0.82259265 | P62: 0.87057383 | Q62: 0.89492755 | R62: 0.99604175 | S62: 1.0558284 | T62: 1.0532452 | U62: 1.1259464 | V62: 1.1942191 | W62: 1.2255877 | X62: 1.1521483 | Y62: 1.1170894 | Z62: 1.2761464 | AA62: 1.3990373 | AB62: 1.4924048 | AC62: 1.5411183 | AD62: 1.6208314 | AE62: 1.6389144 | AF62: 1.5920461 | AG62: 1.5975817 | AH62: 1.7023896 | AI62: 1.7138299 | AJ62: 1.7224286 | AK62: 1.7373748 | AL62: 1.7341272 | AM62: 1.7872318 | AN62: 1.810186 | AO62: 1.8156987 | AP62: 1.8854976 | AQ62: 1.7542453 | AR62: 1.7298979 | AS62: 1.7338824 | AT62: 1.6659388 | AU62: 1.7212026
A63: INTL.4415-2-ARG-QBTU.A | B63: Petroleum and other liquids (quad Btu) | C63: 1.1020519 | D63: 1.0628365 | E63: 1.0303121 | F63: 1.0502004 | G63: 1.0244475 | H63: 0.92199108 | I63: 0.99245344 | J63: 0.99942977 | K63: 0.95900218 | L63: 0.87537702 | M63: 0.83403077 | N63: 0.84526898 | O63: 0.88332017 | P63: 1.0124313 | Q63: 0.90338261 | R63: 0.88432854 | S63: 0.96253758 | T63: 0.99225108 | U63: 1.0820342 | V63: 0.99065271 | W63: 1.1268069 | X63: 1.0659743 | Y63: 0.95948738 | Z63: 1.0271127 | AA63: 1.1479248 | AB63: 1.1576204 | AC63: 1.2272817 | AD63: 1.2965953 | AE63: 1.4223934 | AF63: 1.3557148 | AG63: 1.5004415 | AH63: 1.4947934 | AI63: 1.56194 | AJ63: 1.5690593 | AK63: 1.5761607 | AL63: 1.6340337 | AM63: 1.595071 | AN63: 1.4027048 | AO63: 1.2757995 | AP63: 1.3982756 | AQ63: 1.1177446 | AR63: 1.4479369 | AS63: 1.4967228 | AT63: 1.4730775 | AU63: 1.4565866
A64: INTL.4419-2-ARG-QBTU.A | B64: Nuclear, renewables, and other (quad Btu) | C64: 0.087834387 | D64: 0.089653764 | E64: 0.087371249 | F64: 0.10287242 | G64: 0.12145115 | H64: 0.13489001 | I64: 0.13551961 | J64: 0.14789255 | K64: 0.11006193 | L64: 0.10319451 | M64: 0.14728277 | N64: 0.15038358 | O64: 0.15722157 | P64: 0.17476819 | Q64: 0.1901946 | R64: 0.18183709 | S64: 0.17374854 | T64: 0.20348735 | U64: 0.20489713 | V64: 0.17533668 | W64: 0.17847234 | X64: 0.21405632 | Y64: 0.21425713 | Z64: 0.22464921 | AA64: 0.21622141 | AB64: 0.21891503 | AC64: 0.23866428 | AD64: 0.22615133 | AE64: 0.22008065 | AF64: 0.23939817 | AG64: 0.24216237 | AH64: 0.22908478 | AI64: 0.22000596 | AJ64: 0.2348761 | AK64: 0.22891037 | AL64: 0.24099967 | AM64: 0.24797664 | AN64: 0.23520984 | AO64: 0.24481875 | AP64: 0.26200281 | AQ64: 0.27267255 | AR64: 0.26904701 | AS64: 0.29333411 | AT64: 0.31982829 | AU64: 0.36085212
A65: INTL.4417-2-ARG-QBTU.A | B65: Nuclear (quad Btu) | C65: 0.025890133 | D65: 0.031151668 | E65: 0.020680602 | F65: 0.038141423 | G65: 0.05068204 | H65: 0.064178204 | I65: 0.063575869 | J65: 0.072522079 | K65: 0.05721698 | L65: 0.05653203 | M65: 0.083020716 | N65: 0.090874027 | O65: 0.079655011 | P65: 0.086386421 | Q65: 0.092385642 | R65: 0.082759793 | S65: 0.081003928 | T65: 0.087207986 | U65: 0.08340361 | V65: 0.078955418 | W65: 0.070059033 | X65: 0.076567441 | Y65: 0.0630941 | Z65: 0.082291562 | AA65: 0.085604295 | AB65: 0.074565754 | AC65: 0.083731372 | AD65: 0.078686185 | AE65: 0.080184524 | AF65: 0.088846793 | AG65: 0.078323306 | AH65: 0.068993808 | AI65: 0.06909916 | AJ65: 0.067092791 | AK65: 0.06144228 | AL65: 0.077639531 | AM65: 0.09138283 | AN65: 0.06743226 | AO65: 0.076122755 | AP65: 0.093127473 | AQ65: 0.11765454 | AR65: 0.11888903 | AS65: 0.087290498 | AT65: 0.10477899 | AU65: 0.12215058
A66: INTL.4418-2-ARG-QBTU.A | B66: Renewables and other (quad Btu) | C66: 0.061944254 | D66: 0.058502096 | E66: 0.066690647 | F66: 0.064730995 | G66: 0.070769109 | H66: 0.070711803 | I66: 0.071943742 | J66: 0.075370475 | K66: 0.052844948 | L66: 0.046662476 | M66: 0.064262052 | N66: 0.059509552 | O66: 0.077566556 | P66: 0.088381772 | Q66: 0.09780896 | R66: 0.099077294 | S66: 0.092744613 | T66: 0.11627937 | U66: 0.12149352 | V66: 0.096381262 | W66: 0.10841331 | X66: 0.13748888 | Y66: 0.15116303 | Z66: 0.14235765 | AA66: 0.13061711 | AB66: 0.14434927 | AC66: 0.1549329 | AD66: 0.14746515 | AE66: 0.13989613 | AF66: 0.15055138 | AG66: 0.16383907 | AH66: 0.16009097 | AI66: 0.1509068 | AJ66: 0.16778331 | AK66: 0.16746809 | AL66: 0.16336014 | AM66: 0.15659381 | AN66: 0.16777758 | AO66: 0.16869599 | AP66: 0.16887534 | AQ66: 0.155018 | AR66: 0.15015798 | AS66: 0.20604361 | AT66: 0.2150493 | AU66: 0.23870153
B67: Armenia
A68: INTL.44-2-ARM-QBTU.A | B68: Consumption (quad Btu) | C68: -- | D68: -- | E68: -- | F68: -- | G68: -- | H68: -- | I68: -- | J68: -- | K68: -- | L68: -- | M68: -- | N68: -- | O68: 0.17619472 | P68: 0.12068256 | Q68: 0.11006542 | R68: 0.11841146 | S68: 0.15758119 | T68: 0.13252743 | U68: 0.14045869 | V68: 0.0850982 | W68: 0.091591731 | X68: 0.09193771 | Y68: 0.083343954 | Z68: 0.090654978 | AA68: 0.094623781 | AB68: 0.11329356 | AC68: 0.11309963 | AD68: 0.12831685 | AE68: 0.12339012 | AF68: 0.1078196 | AG68: 0.11825812 | AH68: 0.12525229 | AI68: 0.13568603 | AJ68: 0.13369839 | AK68: 0.13769038 | AL68: 0.12582078 | AM68: 0.12616846 | AN68: 0.13585433 | AO68: 0.13329764 | AP68: 0.14118787 | AQ68: 0.1526505 | AR68: 0.15647268 | AS68: 0.16902117 | AT68: 0.16509011 | AU68: 0.16985684
A69: INTL.4411-2-ARM-QBTU.A | B69: Coal (quad Btu) | C69: -- | D69: -- | E69: -- | F69: -- | G69: -- | H69: -- | I69: -- | J69: -- | K69: -- | L69: -- | M69: -- | N69: -- | O69: 0.0034480893 | P69: 0.0021642263 | Q69: 0.00088036325 | R69: 0.000501318 | S69: 0.00039429094 | T69: 0.00028726388 | U69: 0.00018023683 | V69: 0.00012409533 | W69: 5.9609568e-05 | X69: 4.6009365e-05 | Y69: 4.4018152e-05 | Z69: 6.6809536e-05 | AA69: 3.8799312e-05 | AB69: 1.6971426e-05 | AC69: 2.736459e-05 | AD69: 6.6760796e-05 | AE69: 6.1331896e-05 | AF69: 8.7547124e-06 | AG69: 5.6832267e-05 | AH69: 7.3681421e-05 | AI69: 6.4804436e-05 | AJ69: 3.0938567e-05 | AK69: 2.4570962e-05 | AL69: 2.7496573e-05 | AM69: 2.8300834e-05 | AN69: 3.7205414e-05 | AO69: 4.4048549e-05 | AP69: 0.00011220672 | AQ69: 0.00031190391 | AR69: 0.00046823975 | AS69: 0.00058569645 | AT69: 0.00046206997 | AU69: 0.00065735831
A70: INTL.4413-2-ARM-QBTU.A | B70: Natural gas (quad Btu) | C70: -- | D70: -- | E70: -- | F70: -- | G70: -- | H70: -- | I70: -- | J70: -- | K70: -- | L70: -- | M70: -- | N70: -- | O70: 0.068773137 | P70: 0.05176368 | Q70: 0.0591555 | R70: 0.0591555 | S70: 0.06655779 | T70: 0.048067247 | U70: 0.051764727 | V70: 0.047697498 | W70: 0.052134475 | X70: 0.051764727 | Y70: 0.040302537 | Z70: 0.048806743 | AA70: 0.049176491 | AB70: 0.062857169 | AC70: 0.062857169 | AD70: 0.075946249 | AE70: 0.071361374 | AF70: 0.057310948 | AG70: 0.067294145 | AH70: 0.076537846 | AI70: 0.090588272 | AJ70: 0.08910928 | AK70: 0.092437012 | AL70: 0.07579835 | AM70: 0.081935472 | AN70: 0.087037952 | AO70: 0.091778387 | AP70: 0.092362389 | AQ70: 0.094077841 | AR70: 0.10047758 | AS70: 0.10163816 | AT70: 0.098179882 | AU70: 0.098426396
A71: INTL.4415-2-ARM-QBTU.A | B71: Petroleum and other liquids (quad Btu) | C71: -- | D71: -- | E71: -- | F71: -- | G71: -- | H71: -- | I71: -- | J71: -- | K71: -- | L71: -- | M71: -- | N71: -- | O71: 0.092761236 | P71: 0.052314464 | Q71: 0.03809048 | R71: 0.052220397 | S71: 0.060696298 | T71: 0.063133457 | U71: 0.067990695 | V71: 0.0096664975 | W71: 0.015144154 | X71: 0.014825452 | Y71: 0.014099655 | Z71: 0.01468813 | AA71: 0.0153704 | AB71: 0.017728439 | AC71: 0.016701467 | AD71: 0.018180113 | AE71: 0.019402329 | AF71: 0.016953905 | AG71: 0.018088891 | AH71: 0.017117174 | AI71: 0.017722238 | AJ71: 0.015759131 | AK71: 0.015696952 | AL71: 0.016651356 | AM71: 0.013772 | AN71: 0.016653142 | AO71: 0.016173669 | AP71: 0.01996326 | AQ71: 0.02525237 | AR71: 0.02745376 | AS71: 0.02938194 | AT71: 0.03263132 | AU71: 0.03486621
A72: INTL.4419-2-ARM-QBTU.A | B72: Nuclear, renewables, and other (quad Btu) | C72: -- | D72: -- | E72: -- | F72: -- | G72: -- | H72: -- | I72: -- | J72: -- | K72: -- | L72: -- | M72: -- | N72: -- | O72: 0.011212259 | P72: 0.014440186 | Q72: 0.011939081 | R72: 0.0065342491 | S72: 0.029932814 | T72: 0.021039465 | U72: 0.020523027 | V72: 0.027610109 | W72: 0.024253492 | X72: 0.025301522 | Y72: 0.028897744 | Z72: 0.027093296 | AA72: 0.03003809 | AB72: 0.032690979 | AC72: 0.033513632 | AD72: 0.03412373 | AE72: 0.032565089 | AF72: 0.033545992 | AG72: 0.032818255 | AH72: 0.03152359 | AI72: 0.02731072 | AJ72: 0.02879904 | AK72: 0.029531849 | AL72: 0.03334358 | AM72: 0.030432685 | AN72: 0.032126027 | AO72: 0.025301535 | AP72: 0.028750014 | AQ72: 0.033008381 | AR72: 0.028073103 | AS72: 0.037415366 | AT72: 0.03381684 | AU72: 0.035906876
A73: INTL.4417-2-ARM-QBTU.A | B73: Nuclear (quad Btu) | C73: -- | D73: -- | E73: -- | F73: -- | G73: -- | H73: -- | I73: -- | J73: -- | K73: -- | L73: -- | M73: -- | N73: -- | O73: 0 | P73: 0 | Q73: 0 | R73: 0 | S73: 0.024623522 | T73: 0.016767446 | U73: 0.016650191 | V73: 0.024389012 | W73: 0.021574896 | X73: 0.023298542 | Y73: 0.024506267 | Z73: 0.021340386 | AA73: 0.025854698 | AB73: 0.029360619 | AC73: 0.028399129 | AD73: 0.027529098 | AE73: 0.026569953 | AF73: 0.026851365 | AG73: 0.026816188 | AH73: 0.027636972 | AI73: 0.024904934 | AJ73: 0.025420855 | AK73: 0.026569953 | AL73: 0.030146226 | AM73: 0.025737443 | AN73: 0.028270148 | AO73: 0.022254974 | AP73: 0.023791013 | AQ73: 0.029923661 | AR73: 0.021692309 | AS73: 0.030849982 | AT73: 0.029454638 | AU73: 0.03082653
A74: INTL.4418-2-ARM-QBTU.A | B74: Renewables and other (quad Btu) | C74: -- | D74: -- | E74: -- | F74: -- | G74: -- | H74: -- | I74: -- | J74: -- | K74: -- | L74: -- | M74: -- | N74: -- | O74: 0.011212259 | P74: 0.014440186 | Q74: 0.011939081 | R74: 0.0065342491 | S74: 0.0053092924 | T74: 0.0042720189 | U74: 0.0038728356 | V74: 0.0032210963 | W74: 0.0026785968 | X74: 0.0020029797 | Y74: 0.0043914764 | Z74: 0.0057529099 | AA74: 0.0041833922 | AB74: 0.0033303607 | AC74: 0.0051145029 | AD74: 0.0065946326 | AE74: 0.0059951362 | AF74: 0.0066946277 | AG74: 0.0060020673 | AH74: 0.0038866174 | AI74: 0.0024057862 | AJ74: 0.0033781852 | AK74: 0.0029618959 | AL74: 0.0031973538 | AM74: 0.004695242 | AN74: 0.0038558788 | AO74: 0.0030465616 | AP74: 0.0049590011 | AQ74: 0.0030847195 | AR74: 0.0063807937 | AS74: 0.0065653841 | AT74: 0.0043622014 | AU74: 0.0050803458
B75: Aruba
A76: INTL.44-2-ABW-QBTU.A | B76: Consumption (quad Btu) | C76: -- | D76: -- | E76: -- | F76: -- | G76: -- | H76: -- | I76: 0.001453868 | J76: 0.001453868 | K76: 0.0055701525 | L76: 0.0074044995 | M76: 0.0078206752 | N76: 0.0085313063 | O76: 0.0093710136 | P76: 0.009521171 | Q76: 0.010446587 | R76: 0.01182344 | S76: 0.0077925777 | T76: 0.01260235 | U76: 0.01260235 | V76: 0.012602367 | W76: 0.015072691 | X76: 0.015595912 | Y76: 0.01612162 | Z76: 0.017952978 | AA76: 0.018721994 | AB76: 0.020217968 | AC76: 0.02017945 | AD76: 0.020794461 | AE76: 0.019534151 | AF76: 0.019284482 | AG76: 0.017608694 | AH76: 0.013828724 | AI76: 0.017391996 | AJ76: 0.016709129 | AK76: 0.016928828 | AL76: 0.017388125 | AM76: 0.017059052 | AN76: 0.01770077 | AO76: 0.016737022 | AP76: 0.015944077 | AQ76: 0.015587397 | AR76: 0.016472457 | AS76: 0.016855287 | AT76: 0.01666362 | AU76: 0.016806703
A77: INTL.4411-2-ABW-QBTU.A | B77: Coal (quad Btu) | C77: -- | D77: -- | E77: -- | F77: -- | G77: -- | H77: -- | I77: 0 | J77: 0 | K77: 0 | L77: 0 | M77: 0 | N77: 0 | O77: 0 | P77: 0 | Q77: 0 | R77: 0 | S77: 0 | T77: 0 | U77: 0 | V77: 0 | W77: 0 | X77: 0 | Y77: 0 | Z77: 0 | AA77: 0 | AB77: 0 | AC77: 0 | AD77: 0 | AE77: 0 | AF77: 0 | AG77: 0 | AH77: 0 | AI77: 0 | AJ77: 0 | AK77: 0 | AL77: 0 | AM77: 0 | AN77: 0 | AO77: 0 | AP77: 0 | AQ77: 0 | AR77: 0 | AS77: 0 | AT77: 0 | AU77: 0
A78: INTL.4413-2-ABW-QBTU.A | B78: Natural gas (quad Btu) | C78: -- | D78: -- | E78: -- | F78: -- | G78: -- | H78: -- | I78: 0 | J78: 0 | K78: 0 | L78: 0 | M78: 0 | N78: 0 | O78: 0 | P78: 0 | Q78: 0 | R78: 0 | S78: 0 | T78: 0 | U78: 0 | V78: 0 | W78: 0 | X78: 0 | Y78: 0 | Z78: 0 | AA78: 0 | AB78: 0 | AC78: 0 | AD78: 0 | AE78: 0 | AF78: 0 | AG78: 0 | AH78: 0 | AI78: 0 | AJ78: 0 | AK78: 0 | AL78: 0 | AM78: 0 | AN78: 0 | AO78: 0 | AP78: 0 | AQ78: 0 | AR78: 0 | AS78: 0 | AT78: 0 | AU78: 0
A79: INTL.4415-2-ABW-QBTU.A | B79: Petroleum and other liquids (quad Btu) | C79: -- | D79: -- | E79: -- | F79: -- | G79: -- | H79: -- | I79: 0.001453868 | J79: 0.001453868 | K79: 0.0055701525 | L79: 0.0074044995 | M79: 0.0078206752 | N79: 0.0085313063 | O79: 0.0093710136 | P79: 0.009521171 | Q79: 0.010446587 | R79: 0.01182344 | S79: 0.0077925777 | T79: 0.01260235 | U79: 0.01260235 | V79: 0.012602367 | W79: 0.015072691 | X79: 0.015595912 | Y79: 0.01612162 | Z79: 0.017952978 | AA79: 0.018721994 | AB79: 0.020217968 | AC79: 0.02017945 | AD79: 0.020794461 | AE79: 0.019534151 | AF79: 0.019182118 | AG79: 0.017246666 | AH79: 0.013441446 | AI79: 0.016927945 | AJ79: 0.016187071 | AK79: 0.016386298 | AL79: 0.016791 | AM79: 0.016521 | AN79: 0.017210446 | AO79: 0.01620814 | AP79: 0.01539131 | AQ79: 0.01503463 | AR79: 0.01591969 | AS79: 0.01630252 | AT79: 0.01611085 | AU79: 0.016241466
A80: INTL.4419-2-ABW-QBTU.A | B80: Nuclear, renewables, and other (quad Btu) | C80: -- | D80: -- | E80: -- | F80: -- | G80: -- | H80: -- | I80: 0 | J80: 0 | K80: 0 | L80: 0 | M80: 0 | N80: 0 | O80: 0 | P80: 0 | Q80: 0 | R80: 0 | S80: 0 | T80: 0 | U80: 0 | V80: 0 | W80: 0 | X80: 0 | Y80: 0 | Z80: 0 | AA80: 0 | AB80: 0 | AC80: 0 | AD80: 0 | AE80: 0 | AF80: 0.00010236425 | AG80: 0.00036202823 | AH80: 0.00038727808 | AI80: 0.00046405126 | AJ80: 0.00052205767 | AK80: 0.00054253052 | AL80: 0.00059712479 | AM80: 0.00053805233 | AN80: 0.00049032475 | AO80: 0.00052888195 | AP80: 0.00055276694 | AQ80: 0.00055276694 | AR80: 0.00055276694 | AS80: 0.00055276694 | AT80: 0.00055276985 | AU80: 0.00056523701
A81: INTL.4417-2-ABW-QBTU.A | B81: Nuclear (quad Btu) | C81: -- | D81: -- | E81: -- | F81: -- | G81: -- | H81: -- | I81: 0 | J81: 0 | K81: 0 | L81: 0 | M81: 0 | N81: 0 | O81: 0 | P81: 0 | Q81: 0 | R81: 0 | S81: 0 | T81: 0 | U81: 0 | V81: 0 | W81: 0 | X81: 0 | Y81: 0 | Z81: 0 | AA81: 0 | AB81: 0 | AC81: 0 | AD81: 0 | AE81: 0 | AF81: 0 | AG81: 0 | AH81: 0 | AI81: 0 | AJ81: 0 | AK81: 0 | AL81: 0 | AM81: 0 | AN81: 0 | AO81: 0 | AP81: 0 | AQ81: 0 | AR81: 0 | AS81: 0 | AT81: 0 | AU81: 0
A82: INTL.4418-2-ABW-QBTU.A | B82: Renewables and other (quad Btu) | C82: -- | D82: -- | E82: -- | F82: -- | G82: -- | H82: -- | I82: 0 | J82: 0 | K82: 0 | L82: 0 | M82: 0 | N82: 0 | O82: 0 | P82: 0 | Q82: 0 | R82: 0 | S82: 0 | T82: 0 | U82: 0 | V82: 0 | W82: 0 | X82: 0 | Y82: 0 | Z82: 0 | AA82: 0 | AB82: 0 | AC82: 0 | AD82: 0 | AE82: 0 | AF82: 0.00010236425 | AG82: 0.00036202823 | AH82: 0.00038727808 | AI82: 0.00046405126 | AJ82: 0.00052205767 | AK82: 0.00054253052 | AL82: 0.00059712479 | AM82: 0.00053805233 | AN82: 0.00049032475 | AO82: 0.00052888195 | AP82: 0.00055276694 | AQ82: 0.00055276694 | AR82: 0.00055276694 | AS82: 0.00055276694 | AT82: 0.00055276985 | AU82: 0.00056523701
B83: Australia
A84: INTL.44-2-AUS-QBTU.A | B84: Consumption (quad Btu) | C84: 2.9529332 | D84: 3.0072894 | E84: 3.1576973 | F84: 3.0213708 | G84: 3.0652412 | H84: 3.1942775 | I84: 3.2383584 | J84: 3.4158228 | K84: 3.507619 | L84: 3.7198175 | M84: 3.618888 | N84: 3.5790342 | O84: 3.6590325 | P84: 3.7441788 | Q84: 3.8128923 | R84: 3.9405536 | S84: 4.1308937 | T84: 4.2354212 | U84: 4.4091659 | V84: 4.5229269 | W84: 4.5625963 | X84: 4.6008269 | Y84: 4.7640552 | Z84: 4.7932278 | AA84: 4.9580999 | AB84: 5.0475559 | AC84: 5.1108727 | AD84: 5.2706086 | AE84: 5.2817189 | AF84: 5.4075216 | AG84: 5.4315911 | AH84: 5.4828233 | AI84: 5.5646517 | AJ84: 5.5274035 | AK84: 5.4359772 | AL84: 5.4768782 | AM84: 5.6707741 | AN84: 5.6739453 | AO84: 5.7986195 | AP84: 6.0562333 | AQ84: 5.6459155 | AR84: 5.7643294 | AS84: 6.0460747 | AT84: 5.9802403 | AU84: 5.9926708
A85: INTL.4411-2-AUS-QBTU.A | B85: Coal (quad Btu) | C85: 1.3439878 | D85: 1.3732791 | E85: 1.4155904 | F85: 1.3250994 | G85: 1.2670145 | H85: 1.3625131 | I85: 1.3542805 | J85: 1.4887685 | K85: 1.5008402 | L85: 1.6395307 | M85: 1.4543722 | N85: 1.488688 | O85: 1.5275744 | P85: 1.5224962 | Q85: 1.5061404 | R85: 1.5368333 | S85: 1.671813 | T85: 1.7352251 | U85: 1.8650177 | V85: 1.8979992 | W85: 1.8989455 | X85: 1.8964415 | Y85: 1.9247938 | Z85: 1.8556488 | AA85: 1.9400435 | AB85: 1.96998 | AC85: 2.0040284 | AD85: 2.0213485 | AE85: 1.9997295 | AF85: 2.0460075 | AG85: 1.9611024 | AH85: 1.8809353 | AI85: 1.8457058 | AJ85: 1.7197521 | AK85: 1.6238852 | AL85: 1.6785607 | AM85: 1.7333866 | AN85: 1.713647 | AO85: 1.7500546 | AP85: 1.6969313 | AQ85: 1.6029476 | AR85: 1.6707524 | AS85: 1.6568288 | AT85: 1.5327703 | AU85: 1.5042182
A86: INTL.4413-2-AUS-QBTU.A | B86: Natural gas (quad Btu) | C86: 0.339066 | D86: 0.387504 | E86: 0.428571 | F86: 0.434889 | G86: 0.46376 | H86: 0.495873 | I86: 0.541284 | J86: 0.554876 | K86: 0.578865 | L86: 0.59451 | M86: 0.6525 | N86: 0.61028 | O86: 0.63208429 | P86: 0.65788704 | Q86: 0.68776104 | R86: 0.73807785 | S86: 0.74076567 | T86: 0.74599085 | U86: 0.78171024 | V86: 0.80919626 | W86: 0.84955254 | X86: 0.89576868 | Y86: 0.98473857 | Z86: 1.0134994 | AA86: 1.0523087 | AB86: 1.0618055 | AC86: 1.0609042 | AD86: 1.1786191 | AE86: 1.2007871 | AF86: 1.2615562 | AG86: 1.2775942 | AH86: 1.2984352 | AI86: 1.345778 | AJ86: 1.3874006 | AK86: 1.4179842 | AL86: 1.4373514 | AM86: 1.5615189 | AN86: 1.4701008 | AO86: 1.4877377 | AP86: 1.8001355 | AQ86: 1.775212 | AR86: 1.732626 | AS86: 1.8893775 | AT86: 1.8042293 | AU86: 1.7766294
A87: INTL.4415-2-AUS-QBTU.A | B87: Petroleum and other liquids (quad Btu) | C87: 1.2252791 | D87: 1.1953411 | E87: 1.2626197 | F87: 1.2163253 | G87: 1.2898331 | H87: 1.2858451 | I87: 1.2954069 | J87: 1.326614 | K87: 1.3968562 | L87: 1.4509441 | M87: 1.4754598 | N87: 1.4426887 | O87: 1.4600191 | P87: 1.5167038 | Q87: 1.570986 | R87: 1.6151446 | S87: 1.6653114 | T87: 1.6944362 | U87: 1.7019527 | V87: 1.7486541 | W87: 1.7487927 | X87: 1.7420214 | Y87: 1.7879293 | Z87: 1.8572435 | AA87: 1.8985874 | AB87: 1.9279186 | AC87: 1.9528863 | AD87: 1.989093 | AE87: 2.0156035 | AF87: 2.0281699 | AG87: 2.116068 | AH87: 2.2180091 | AI87: 2.284967 | AJ87: 2.3091387 | AK87: 2.269492 | AL87: 2.2439916 | AM87: 2.2345939 | AN87: 2.335261 | AO87: 2.3846378 | AP87: 2.3495653 | AQ87: 2.0367979 | AR87: 2.081794 | AS87: 2.1830251 | AT87: 2.2942982 | AU87: 2.3611092
A88: INTL.4419-2-AUS-QBTU.A | B88: Nuclear, renewables, and other (quad Btu) | C88: 0.044600346 | D88: 0.051165286 | E88: 0.050916223 | F88: 0.045057062 | G88: 0.044633511 | H88: 0.050046261 | I88: 0.047386956 | J88: 0.045564307 | K88: 0.031057523 | L88: 0.034832674 | M88: 0.036556012 | N88: 0.037377515 | O88: 0.039354691 | P88: 0.047091701 | Q88: 0.048004872 | R88: 0.050497719 | S88: 0.053003698 | T88: 0.059769082 | U88: 0.060485254 | V88: 0.067077377 | W88: 0.065305549 | X88: 0.066595344 | Y88: 0.06659361 | Z88: 0.066836185 | AA88: 0.067160272 | AB88: 0.087851874 | AC88: 0.093053847 | AD88: 0.081548039 | AE88: 0.065598797 | AF88: 0.071788015 | AG88: 0.076826615 | AH88: 0.085443765 | AI88: 0.088201042 | AJ88: 0.11111202 | AK88: 0.12461574 | AL88: 0.11697463 | AM88: 0.14127473 | AN88: 0.15493646 | AO88: 0.17618947 | AP88: 0.20960124 | AQ88: 0.23095806 | AR88: 0.27915692 | AS88: 0.31684333 | AT88: 0.34894254 | AU88: 0.35071408
A89: INTL.4417-2-AUS-QBTU.A | B89: Nuclear (quad Btu) | C89: 0 | D89: 0 | E89: 0 | F89: 0 | G89: 0 | H89: 0 | I89: 0 | J89: 0 | K89: 0 | L89: 0 | M89: 0 | N89: 0 | O89: 0 | P89: 0 | Q89: 0 | R89: 0 | S89: 0 | T89: 0 | U89: 0 | V89: 0 | W89: 0 | X89: 0 | Y89: 0 | Z89: 0 | AA89: 0 | AB89: 0 | AC89: 0 | AD89: 0 | AE89: 0 | AF89: 0 | AG89: 0 | AH89: 0 | AI89: 0 | AJ89: 0 | AK89: 0 | AL89: 0 | AM89: 0 | AN89: 0 | AO89: 0 | AP89: 0 | AQ89: 0 | AR89: 0 | AS89: 0 | AT89: 0 | AU89: 0
A90: INTL.4418-2-AUS-QBTU.A | B90: Renewables and other (quad Btu) | C90: 0.044600346 | D90: 0.051165286 | E90: 0.050916223 | F90: 0.045057062 | G90: 0.044633511 | H90: 0.050046261 | I90: 0.047386956 | J90: 0.045564307 | K90: 0.031057523 | L90: 0.034832674 | M90: 0.036556012 | N90: 0.037377515 | O90: 0.039354691 | P90: 0.047091701 | Q90: 0.048004872 | R90: 0.050497719 | S90: 0.053003698 | T90: 0.059769082 | U90: 0.060485254 | V90: 0.067077377 | W90: 0.065305549 | X90: 0.066595344 | Y90: 0.06659361 | Z90: 0.066836185 | AA90: 0.067160272 | AB90: 0.087851874 | AC90: 0.093053847 | AD90: 0.081548039 | AE90: 0.065598797 | AF90: 0.071788015 | AG90: 0.076826615 | AH90: 0.085443765 | AI90: 0.088201042 | AJ90: 0.11111202 | AK90: 0.12461574 | AL90: 0.11697463 | AM90: 0.14127473 | AN90: 0.15493646 | AO90: 0.17618947 | AP90: 0.20960124 | AQ90: 0.23095806 | AR90: 0.27915692 | AS90: 0.31684333 | AT90: 0.34894254 | AU90: 0.35071408
B91: Austria
A92: INTL.44-2-AUT-QBTU.A | B92: Consumption (quad Btu) | C92: 0.89856379 | D92: 0.87473959 | E92: 0.82292177 | F92: 0.83048377 | G92: 0.86923295 | H92: 0.87877005 | I92: 0.85714451 | J92: 0.84376895 | K92: 0.863969 | L92: 0.87920751 | M92: 0.9404268 | N92: 1.0007426 | O92: 0.95509311 | P92: 0.96873405 | Q92: 0.97072086 | R92: 1.0184497 | S92: 1.0933443 | T92: 1.0853194 | U92: 1.1030292 | V92: 1.0941019 | W92: 1.0759976 | X92: 1.1442246 | Y92: 1.151357 | Z92: 1.2215423 | AA92: 1.2500379 | AB92: 1.304552 | AC92: 1.2999577 | AD92: 1.2638327 | AE92: 1.2622074 | AF92: 1.1854333 | AG92: 1.248979 | AH92: 1.202366 | AI92: 1.1922828 | AJ92: 1.204534 | AK92: 1.1593218 | AL92: 1.1856582 | AM92: 1.2031967 | AN92: 1.235349 | AO92: 1.213493 | AP92: 1.2452612 | AQ92: 1.1420476 | AR92: 1.2030745 | AS92: 1.1353163 | AT92: 1.0884802 | AU92: 1.0674109
A93: INTL.4411-2-AUT-QBTU.A | B93: Coal (quad Btu) | C93: 0.10024752 | D93: 0.10460161 | E93: 0.094376028 | F93: 0.10259439 | G93: 0.12371669 | H93: 0.11753387 | I93: 0.094748649 | J93: 0.10035299 | K93: 0.09586051 | L93: 0.098710603 | M93: 0.11677069 | N93: 0.12537459 | O93: 0.087391312 | P93: 0.076106556 | Q93: 0.079204976 | R93: 0.097136882 | S93: 0.10568701 | T93: 0.10481691 | U93: 0.087377175 | V93: 0.097609864 | W93: 0.097155545 | X93: 0.10767627 | Y93: 0.10181437 | Z93: 0.11721726 | AA93: 0.1189578 | AB93: 0.11697511 | AC93: 0.10983819 | AD93: 0.096220617 | AE93: 0.090998576 | AF93: 0.073064317 | AG93: 0.084513498 | AH93: 0.086597043 | AI93: 0.080895012 | AJ93: 0.081812187 | AK93: 0.077223866 | AL93: 0.091476382 | AM93: 0.085730542 | AN93: 0.084691891 | AO93: 0.080961855 | AP93: 0.07779845 | AQ93: 0.069798919 | AR93: 0.068126869 | AS93: 0.072505988 | AT93: 0.078281711 | AU93: 0.064179142
A94: INTL.4413-2-AUT-QBTU.A | B94: Natural gas (quad Btu) | C94: 0.185256 | D94: 0.172515 | E94: 0.16709 | F94: 0.170345 | G94: 0.188825 | H94: 0.202852 | I94: 0.196378 | J94: 0.20501 | K94: 0.195299 | L94: 0.20943 | M94: 0.23091 | N94: 0.24168 | O94: 0.23733093 | P94: 0.25031524 | Q94: 0.25763931 | R94: 0.27854852 | S94: 0.2992301 | T94: 0.28838109 | U94: 0.29607676 | V94: 0.30107323 | W94: 0.27259959 | X94: 0.2886807 | Y94: 0.29193943 | Z94: 0.31567146 | AA94: 0.31533766 | AB94: 0.35990216 | AC94: 0.33764025 | AD94: 0.31842554 | AE94: 0.33645505 | AF94: 0.32841608 | AG94: 0.35814497 | AH94: 0.33802284 | AI94: 0.32303982 | AJ94: 0.31130138 | AK94: 0.2841554 | AL94: 0.30321569 | AM94: 0.31665142 | AN94: 0.34370915 | AO94: 0.32021695 | AP94: 0.33444363 | AQ94: 0.31950509 | AR94: 0.33837193 | AS94: 0.2966094 | AT94: 0.25419695 | AU94: 0.25124519
A95: INTL.4415-2-AUT-QBTU.A | B95: Petroleum and other liquids (quad Btu) | C95: 0.49776443 | D95: 0.4791052 | E95: 0.44382942 | F95: 0.43741125 | G95: 0.42524347 | H95: 0.41506322 | I95: 0.43179073 | J95: 0.43776751 | K95: 0.42647761 | L95: 0.42592183 | M95: 0.45216074 | N95: 0.48610638 | O95: 0.47699282 | P95: 0.4896611 | Q95: 0.48555798 | R95: 0.48556928 | S95: 0.53212148 | T95: 0.53184709 | U95: 0.55637103 | V95: 0.52736396 | W95: 0.52419903 | X95: 0.55915632 | Y95: 0.57023475 | Z95: 0.60257284 | AA95: 0.61794887 | AB95: 0.62108036 | AC95: 0.62919622 | AD95: 0.60906921 | AE95: 0.5940478 | AF95: 0.5652547 | AG95: 0.58103561 | AH95: 0.54972055 | AI95: 0.54153966 | AJ95: 0.55036312 | AK95: 0.53604525 | AL95: 0.53955089 | AM95: 0.5492738 | AN95: 0.54985355 | AO95: 0.5608366 | AP95: 0.57889974 | AQ95: 0.50108375 | AR95: 0.52816549 | AS95: 0.51001029 | AT95: 0.50584067 | AU95: 0.50468519
A96: INTL.4419-2-AUT-QBTU.A | B96: Nuclear, renewables, and other (quad Btu) | C96: 0.11529584 | D96: 0.11851777 | E96: 0.11762633 | F96: 0.12013313 | G96: 0.13144779 | H96: 0.14332096 | I96: 0.13422713 | J96: 0.10063845 | K96: 0.14633188 | L96: 0.14514507 | M96: 0.14058537 | N96: 0.1475816 | O96: 0.15337804 | P96: 0.15265115 | Q96: 0.14831859 | R96: 0.15719502 | S96: 0.1563057 | T96: 0.16027431 | U96: 0.16320426 | V96: 0.16805487 | W96: 0.1820434 | X96: 0.18871133 | Y96: 0.18736843 | Z96: 0.18608073 | AA96: 0.1977936 | AB96: 0.20659438 | AC96: 0.22328299 | AD96: 0.24011729 | AE96: 0.24070599 | AF96: 0.21869825 | AG96: 0.22528496 | AH96: 0.22802552 | AI96: 0.24680833 | AJ96: 0.26105734 | AK96: 0.26189727 | AL96: 0.25141521 | AM96: 0.25154093 | AN96: 0.25709437 | AO96: 0.25147755 | AP96: 0.2541194 | AQ96: 0.2516598 | AR96: 0.26841021 | AS96: 0.25619057 | AT96: 0.25016083 | AU96: 0.24730142
A97: INTL.4417-2-AUT-QBTU.A | B97: Nuclear (quad Btu) | C97: 0 | D97: 0 | E97: 0 | F97: 0 | G97: 0 | H97: 0 | I97: 0 | J97: 0 | K97: 0 | L97: 0 | M97: 0 | N97: 0 | O97: 0 | P97: 0 | Q97: 0 | R97: 0 | S97: 0 | T97: 0 | U97: 0 | V97: 0 | W97: 0 | X97: 0 | Y97: 0 | Z97: 0 | AA97: 0 | AB97: 0 | AC97: 0 | AD97: 0 | AE97: 0 | AF97: 0 | AG97: 0 | AH97: 0 | AI97: 0 | AJ97: 0 | AK97: 0 | AL97: 0 | AM97: 0 | AN97: 0 | AO97: 0 | AP97: 0 | AQ97: 0 | AR97: 0 | AS97: 0 | AT97: 0 | AU97: 0
A98: INTL.4418-2-AUT-QBTU.A | B98: Renewables and other (quad Btu) | C98: 0.11529584 | D98: 0.11851777 | E98: 0.11762633 | F98: 0.12013313 | G98: 0.13144779 | H98: 0.14332096 | I98: 0.13422713 | J98: 0.10063845 | K98: 0.14633188 | L98: 0.14514507 | M98: 0.14058537 | N98: 0.1475816 | O98: 0.15337804 | P98: 0.15265115 | Q98: 0.14831859 | R98: 0.15719502 | S98: 0.1563057 | T98: 0.16027431 | U98: 0.16320426 | V98: 0.16805487 | W98: 0.1820434 | X98: 0.18871133 | Y98: 0.18736843 | Z98: 0.18608073 | AA98: 0.1977936 | AB98: 0.20659438 | AC98: 0.22328299 | AD98: 0.24011729 | AE98: 0.24070599 | AF98: 0.21869825 | AG98: 0.22528496 | AH98: 0.22802552 | AI98: 0.24680833 | AJ98: 0.26105734 | AK98: 0.26189727 | AL98: 0.25141521 | AM98: 0.25154093 | AN98: 0.25709437 | AO98: 0.25147755 | AP98: 0.2541194 | AQ98: 0.2516598 | AR98: 0.26841021 | AS98: 0.25619057 | AT98: 0.25016083 | AU98: 0.24730142
B99: Azerbaijan
A100: INTL.44-2-AZE-QBTU.A | B100: Consumption (quad Btu) | C100: -- | D100: -- | E100: -- | F100: -- | G100: -- | H100: -- | I100: -- | J100: -- | K100: -- | L100: -- | M100: -- | N100: -- | O100: 0.97918791 | P100: 0.82740467 | Q100: 0.74682613 | R100: 0.71745753 | S100: 0.63269607 | T100: 0.62683729 | U100: 0.53339575 | V100: 0.55353809 | W100: 0.49701073 | X100: 0.43823579 | Y100: 0.5182504 | Z100: 0.55087239 | AA100: 0.60801264 | AB100: 0.62853819 | AC100: 0.64061411 | AD100: 0.52581902 | AE100: 0.56511686 | AF100: 0.52917446 | AG100: 0.56501347 | AH100: 0.5387556 | AI100: 0.59225513 | AJ100: 0.55782255 | AK100: 0.57630812 | AL100: 0.60783355 | AM100: 0.59652447 | AN100: 0.59548732 | AO100: 0.5971819 | AP100: 0.62355844 | AQ100: 0.60940881 | AR100: 0.67950554 | AS100: 0.72255879 | AT100: 0.74957011 | AU100: 0.65287564
...

Sheet Emissions
A1: Country | B1: Code | C1: Year | D1: Annual_CO2_emissions_In_Tonnes
A2: Afghanistan | B2: AFG | C2: 1949 | D2: 14656
A3: Afghanistan | B3: AFG | C3: 1950 | D3: 84272
A4: Afghanistan | B4: AFG | C4: 1951 | D4: 91600
A5: Afghanistan | B5: AFG | C5: 1952 | D5: 91600
A6: Afghanistan | B6: AFG | C6: 1953 | D6: 106256
A7: Afghanistan | B7: AFG | C7: 1954 | D7: 106256
A8: Afghanistan | B8: AFG | C8: 1955 | D8: 153888
A9: Afghanistan | B9: AFG | C9: 1956 | D9: 183200
A10: Afghanistan | B10: AFG | C10: 1957 | D10: 293120
A11: Afghanistan | B11: AFG | C11: 1958 | D11: 329760
A12: Afghanistan | B12: AFG | C12: 1959 | D12: 384571
A13: Afghanistan | B13: AFG | C13: 1960 | D13: 413885
... A218: Africa | B218: OWID_AFR | C218: 2024 | D218: 1502098700
A219: Africa (GCP) | C219: 1850 | D219: 0
A220: Africa (GCP) | C220: 1851 | D220: 0
A221: Africa (GCP) | C221: 1852 | D221: 0
A222: Africa (GCP) | C222: 1853 | D222: 0
A223: Africa (GCP) | C223: 1854 | D223: 0
A224: Africa (GCP) | C224: 1855 | D224: 0
A225: Africa (GCP) | C225: 1856 | D225: 0
A226: Africa (GCP) | C226: 1857 | D226: 0
A227: Africa (GCP) | C227: 1858 | D227: 0
A228: Africa (GCP) | C228: 1859 | D228: 0
A229: Africa (GCP) | C229: 1860 | D229: 0
A230: Africa (GCP) | C230: 1861 | D230: 0
... A393: Africa (GCP) | C393: 2024 | D393: 1502087400
A394: Albania | B394: ALB | C394: 1933 | D394: 7328
A395: Albania | B395: ALB | C395: 1934 | D395: 7328
A396: Albania | B396: ALB | C396: 1935 | D396: 18320
A397: Albania | B397: ALB | C397: 1936 | D397: 128209.99
A398: Albania | B398: ALB | C398: 1937 | D398: 296725
A399: Albania | B399: ALB | C399: 1938 | D399: 348080
A400: Albania | B400: ALB | C400: 1939 | D400: 432352
A401: Albania | B401: ALB | C401: 1940 | D401: 692496
A402: Albania | B402: ALB | C402: 1941 | D402: 626485
A403: Albania | B403: ALB | C403: 1942 | D403: 743792
A404: Albania | B404: ALB | C404: 1943 | D404: 461664
A405: Albania | B405: ALB | C405: 1944 | D405: 153888
... A1568: Asia | B1568: OWID_ASI | C1568: 2024 | D1568: 23392487000
A1569: Asia (GCP) | C1569: 1850 | D1569: 14658.506
A1570: Asia (GCP) | C1570: 1851 | D1570: 0
A1571: Asia (GCP) | C1571: 1852 | D1571: 0
A1572: Asia (GCP) | C1572: 1853 | D1572: 0
A1573: Asia (GCP) | C1573: 1854 | D1573: 0
A1574: Asia (GCP) | C1574: 1855 | D1574: 44448.37
A1575: Asia (GCP) | C1575: 1856 | D1575: 0
A1576: Asia (GCP) | C1576: 1857 | D1576: 0
A1577: Asia (GCP) | C1577: 1858 | D1577: 456898.16
A1578: Asia (GCP) | C1578: 1859 | D1578: 702673.75
A1579: Asia (GCP) | C1579: 1860 | D1579: 730582.1
A1580: Asia (GCP) | C1580: 1861 | D1580: 608366.25
... A2018: Asia (excl. China and India) | C2018: 2024 | D2018: 7909973000
A2019: Australia | B2019: AUS | C2019: 1750 | D2019: 0
A2020: Australia | B2020: AUS | C2020: 1751 | D2020: 0
A2021: Australia | B2021: AUS | C2021: 1752 | D2021: 0
A2022: Australia | B2022: AUS | C2022: 1753 | D2022: 0
A2023: Australia | B2023: AUS | C2023: 1754 | D2023: 0
A2024: Australia | B2024: AUS | C2024: 1755 | D2024: 0
A2025: Australia | B2025: AUS | C2025: 1756 | D2025: 0
A2026: Australia | B2026: AUS | C2026: 1757 | D2026: 0
A2027: Australia | B2027: AUS | C2027: 1758 | D2027: 0
A2028: Australia | B2028: AUS | C2028: 1759 | D2028: 0
A2029: Australia | B2029: AUS | C2029: 1760 | D2029: 0
A2030: Australia | B2030: AUS | C2030: 1761 | D2030: 0
... A5224: Central African Republic | B5224: CAF | C5224: 2024 | D5224: 394681
A5225: Central America (GCP) | C5225: 1850 | D5225: 0
A5226: Central America (GCP) | C5226: 1851 | D5226: 0
A5227: Central America (GCP) | C5227: 1852 | D5227: 0
A5228: Central America (GCP) | C5228: 1853 | D5228: 0
A5229: Central America (GCP) | C5229: 1854 | D5229: 0
A5230: Central America (GCP) | C5230: 1855 | D5230: 0
A5231: Central America (GCP) | C5231: 1856 | D5231: 384519.94
A5232: Central America (GCP) | C5232: 1857 | D5232: 360731.44
A5233: Central America (GCP) | C5233: 1858 | D5233: 338412.53
A5234: Central America (GCP) | C5234: 1859 | D5234: 317476.06
A5235: Central America (GCP) | C5235: 1860 | D5235: 297834.84
A5236: Central America (GCP) | C5236: 1861 | D5236: 442156.12
... A5399: Central America (GCP) | C5399: 2024 | D5399: 185165940
A5400: Chad | B5400: TCD | C5400: 1950 | D5400: 29602
A5401: Chad | B5401: TCD | C5401: 1951 | D5401: 39470
A5402: Chad | B5402: TCD | C5402: 1952 | D5402: 51187
A5403: Chad | B5403: TCD | C5403: 1953 | D5403: 43170
A5404: Chad | B5404: TCD | C5404: 1954 | D5404: 45637
A5405: Chad | B5405: TCD | C5405: 1955 | D5405: 45020
A5406: Chad | B5406: TCD | C5406: 1956 | D5406: 58588
A5407: Chad | B5407: TCD | C5407: 1957 | D5407: 62905
A5408: Chad | B5408: TCD | C5408: 1958 | D5408: 72155
A5409: Chad | B5409: TCD | C5409: 1959 | D5409: 62288
A5410: Chad | B5410: TCD | C5410: 1960 | D5410: 54960
A5411: Chad | B5411: TCD | C5411: 1961 | D5411: 51296
... A8788: Europe | B8788: OWID_EUR | C8788: 2024 | D8788: 4880514000
A8789: Europe (GCP) | C8789: 1850 | D8789: 176775220
A8790: Europe (GCP) | C8790: 1851 | D8790: 173859020
A8791: Europe (GCP) | C8791: 1852 | D8791: 180432720
A8792: Europe (GCP) | C8792: 1853 | D8792: 186703470
A8793: Europe (GCP) | C8793: 1854 | D8793: 221565870
A8794: Europe (GCP) | C8794: 1855 | D8794: 221538050
A8795: Europe (GCP) | C8795: 1856 | D8795: 236781500
A8796: Europe (GCP) | C8796: 1857 | D8796: 238329630
...

Sheet Calculations
A1: KPIS TABLE
A2: Countries / Economies Analysed | B2: =COUNTA(qry_Master_Clean__2[Country]) -> 212
A3: Average GDP per Capita | B3: =_xlfn.AGGREGATE(1,6,qry_Master_Clean__2[GDP per Capita (US$)]) -> 19447.404
A4: Average CO₂ Emissions per Capita | B4: =_xlfn.AGGREGATE(1,6,qry_Master_Clean__2[Emissions Per Capita (tonnes per person)]) -> 3.7043236 | C4: =_xlfn.AGGREGATE(1,6,qry_Master_Clean__2[Emissions Per Capita (tonnes per person)]) -> 3.7043236
A5: Average Renewable Energy Share | B5: =AVERAGE(qry_Master_Clean__2[Renewalble]) -> 28.632075 | C5: =B5/100 -> 0.28632075

Sheet Renewable
A1: Country Name | B1: Country Code | C1: Indicator Name | D1: Indicator Code | E1: 1960 | F1: 1961 | G1: 1962 | H1: 1963 | I1: 1964 | J1: 1965 | K1: 1966 | L1: 1967 | M1: 1968 | N1: 1969 | O1: 1970 | P1: 1971 | Q1: 1972 | R1: 1973 | S1: 1974 | T1: 1975 | U1: 1976 | V1: 1977 | W1: 1978 | X1: 1979 | Y1: 1980 | Z1: 1981 | AA1: 1982 | AB1: 1983 | AC1: 1984 | AD1: 1985 | AE1: 1986 | AF1: 1987 | AG1: 1988 | AH1: 1989 | AI1: 1990 | AJ1: 1991 | AK1: 1992 | AL1: 1993 | AM1: 1994 | AN1: 1995 | AO1: 1996 | AP1: 1997 | AQ1: 1998 | AR1: 1999 | AS1: 2000 | AT1: 2001 | AU1: 2002 | AV1: 2003 | AW1: 2004 | AX1: 2005 | AY1: 2006 | AZ1: 2007 | BA1: 2008 | BB1: 2009 | BC1: 2010 | BD1: 2011 | BE1: 2012 | BF1: 2013 | BG1: 2014 | BH1: 2015 | BI1: 2016 | BJ1: 2017 | BK1: 2018 | BL1: 2019 | BM1: 2020 | BN1: Renewable 2021
A2: Aruba | B2: ABW | C2: Renewable energy consumption (% of total final energy consumption) | D2: EG.FEC.RNEW.ZS | AI2: 0.3 | AJ2: 0.2 | AK2: 0.2 | AL2: 0.2 | AM2: 0.2 | AN2: 0.2 | AO2: 0.2 | AP2: 0.2 | AQ2: 0.2 | AR2: 0.2 | AS2: 0.2 | AT2: 0.2 | AU2: 0.2 | AV2: 0.2 | AW2: 0.2 | AX2: 0.2 | AY2: 0.2 | AZ2: 0.2 | BA2: 0.2 | BB2: 0.3 | BC2: 5.5 | BD2: 5.7 | BE2: 6.9 | BF2: 6.9 | BG2: 6.9 | BH2: 6.7 | BI2: 7 | BJ2: 6.8 | BK2: 8.6 | BL2: 8.3 | BM2: 9.1 | BN2: 8.8
A3: Africa Eastern and Southern | B3: AFE | C3: Renewable energy consumption (% of total final energy consumption) | D3: EG.FEC.RNEW.ZS | AI3: 60.842404 | AJ3: 62.133295 | AK3: 63.940789 | AL3: 64.651965 | AM3: 65.145067 | AN3: 64.721535 | AO3: 63.929272 | AP3: 63.241293 | AQ3: 63.962096 | AR3: 65.058401 | AS3: 65.385867 | AT3: 65.817363 | AU3: 65.099281 | AV3: 64.615124 | AW3: 63.678035 | AX3: 63.109098 | AY3: 62.738124 | AZ3: 61.505169 | BA3: 61.908027 | BB3: 61.304601 | BC3: 62.876387 | BD3: 62.805279 | BE3: 61.409964 | BF3: 60.801799 | BG3: 61.235882 | BH3: 61.670278 | BI3: 61.822884 | BJ3: 61.42695 | BK3: 61.58753 | BL3: 62.69071 | BM3: 65.78238
A4: Afghanistan | B4: AFG | C4: Renewable energy consumption (% of total final energy consumption) | D4: EG.FEC.RNEW.ZS | AI4: 23 | AJ4: 23.7 | AK4: 27.4 | AL4: 28.5 | AM4: 30.1 | AN4: 31.8 | AO4: 33.9 | AP4: 36.4 | AQ4: 38 | AR4: 43.4 | AS4: 45 | AT4: 45.6 | AU4: 37.8 | AV4: 36.7 | AW4: 44.2 | AX4: 33.9 | AY4: 31.9 | AZ4: 28.8 | BA4: 21.2 | BB4: 16.5 | BC4: 15.2 | BD4: 12.6 | BE4: 15.4 | BF4: 16.9 | BG4: 19.1 | BH4: 17.7 | BI4: 20.2 | BJ4: 19.5 | BK4: 18.3 | BL4: 18.9 | BM4: 18.2 | BN4: 20
A5: Africa Western and Central | B5: AFW | C5: Renewable energy consumption (% of total final energy consumption) | D5: EG.FEC.RNEW.ZS | AI5: 85.895442 | AJ5: 85.262074 | AK5: 83.818324 | AL5: 85.103232 | AM5: 86.557685 | AN5: 86.148094 | AO5: 85.118648 | AP5: 83.911059 | AQ5: 84.634537 | AR5: 84.005039 | AS5: 83.101512 | AT5: 81.939243 | AU5: 81.735528 | AV5: 80.71045 | AW5: 80.790537 | AX5: 80.934034 | AY5: 81.87331 | AZ5: 82.330015 | BA5: 81.21117 | BB5: 82.390213 | BC5: 80.687806 | BD5: 79.282287 | BE5: 78.48123 | BF5: 76.701499 | BG5: 75.741009 | BH5: 76.181671 | BI5: 75.79684 | BJ5: 76.101681 | BK5: 75.476578 | BL5: 75.078788 | BM5: 75.84698
A6: Angola | B6: AGO | C6: Renewable energy consumption (% of total final energy consumption) | D6: EG.FEC.RNEW.ZS | AI6: 72.3 | AJ6: 71.9 | AK6: 72.7 | AL6: 71.3 | AM6: 72.2 | AN6: 73.8 | AO6: 72.9 | AP6: 73.4 | AQ6: 76.4 | AR6: 72.8 | AS6: 73.8 | AT6: 72.8 | AU6: 70.8 | AV6: 65.6 | AW6: 62.3 | AX6: 68.9 | AY6: 62.6 | AZ6: 58.9 | BA6: 55.4 | BB6: 53 | BC6: 53.1 | BD6: 51.7 | BE6: 49 | BF6: 46.8 | BG6: 47.5 | BH6: 47.1 | BI6: 48.1 | BJ6: 52.5 | BK6: 52.5 | BL6: 51 | BM6: 60.1 | BN6: 52.9
A7: Albania | B7: ALB | C7: Renewable energy consumption (% of total final energy consumption) | D7: EG.FEC.RNEW.ZS | AI7: 25.5 | AJ7: 33 | AK7: 46.8 | AL7: 51.1 | AM7: 51.4 | AN7: 50.6 | AO7: 51.6 | AP7: 55.9 | AQ7: 49.9 | AR7: 42.6 | AS7: 41.4 | AT7: 39 | AU7: 35.8 | AV7: 33.7 | AW7: 35.8 | AX7: 36.8 | AY7: 31.6 | AZ7: 32 | BA7: 35.8 | BB7: 37.1 | BC7: 37 | BD7: 35.8 | BE7: 39.9 | BF7: 41.1 | BG7: 38.6 | BH7: 38.5 | BI7: 39.4 | BJ7: 36.9 | BK7: 37.8 | BL7: 40.1 | BM7: 44.4 | BN7: 41.9
A8: Andorra | B8: AND | C8: Renewable energy consumption (% of total final energy consumption) | D8: EG.FEC.RNEW.ZS | AI8: 14.1 | AJ8: 14.1 | AK8: 14.1 | AL8: 13.7 | AM8: 14.4 | AN8: 14.3 | AO8: 13.9 | AP8: 14 | AQ8: 14.2 | AR8: 14.3 | AS8: 14.5 | AT8: 15.4 | AU8: 15.8 | AV8: 16.5 | AW8: 16.6 | AX8: 16.6 | AY8: 17.6 | AZ8: 16.6 | BA8: 17 | BB8: 17.1 | BC8: 18.7 | BD8: 18.6 | BE8: 18.8 | BF8: 19.1 | BG8: 19.4 | BH8: 19 | BI8: 18.9 | BJ8: 18 | BK8: 17.6 | BL8: 17.2 | BM8: 20.9 | BN8: 18.4
A9: Arab World | B9: ARB | C9: Renewable energy consumption (% of total final energy consumption) | D9: EG.FEC.RNEW.ZS | AI9: 7.5567525 | AJ9: 7.481365 | AK9: 7.1300832 | AL9: 6.8817629 | AM9: 7.0401037 | AN9: 6.9182767 | AO9: 6.9793272 | AP9: 7.0052482 | AQ9: 6.8554305 | AR9: 6.8423746 | AS9: 6.6862092 | AT9: 6.5159874 | AU9: 6.3598823 | AV9: 6.4659549 | AW9: 6.7411835 | AX9: 6.4044867 | AY9: 6.1956471 | AZ9: 5.6000458 | BA9: 5.1313087 | BB9: 5.0552224 | BC9: 4.8356216 | BD9: 4.6594628 | BE9: 4.4442822 | BF9: 4.4832374 | BG9: 4.3513725 | BH9: 4.2149694 | BI9: 4.2907776 | BJ9: 4.3581618 | BK9: 4.5042582 | BL9: 4.7063316 | BM9: 5.1706007
A10: United Arab Emirates | B10: ARE | C10: Renewable energy consumption (% of total final energy consumption) | D10: EG.FEC.RNEW.ZS | AI10: 0 | AJ10: 0 | AK10: 0.2 | AL10: 0.1 | AM10: 0.1 | AN10: 0.1 | AO10: 0.1 | AP10: 0.1 | AQ10: 0.1 | AR10: 0.1 | AS10: 0.1 | AT10: 0.1 | AU10: 0.1 | AV10: 0.1 | AW10: 0.1 | AX10: 0.1 | AY10: 0.1 | AZ10: 0.1 | BA10: 0.1 | BB10: 0.1 | BC10: 0.1 | BD10: 0.1 | BE10: 0.1 | BF10: 0.1 | BG10: 0.1 | BH10: 0.1 | BI10: 0.1 | BJ10: 0.2 | BK10: 0.3 | BL10: 0.7 | BM10: 0.9 | BN10: 1
A11: Argentina | B11: ARG | C11: Renewable energy consumption (% of total final energy consumption) | D11: EG.FEC.RNEW.ZS | AI11: 8.6 | AJ11: 8.4 | AK11: 9 | AL11: 9.7 | AM11: 10 | AN11: 10.2 | AO11: 8.6 | AP11: 9.7 | AQ11: 9.6 | AR11: 8.8 | AS11: 9.8 | AT11: 11.5 | AU11: 11.6 | AV11: 10.8 | AW11: 9.3 | AX11: 9.6 | AY11: 9.2 | AZ11: 7.7 | BA11: 7.7 | BB11: 8.6 | BC11: 8.8 | BD11: 8.8 | BE11: 8.6 | BF11: 8.9 | BG11: 9.8 | BH11: 9.4 | BI11: 9.4 | BJ11: 10.4 | BK11: 10.5 | BL11: 10.7 | BM11: 9.8 | BN11: 9.2
A12: Armenia | B12: ARM | C12: Renewable energy consumption (% of total final energy consumption) | D12: EG.FEC.RNEW.ZS | AI12: 2.1 | AJ12: 2.3 | AK12: 6.7 | AL12: 12.9 | AM12: 17.8 | AN12: 9.3 | AO12: 12.5 | AP12: 10.1 | AQ12: 9.4 | AR12: 8.4 | AS12: 7.2 | AT12: 5.4 | AU12: 8.9 | AV12: 9.8 | AW12: 8.7 | AX12: 6.5 | AY12: 7.7 | AZ12: 7 | BA12: 6.4 | BB12: 7.8 | BC12: 9.4 | BD12: 8 | BE12: 6.6 | BF12: 6.8 | BG12: 7.1 | BH12: 10.7 | BI12: 13.2 | BJ12: 12.6 | BK12: 11.1 | BL12: 10.3 | BM12: 8.4 | BN12: 9.1
A13: American Samoa | B13: ASM | C13: Renewable energy consumption (% of total final energy consumption) | D13: EG.FEC.RNEW.ZS | AI13: 0 | AJ13: 0 | AK13: 0 | AL13: 0 | AM13: 0 | AN13: 0 | AO13: 0 | AP13: 0 | AQ13: 0 | AR13: 0 | AS13: 0 | AT13: 0 | AU13: 0 | AV13: 0 | AW13: 0 | AX13: 0 | AY13: 0 | AZ13: 0 | BA13: 0 | BB13: 0 | BC13: 0 | BD13: 0 | BE13: 0.1 | BF13: 0.2 | BG13: 0.2 | BH13: 0.2 | BI13: 0.2 | BJ13: 0.3 | BK13: 0.3 | BL13: 0.4 | BM13: 0.4 | BN13: 0.4
A14: Antigua and Barbuda | B14: ATG | C14: Renewable energy consumption (% of total final energy consumption) | D14: EG.FEC.RNEW.ZS | AI14: 0 | AJ14: 0 | AK14: 0 | AL14: 0 | AM14: 0 | AN14: 0 | AO14: 0 | AP14: 0 | AQ14: 0 | AR14: 0 | AS14: 0 | AT14: 0 | AU14: 0 | AV14: 0 | AW14: 0 | AX14: 0 | AY14: 0 | AZ14: 0 | BA14: 0 | BB14: 0 | BC14: 0 | BD14: 0.1 | BE14: 0.1 | BF14: 0.1 | BG14: 0.1 | BH14: 0.4 | BI14: 0.4 | BJ14: 0.4 | BK14: 0.7 | BL14: 0.7 | BM14: 0.9 | BN14: 0.9
A15: Australia | B15: AUS | C15: Renewable energy consumption (% of total final energy consumption) | D15: EG.FEC.RNEW.ZS | AI15: 8 | AJ15: 8.2 | AK15: 7.5 | AL15: 8.6 | AM15: 8.3 | AN15: 8.2 | AO15: 8.9 | AP15: 9.1 | AQ15: 8.6 | AR15: 8.5 | AS15: 8.4 | AT15: 8.4 | AU15: 8.7 | AV15: 7.2 | AW15: 6.7 | AX15: 6.7 | AY15: 6.8 | AZ15: 7 | BA15: 6.8 | BB15: 7.1 | BC15: 8.2 | BD15: 8.3 | BE15: 8.3 | BF15: 9.2 | BG15: 9.3 | BH15: 9.4 | BI15: 9.6 | BJ15: 9.9 | BK15: 9.8 | BL15: 10.3 | BM15: 11.2 | BN15: 12.3
A16: Austria | B16: AUT | C16: Renewable energy consumption (% of total final energy consumption) | D16: EG.FEC.RNEW.ZS | AI16: 25.2 | AJ16: 24.5 | AK16: 26.2 | AL16: 26.4 | AM16: 25.7 | AN16: 25.7 | AO16: 24.1 | AP16: 24.9 | AQ16: 24.5 | AR16: 26.5 | AS16: 26.4 | AT16: 25.5 | AU16: 24.7 | AV16: 22.6 | AW16: 23.2 | AX16: 24.4 | AY16: 26.6 | AZ16: 29 | BA16: 29.7 | BB16: 31.3 | BC16: 31.1 | BD16: 31.6 | BE16: 34.4 | BF16: 34.6 | BG16: 35.7 | BH16: 34.8 | BI16: 34.6 | BJ16: 34 | BK16: 34.1 | BL16: 34 | BM16: 35.8 | BN16: 36
A17: Azerbaijan | B17: AZE | C17: Renewable energy consumption (% of total final energy consumption) | D17: EG.FEC.RNEW.ZS | AI17: 0.7 | AJ17: 0.8 | AK17: 1.2 | AL17: 2 | AM17: 1.5 | AN17: 1.4 | AO17: 1.7 | AP17: 2 | AQ17: 2.5 | AR17: 2.1 | AS17: 2.1 | AT17: 1.8 | AU17: 2.4 | AV17: 2.9 | AW17: 3.1 | AX17: 3.4 | AY17: 2.9 | AZ17: 3.8 | BA17: 3.1 | BB17: 3.3 | BC17: 4.4 | BD17: 3.5 | BE17: 2.8 | BF17: 2.5 | BG17: 2.1 | BH17: 2.3 | BI17: 1.9 | BJ17: 1.9 | BK17: 1.9 | BL17: 1.7 | BM17: 1.3 | BN17: 1.3
A18: Burundi | B18: BDI | C18: Renewable energy consumption (% of total final energy consumption) | D18: EG.FEC.RNEW.ZS | AI18: 94.6 | AJ18: 93.5 | AK18: 94.3 | AL18: 94 | AM18: 93.9 | AN18: 93.7 | AO18: 93.5 | AP18: 93.4 | AQ18: 93.2 | AR18: 93.8 | AS18: 93.2 | AT18: 94.7 | AU18: 94.6 | AV18: 95.8 | AW18: 96 | AX18: 96 | AY18: 95.3 | AZ18: 95.3 | BA18: 95 | BB18: 94.6 | BC18: 93.2 | BD18: 92.1 | BE18: 91.7 | BF18: 90.8 | BG18: 91.3 | BH18: 91.2 | BI18: 89.6 | BJ18: 88.2 | BK18: 85.7 | BL18: 84.8 | BM18: 83.4 | BN18: 83.1
A19: Belgium | B19: BEL | C19: Renewable energy consumption (% of total final energy consumption) | D19: EG.FEC.RNEW.ZS | AI19: 1.3 | AJ19: 1.2 | AK19: 1.2 | AL19: 1 | AM19: 0.9 | AN19: 1.3 | AO19: 1.2 | AP19: 1.1 | AQ19: 1.3 | AR19: 1.4 | AS19: 1.4 | AT19: 1.6 | AU19: 1.7 | AV19: 1.9 | AW19: 2 | AX19: 2.5 | AY19: 2.9 | AZ19: 3.4 | BA19: 4 | BB19: 4.9 | BC19: 6.2 | BD19: 6.7 | BE19: 7.7 | BF19: 8.3 | BG19: 9.1 | BH19: 9.4 | BI19: 9.2 | BJ19: 9.7 | BK19: 10.7 | BL19: 10.2 | BM19: 12.3 | BN19: 11.7
